Workbook
Name _xlchart.v1.0: #REF!
Name _xlchart.v1.1: 'Copia di Tour List'!$BA$5:$BA$45
Name _xlchart.v1.1: #REF!
Name _xlchart.v1.0: 'Copia di Tour List'!$BA$3

Sheet Pricing
A1: NCC Pricing Calculator - v.1.9 | N1: Release date | O1: 46041
A2: SERVICE DETAILS | B2: Personalizza dati | C2: Dati utilizzati | D2: Dati Default
A3: Destinazione | B3: Chianti Classico - TOUR FD
A4: Tipo | B4: TOUR FD | C4: =IF(B4="- - - - -",D4,B4) -> TOUR FD | D4: =VLOOKUP(B3,'Tour List'!A2:K52,3,0) -> TOUR FD
A5: Kilometraggio | C5: =IF(B5="",D5,B5) -> 250 | D5: =VLOOKUP(B3,'Tour List'!A2:K43,5,0) -> 250
A6: Extra Km se non si parte/arriva da Siena | C6: =B6
A7: Durata del servizio (ore) | C7: =IF(B7="",D7,B7) -> 8 | D7: =VLOOKUP(B3,'Tour List'!A2:K43,4,0) -> 8
A8: Estensione del servizio, con cliente (ore) | C8: =IF(B8="",D8,B8)
A9: Ore di spostamento se non si parte/arriva da Siena | C9: =IF(B9="",D9,B9)
A10: Toll € | C10: =IF(B10="",D10,B10) -> 0 | D10: =VLOOKUP(B3,'Tour List'!A2:K43,6,0) -> 0
A11: Pax (relativo solo alle esperienze) | B11: 2 | C11: =B11 -> 2
A12: Esperienze (p.p.) solo se presenti | C12: =IF(B12="",D12,B12) -> 70 | D12: =VLOOKUP(B3,'Tour List'!A2:K43,11,0) -> 70
A13: PRICING POLICIES
A14: Stagionalità | B14: Low | C14: =B14 -> Low
A15: Riempimento | B15: Car (2pax) | C15: =B15 -> Car (2pax)
A16: VAT | B16: 0.1 | C16: =B16 -> 0.1
A17: Card Fees | B17: 0.05 | C17: =B17 -> 0.05
A18: Maggiorazioni (notturno, festivo) | B18: 0 | C18: =B18 -> 0
A19: Costi trasferta € | B19: 0 | C19: =B19 -> 0
A21: PRICE
A22: Taxable transport | B22: {=INDEX('Pricing Calculator'!E2:H6,MATCH(B14,'Pricing Calculator'!E2:E6,0),MATCH(B15,'Pricing Calculator'!E3:H3,0))} -> 433.9574
A23: Taxable experience | B23: {=INDEX('Pricing Calculator'!E10:H14,MATCH(B14,'Pricing Calculator'!E10:E14,0),MATCH(B15,'Pricing Calculator'!E10:H10,0))} -> 147
A24: Maggiorazione | B24: =(B22+B23)*B18 -> 0
A25: Costi trasferta € | B25: =B19 -> 0
A26: Taxable Price | B26: =B22+B23+B24+B25 -> 580.9574 | C26: =CEILING(B26,5) -> 585
A27: =CONCATENATE("VAT (",(B16*100),"%)") -> VAT (10%) | B27: =B26*B16 -> 58.09574 | C27: =CEILING(D27,5) -> 645 | D27: =C26+B27 -> 643.09574
A28: =CONCATENATE("CC fees (",(B17*100),"%)") -> CC fees (5%) | B28: =(B26+B27)*B17 -> 31.952657
A29: FINAL PRICE | B29: =B26+B27+B28 -> 671.00579 | C29: =CEILING(B29,5) -> 675

Sheet Preventivi
A1: USER | B1: DATE | C1: CLIENTE | D1: URL | E1: DESTINAZIONE | F1: TIPO | G1: MILEAGE | H1: EXTRA_KM | I1: DURATA | J1: EXTRA DURATA | K1: PEDAGGIO | L1: PAX (ESPERIENZE) | M1: EXP PER PAX | N1: STAGIONE | O1: RIEMPIMENTO | P1: VAT % | Q1: CARD FEES % | R1: MAGGIORAZIONI | S1: TRASFERTA | T1: IMPONIBILE | U1: VAT € | V1: CC FEES € | W1: PREZZO FINALE | X1: PREZZO CLIENTE | Y1: % SCONTO | Z1: SCONTP € | AA1: DEPOSITO % | AB1: DEPOSITO IMPONIBILE | AC1: DEPOSITO FULL | AD1: SALDO IMPONIBILE | AE1: SALDO BANCA | AF1: SALDO CC
A2: michelamenegon@gmail.com | B2: 27 December 2025 | C2: Ying Goh | D2: https://docs.google.com/document/d/1Ux04QH-POEJAv-hxb3j95oA3h9n8WKv9MJtxXn0ebtE/edit?usp=drivesdk | F2: TOUR FD+ | G2: 750 | H2: 75 | I2: 11 | J2: 1 | K2: 30 | M2: 0 | N2: Average | O2: Van (3-6 pax) | P2: 0.1 | Q2: 0.05 | R2: 0 | S2: 0 | T2: 1050 | U2: 104.9649 | V2: 57.730693 | W2: 1215 | X2: 1155 | Y2: 0.1 | Z2: 1050 | AA2: 0.3 | AB2: 315 | AC2: 365 | AD2: 735 | AE2: 810 | AF2: 850
A3: michelamenegon@gmail.com | B3: 27 December 2025 | C3: Ying Goh | D3: https://docs.google.com/document/d/1q0FuAuMEE6HYeVTbUiYiI4EQedN6oX7q8zDc-pcnlT8/edit?usp=drivesdk | F3: TOUR FD+ | G3: 750 | H3: 75 | I3: 11 | J3: 1 | K3: 30 | M3: 0 | N3: Average | O3: Van (3-6 pax) | P3: 0.1 | Q3: 0.05 | R3: 0 | S3: 0 | T3: 1050 | U3: 104.9649 | V3: 57.730693 | W3: 1215 | X3: 1155 | Y3: 0.1 | Z3: 1050 | AA3: 0.3 | AB3: 315 | AC3: 365 | AD3: 735 | AE3: 810 | AF3: 850
A4: michelamenegon@gmail.com | B4: 28 December 2025 | C4: Cliente Argiano 29/12/25 | D4: https://docs.google.com/document/d/1RGpvI1GW4-sqj5h_f1y2EwakEbhIjrpGtCmL9zMiFPs/edit?usp=drivesdk | F4: TOUR FD+ | G4: 350 | H4: 250 | I4: 12 | J4: 4 | K4: 20 | M4: 0 | N4: Low | O4: Full (7-8 pax) | P4: 0.1 | Q4: 0.05 | R4: 0 | S4: 0 | T4: 1005 | U4: 100.1002 | V4: 55.055108 | W4: 1160 | X4: 1110 | Y4: 0 | Z4: 1110 | AA4: 0.3 | AB4: 335 | AC4: 390 | AD4: 810 | AE4: 890 | AF4: 935
A5: michelamenegon@gmail.com | B5: 28 December 2025 | C5: Julia Guest | D5: https://docs.google.com/document/d/1iA16qTkmkjjvfHaj-o93aGIx5qJlH1VgVYsW8cSI1VE/edit?usp=drivesdk | F5: TRF | G5: 500 | H5: 90 | I5: 6 | J5: 1 | K5: 27 | M5: 0 | N5: High | O5: Car (2pax) | P5: 0.1 | Q5: 0.05 | R5: 0 | S5: 0 | T5: 615 | U5: 61.172754 | V5: 33.645015 | W5: 710 | X5: 680 | Y5: 0.1 | Z5: 620 | AA5: 0.3 | AB5: 190 | AC5: 220 | AD5: 440 | AE5: 480 | AF5: 505
A6: michelamenegon@gmail.com | B6: 28 December 2025 | C6: Ying Goh | D6: https://docs.google.com/document/d/1S4-slFR-Ebpu_LRa3sWrLp3NJ-mvyQY8VY6tioiOJvc/edit?usp=drivesdk | F6: TOUR FD | G6: 250 | H6: 140 | I6: 10 | J6: 3 | K6: 0 | M6: 0 | N6: Average | O6: Van (3-6 pax) | P6: 0.1 | Q6: 0.05 | R6: 0 | S6: 0 | T6: 740 | U6: 73.834785 | V6: 40.609132 | W6: 855 | X6: 815 | Y6: 0.1 | Z6: 745 | AA6: 0.3 | AB6: 225 | AC6: 260 | AD6: 525 | AE6: 580 | AF6: 605
A7: michelamenegon@gmail.com | B7: 29 December 2025 | C7: Tina Benton | D7: https://docs.google.com/document/d/1CkTZU-UbISqKAYc0hACPHnbE8KHroVRAOa6x2v5dHNA/edit?usp=drivesdk | F7: TOUR FD | G7: 250 | H7: 80 | I7: 8 | J7: 2 | K7: 0 | M7: 0 | N7: High | O7: Van (3-6 pax) | P7: 0.1 | Q7: 0.05 | R7: 0 | S7: 0 | T7: 685 | U7: 68.15959 | V7: 37.487774 | W7: 790 | X7: 755 | Y7: 0.1 | Z7: 690 | AA7: 0.3 | AB7: 210 | AC7: 245 | AD7: 485 | AE7: 535 | AF7: 560
A8: michelamenegon@gmail.com | B8: 29 December 2025 | C8: Vilena Tjurina | D8: https://docs.google.com/document/d/1sx7zVJ8b58Jf3-o24PjRwoyKm2_RuWOYEthAJ19jkpM/edit?usp=drivesdk | F8: TOUR FD | G8: 250 | H8: 60 | I8: 8 | J8: 1 | K8: 0 | M8: 0 | N8: Low | O8: Van (3-6 pax) | P8: 0.1 | Q8: 0.05 | R8: 0 | S8: 0 | T8: 545 | U8: 54.366754 | V8: 29.901715 | W8: 630 | X8: 600 | Z8: 600 | AA8: 0.3 | AB8: 180 | AC8: 210 | AD8: 440 | AE8: 485 | AF8: 505
A9: michelamenegon@gmail.com | B9: 29 December 2025 | C9: Vilena Tjurina | D9: https://docs.google.com/document/d/1jUDIKng0eiTwTryp9EK9pQMEcxi-WjA0Azj1wP94rYc/edit?usp=drivesdk | F9: TOUR FD | G9: 250 | H9: 60 | I9: 8 | J9: 1 | K9: 0 | M9: 0 | N9: Low | O9: Van (3-6 pax) | P9: 0.1 | Q9: 0.05 | R9: 0 | S9: 0 | T9: 545 | U9: 54.366754 | V9: 29.901715 | W9: 630 | X9: 600 | Z9: 600 | AA9: 0.3 | AB9: 180 | AC9: 210 | AD9: 440 | AE9: 485 | AF9: 505
A10: michelamenegon@gmail.com | B10: 30 December 2025 | C10: Cliente Athena ?? | D10: https://docs.google.com/document/d/1Cn7x0-NlgoSpyQjgedYwgLnUWJjfGBJ0HoSy4us4D9g/edit?usp=drivesdk | F10: TRF | G10: 150 | I10: 3 | K10: 0 | M10: 0 | N10: High | O10: Van (3-6 pax) | P10: 0.1 | Q10: 0.05 | R10: 0 | S10: 0 | T10: 235 | U10: 23.099859 | V10: 12.704922 | W10: 270 | X10: 260 | Y10: 0.1 | Z10: 240 | AA10: 0.3 | AB10: 75 | AC10: 90 | AD10: 170 | AE10: 190 | AF10: 200
A11: michelamenegon@gmail.com | B11: 30 December 2025 | C11: Vilena Tjurina | D11: https://docs.google.com/document/d/1HgrHJl9zE0qWfFUcOOBGptsSO4wrGgiNNDvjuoWCx2o/edit?usp=drivesdk | F11: TOUR HD | G11: 150 | H11: 60 | I11: 5 | J11: 1 | K11: 0 | M11: 0 | N11: Low | O11: Van (3-6 pax) | P11: 0.1 | Q11: 0.05 | R11: 0 | S11: 0 | T11: 370 | U11: 36.806196 | V11: 20.243408 | W11: 430 | X11: 260 | Z11: 260 | AA11: 0.3 | AB11: 80 | AC11: 95 | AD11: 150 | AE11: 165 | AF11: 175
A12: michelamenegon@gmail.com | B12: 30 December 2025 | C12: Vilena Tjurina | D12: https://docs.google.com/document/d/1eXSLJ3db5H-qixd9hc5aDCnzI0JlbPoy-FoB3KvdvMU/edit?usp=drivesdk | F12: TOUR FD | G12: 200 | H12: 60 | I12: 7 | J12: 1 | K12: 0 | M12: 0 | N12: Low | O12: Van (3-6 pax) | P12: 0.1 | Q12: 0.05 | R12: 0 | S12: 0 | T12: 475 | U12: 47.190712 | V12: 25.954891 | W12: 550 | X12: 260 | Z12: 260 | AA12: 0.3 | AB12: 80 | AC12: 95 | AD12: 120 | AE12: 130 | AF12: 140
A13: michelamenegon@gmail.com | B13: 30 December 2025 | C13: Vilena Tjurina | D13: https://docs.google.com/document/d/1Hn_4YKUIkEaY-YafIbHU_biHQbv0eSJWhlORRoxGooY/edit?usp=drivesdk | F13: TOUR FD | G13: 200 | H13: 60 | I13: 7 | J13: 1 | K13: 0 | M13: 0 | N13: Low | O13: Van (3-6 pax) | P13: 0.1 | Q13: 0.05 | R13: 0 | S13: 0 | T13: 475 | U13: 47.190712 | V13: 25.954891 | W13: 550 | X13: 525 | Z13: 525 | AA13: 0.3 | AB13: 160 | AC13: 185 | AD13: 385 | AE13: 425 | AF13: 445
A14: michelamenegon@gmail.com | B14: 31 December 2025 | C14: Wilson Brazil | D14: https://docs.google.com/document/d/16uqc7Up-sLiT7DGiFcMnRMhDxau1EmvQz0QkYS2JplA/edit?usp=drivesdk | F14: TOUR FD+ | G14: 300 | I14: 11 | K14: 0 | M14: 0 | N14: Average | O14: Car (2pax) | P14: 0.1 | Q14: 0.05 | R14: 0 | S14: 0 | T14: 605 | U14: 60.101324 | V14: 33.055728 | W14: 695 | X14: 670 | Y14: 0.1 | Z14: 610 | AA14: 0.3 | AB14: 185 | AC14: 215 | AD14: 430 | AE14: 475 | AF14: 495
A15: michelamenegon@gmail.com | B15: 31 December 2025 | C15: Jim Winkler | D15: https://docs.google.com/document/d/1HMxBE_xi-Geic86RU16VXYxrloaITg9s-608ogf9Y3w/edit?usp=drivesdk | F15: TOUR FD+ | G15: 300 | H15: 200 | I15: 11 | J15: 3 | K15: 0 | M15: 0 | N15: High | O15: Full (7-8 pax) | P15: 0.1 | Q15: 0.05 | R15: 0 | S15: 0 | T15: 1040 | U15: 103.97366 | V15: 57.185514 | W15: 1205 | X15: 1145 | Y15: 0.1 | Z15: 1045 | AA15: 0.3 | AB15: 315 | AC15: 365 | AD15: 735 | AE15: 810 | AF15: 850
A16: michelamenegon@gmail.com | B16: 31 December 2025 | C16: Jim Winkler | D16: https://docs.google.com/document/d/1Gyx934oyxLFXdKuvmYdJVU5ry97wrg3zzT0cAZX5rAU/edit?usp=drivesdk | F16: TOUR FD+ | G16: 250 | H16: 200 | I16: 10 | J16: 3 | K16: 0 | M16: 0 | N16: High | O16: Full (7-8 pax) | P16: 0.1 | Q16: 0.05 | R16: 0 | S16: 0 | T16: 935 | U16: 93.134679 | V16: 51.224074 | W16: 1080 | X16: 1030 | Y16: 0.1 | Z16: 940 | AA16: 0.3 | AB16: 285 | AC16: 330 | AD16: 660 | AE16: 730 | AF16: 765
A17: michelamenegon@gmail.com | B17: 31 December 2025 | C17: Jim Winkler | D17: https://docs.google.com/document/d/1Wm4A-vWybeMF4hygFBmUIk559UXNbh99IkovkgeBVio/edit?usp=drivesdk | F17: TOUR FD+ | G17: 250 | H17: 200 | I17: 10 | J17: 3 | K17: 0 | M17: 0 | N17: High | O17: Full (7-8 pax) | P17: 0.1 | Q17: 0.05 | R17: 0 | S17: 0 | T17: 935 | U17: 93.134679 | V17: 51.224074 | W17: 1080 | X17: 1030 | Y17: 0.1 | Z17: 940 | AA17: 0.3 | AB17: 285 | AC17: 330 | AD17: 660 | AE17: 730 | AF17: 765
A18: michelamenegon@gmail.com | B18: 31 December 2025 | C18: Jim Winkler | D18: https://docs.google.com/document/d/1ShEetJKAlcUUl0XYJPbLclbf2ulJnbbcuui48gRY9K4/edit?usp=drivesdk | F18: TOUR FD | G18: 250 | H18: 200 | I18: 8 | J18: 3 | K18: 0 | M18: 0 | N18: High | O18: Full (7-8 pax) | P18: 0.1 | Q18: 0.05 | R18: 0 | S18: 0 | T18: 830 | U18: 82.62515 | V18: 45.443832 | W18: 955 | X18: 915 | Y18: 0.1 | Z18: 835 | AA18: 0.3 | AB18: 255 | AC18: 295 | AD18: 590 | AE18: 645 | AF18: 680
A19: michelamenegon@gmail.com | B19: 01 January 2026 | C19: Amy Dickey | D19: https://docs.google.com/document/d/1SeafGxO8lhnhCKgd-VQUNqBFpU5jiWr8vcpysSNGr8k/edit?usp=drivesdk | F19: TOUR FD | G19: 250 | I19: 9 | K19: 0 | M19: 0 | N19: High | O19: Van (3-6 pax) | P19: 0.1 | Q19: 0.05 | R19: 0 | S19: 0 | T19: 640 | U19: 63.879092 | V19: 35.1335 | W19: 740 | X19: 705 | Y19: 0.1 | Z19: 645 | AA19: 0.3 | AB19: 195 | AC19: 230 | AD19: 455 | AE19: 500 | AF19: 525
A20: michelamenegon@gmail.com | B20: 01 January 2026 | C20: Emily Moroney | D20: https://docs.google.com/document/d/1qnIHWQ_SS9aQNWDm_g3Ii82qwYP9QZB6-aktSQ0I8xY/edit?usp=drivesdk | F20: TRF | G20: 500 | H20: 20 | I20: 6 | J20: 1 | K20: 27 | M20: 0 | N20: High | O20: Car (2pax) | P20: 0.1 | Q20: 0.05 | R20: 0 | S20: 0 | T20: 590 | U20: 58.917851 | V20: 32.404818 | W20: 685 | X20: 650 | Y20: 0.1 | Z20: 595 | AA20: 0.3 | AB20: 180 | AC20: 210 | AD20: 420 | AE20: 460 | AF20: 485
A21: michelamenegon@gmail.com | B21: 01 January 2026 | C21: Emily Moroney | D21: https://docs.google.com/document/d/1k5oAhsbxVq38MKIeGX6jiSZ3LFEgM7qZ1oRZM60xKiA/edit?usp=drivesdk | F21: TOUR FD+ | G21: 750 | H21: 75 | I21: 13 | J21: 1 | K21: 27 | M21: 0 | N21: Average | O21: Van (3-6 pax) | P21: 0.1 | Q21: 0.05 | R21: 0 | S21: 0 | T21: 1115 | U21: 111.28146 | V21: 61.204803 | W21: 1290 | X21: 1230 | Y21: 0.1 | Z21: 1120 | AA21: 0.3 | AB21: 340 | AC21: 395 | AD21: 790 | AE21: 865 | AF21: 910
A22: michelamenegon@gmail.com | B22: 04 January 2026 | C22: Claudine | D22: https://docs.google.com/document/d/1gH-oAndu6X0uN_DZeB6r1NO4Xs3Zd6PalM8FOX_812A/edit?usp=drivesdk | F22: TRF | G22: 500 | I22: 6 | K22: 30 | M22: 0 | N22: High | O22: Van (3-6 pax) | P22: 0.1 | Q22: 0.05 | R22: 0 | S22: 0 | T22: 650 | U22: 64.646749 | V22: 35.555712 | W22: 750 | X22: 715 | Y22: 0.1 | Z22: 650 | AA22: 0.3 | AB22: 195 | AC22: 230 | AD22: 455 | AE22: 505 | AF22: 530
A23: michelamenegon@gmail.com | B23: 04 January 2026 | C23: Client Athena | D23: https://docs.google.com/document/d/1qvr4JFJ-CSc8BBvUiqp5MXmzEUelnT15Yb8B_48n61w/edit?usp=drivesdk | F23: TRF | G23: 160 | I23: 4 | K23: 0 | M23: 0 | N23: Low | O23: Car (2pax) | P23: 0.1 | Q23: 0.05 | R23: 0 | S23: 0 | T23: 190 | U23: 18.938991 | V23: 10.416445 | W23: 220 | X23: 210 | Z23: 210 | AA23: 0.3 | AB23: 65 | AC23: 80 | AD23: 155 | AE23: 170 | AF23: 180
A24: michelamenegon@gmail.com | B24: 05 January 2026 | C24: Suzanne Conley | D24: https://docs.google.com/document/d/14An-KTWCesFnSvy8YElBGjuLFKkJl4FDgVTx3UkfwiA/edit?usp=drivesdk | F24: TOUR FD | G24: 550 | H24: 40 | I24: 11 | J24: 1 | K24: 30 | M24: 0 | N24: High | O24: Full (7-8 pax) | P24: 0.1 | Q24: 0.05 | R24: 0 | S24: 0 | T24: 1345 | U24: 134.03412 | V24: 73.718767 | W24: 1550 | X24: 1480 | Y24: 0.1 | Z24: 1350 | AA24: 0.3 | AB24: 405 | AC24: 470 | AD24: 950 | AE24: 1045 | AF24: 1095
A25: michelamenegon@gmail.com | B25: 05 January 2026 | C25: Suzanne Conley | D25: https://docs.google.com/document/d/1_flYYrbNfpWai_cBOmH2nZ5rg1aEJ4GKhtZq61rFDo0/edit?usp=drivesdk | F25: TRF | G25: 830 | H25: 20 | I25: 9 | J25: 1 | K25: 60 | M25: 0 | N25: High | O25: Full (7-8 pax) | P25: 0.1 | Q25: 0.05 | R25: 0 | S25: 0 | T25: 1020 | U25: 101.92901 | V25: 56.060956 | W25: 1180 | X25: 1125 | Y25: 0.1 | Z25: 1025 | AA25: 0.3 | AB25: 310 | AC25: 360 | AD25: 720 | AE25: 795 | AF25: 835
A26: michelamenegon@gmail.com | B26: 05 January 2026 | C26: Suzanne Conley | D26: https://docs.google.com/document/d/1xaW990GKjFWzSD-9DSGFNTPW_Y9blT79T5jRMHCrXA0/edit?usp=drivesdk | F26: TOUR FD | G26: 600 | H26: 40 | I26: 11 | J26: 1 | K26: 30 | M26: 0 | N26: High | O26: Full (7-8 pax) | P26: 0.1 | Q26: 0.05 | R26: 0 | S26: 0 | T26: 1400 | U26: 139.87891 | V26: 76.933401 | W26: 1620 | X26: 1540 | Y26: 0.1 | Z26: 1400 | AA26: 0.3 | AB26: 420 | AC26: 490 | AD26: 980 | AE26: 1080 | AF26: 1135
A27: michelamenegon@gmail.com | B27: 05 January 2026 | C27: Karen Harmatuk | D27: https://docs.google.com/document/d/1UPVb9WINU5G34QXps8GGig28G21izizL0jmBRrKIrs0/edit?usp=drivesdk | F27: TOUR FD | G27: 250 | I27: 9 | K27: 0 | M27: 0 | N27: Average | O27: Car (2pax) | P27: 0.1 | Q27: 0.05 | R27: 0 | S27: 0 | T27: 500 | U27: 49.672543 | V27: 27.319899 | W27: 575 | X27: 550 | Y27: 0.1 | Z27: 500 | AA27: 0.3 | AB27: 150 | AC27: 175 | AD27: 350 | AE27: 385 | AF27: 405
A28: michelamenegon@gmail.com | B28: 05 January 2026 | C28: Scott Swanstrom | D28: https://docs.google.com/document/d/1Ukn6E4sUDQXBfJvkc0xNsjG1RYL_d5HhCMyGRVEUBaM/edit?usp=drivesdk | F28: TRF | G28: 500 | H28: 85 | I28: 8 | J28: 2 | K28: 0 | M28: 0 | N28: High | O28: Car (2pax) | P28: 0.1 | Q28: 0.05 | R28: 0 | S28: 0 | T28: 660 | U28: 65.579502 | V28: 36.068726 | W28: 760 | X28: 730 | Y28: 0.1 | Z28: 665 | AA28: 0.3 | AB28: 200 | AC28: 235 | AD28: 470 | AE28: 515 | AF28: 540
A29: michelamenegon@gmail.com | B29: 07 January 2026 | C29: Mel Roth | D29: https://docs.google.com/document/d/1122aPVTVzY0ga9gR2zpvvxjl5y4qahQcTJ5Xxo7zg6c/edit?usp=drivesdk | F29: TRF | G29: 415 | I29: 6 | K29: 15 | M29: 0 | N29: High | O29: Car (2pax) | P29: 0.1 | Q29: 0.05 | R29: 0 | S29: 0 | T29: 475 | U29: 47.302523 | V29: 26.016388 | W29: 550 | X29: 525 | Y29: 0.1 | Z29: 480 | AA29: 0.3 | AB29: 145 | AC29: 170 | AD29: 340 | AE29: 375 | AF29: 390
A30: michelamenegon@gmail.com | B30: 07 January 2026 | C30: Mel Roth | D30: https://docs.google.com/document/d/1ttEQOFsn8UC1PCASpUcK19AXoh4mmqk2I4BNnNg-gTc/edit?usp=drivesdk | F30: TRF | G30: 250 | I30: 3 | K30: 10 | M30: 0 | N30: High | O30: Car (2pax) | P30: 0.1 | Q30: 0.05 | R30: 0 | S30: 0 | T30: 270 | U30: 26.925082 | V30: 14.808795 | W30: 315 | X30: 300 | Y30: 0.1 | Z30: 275 | AA30: 0.3 | AB30: 85 | AC30: 100 | AD30: 195 | AE30: 215 | AF30: 225
A31: michelamenegon@gmail.com | B31: 07 January 2026 | C31: Stacy | D31: https://docs.google.com/document/d/1yld9tQ1_kNjybvw0V-5RwO8R15bRYrgTEAMR30Ixg1Y/edit?usp=drivesdk | F31: TOUR FD+ | G31: 550 | I31: 2 | K31: 50 | M31: 0 | N31: Low | O31: Car (2pax) | P31: 0.1 | Q31: 0.05 | R31: 0 | S31: 0 | T31: 505 | U31: 50.048771 | V31: 27.526824 | W31: 580 | X31: 560 | Y31: 0.1 | Z31: 510 | AA31: 0.3 | AB31: 155 | AC31: 180 | AD31: 360 | AE31: 395 | AF31: 415
A32: michelamenegon@gmail.com | B32: 07 January 2026 | C32: Panayiota Costari | D32: https://docs.google.com/document/d/12-OelmxSQssdwS-JprYE42fS5HhC_nC0sSbfg2zP8qA/edit?usp=drivesdk | F32: TOUR FD+ | G32: 300 | H32: 140 | I32: 10 | J32: 2 | K32: 0 | M32: 0 | N32: Average | O32: Full (7-8 pax) | P32: 0.1 | Q32: 0.05 | R32: 0 | S32: 0 | T32: 900 | U32: 89.588695 | V32: 49.273782 | W32: 1035 | X32: 990 | Y32: 0.1 | Z32: 900 | AA32: 0.3 | AB32: 270 | AC32: 315 | AD32: 630 | AE32: 695 | AF32: 730
A33: michelamenegon@gmail.com | B33: 07 January 2026 | C33: Torre del Fuggisole | D33: https://docs.google.com/document/d/1lAEPMBilU4jfRCwAP2xiMsxg9FLMwcR4LMjKAgBN08g/edit?usp=drivesdk | F33: TOUR HD | G33: 100 | I33: 4 | K33: 0 | M33: 0 | N33: Low | O33: Van (3-6 pax) | P33: 0.1 | Q33: 0.05 | R33: 0 | S33: 0 | T33: 255 | U33: 25.043764 | V33: 13.77407 | W33: 290 | X33: 285 | Y33: 0.1 | Z33: 260 | AA33: 0.3 | AB33: 80 | AC33: 95 | AD33: 185 | AE33: 205 | AF33: 215
A34: michelamenegon@gmail.com | B34: 08 January 2026 | C34: Signori Baladi | D34: https://docs.google.com/document/d/1kgxMne3qdXaf3tNSJQol3f60s1YaG5Q9YaVJGTnUGSc/edit?usp=drivesdk | F34: TRF | G34: 150 | I34: 3 | K34: 0 | M34: 0 | N34: Average | O34: Car (2pax) | P34: 0.1 | Q34: 0.05 | R34: 0 | S34: 0 | T34: 180 | U34: 17.962509 | V34: 9.8793798 | W34: 210 | X34: 200 | Y34: 0.1 | Z34: 185 | AA34: 0.3 | AB34: 60 | AC34: 70 | AD34: 135 | AE34: 145 | AF34: 155
A35: michelamenegon@gmail.com | B35: 08 January 2026 | C35: Ying Goh | D35: https://docs.google.com/document/d/1dfxSz1zxGuxg-kwqiRW8BC-g8FOB6bq1zivZhdngk0w/edit?usp=drivesdk | F35: TOUR FD+ | G35: 750 | H35: 75 | I35: 16 | J35: 2 | K35: 30 | M35: 0 | N35: Low | O35: Van (3-6 pax) | P35: 0.1 | Q35: 0.05 | R35: 0 | S35: 0 | T35: 1120 | U35: 111.68068 | V35: 61.424376 | W35: 1290 | X35: 1230 | Y35: 0.1 | Z35: 1120 | AA35: 0.3 | AB35: 340 | AC35: 395 | AD35: 785 | AE35: 865 | AF35: 910
A36: michelamenegon@gmail.com | B36: 09 January 2026 | C36: DEBORAH KOPS | D36: https://docs.google.com/document/d/1yqDqXyyuFZrs9o04o8eiZx6VeP8Cl5Codmd9iZFXkxQ/edit?usp=drivesdk | F36: TOUR HD | G36: 150 | I36: 5 | K36: 0 | M36: 0 | N36: High | O36: Car (2pax) | P36: 0.1 | Q36: 0.05 | R36: 0 | S36: 0 | T36: 325 | U36: 32.270683 | V36: 17.748876 | W36: 375 | X36: 360 | Y36: 0.1 | Z36: 330 | AA36: 0.3 | AB36: 100 | AC36: 120 | AD36: 235 | AE36: 260 | AF36: 270
A37: michelamenegon@gmail.com | B37: 09 January 2026 | C37: DEBORAH KOPS | D37: https://docs.google.com/document/d/1NIka7xw960RETGMUexilfELq2FC-m9qdE9aLyRhP2pE/edit?usp=drivesdk | F37: TOUR FD | G37: 250 | I37: 9 | K37: 0 | M37: 0 | N37: High | O37: Car (2pax) | P37: 0.1 | Q37: 0.05 | R37: 0 | S37: 0 | T37: 545 | U37: 54.297228 | V37: 29.863475 | W37: 630 | X37: 600 | Y37: 0.1 | Z37: 550 | AA37: 0.3 | AB37: 165 | AC37: 195 | AD37: 390 | AE37: 430 | AF37: 450
A38: michelamenegon@gmail.com | B38: 09 January 2026 | C38: Teresa Pusley | D38: https://docs.google.com/document/d/1WJIayU3LusH_ZBZiHYZYtiqmY4cXSQfOyrzGkV0h9B4/edit?usp=drivesdk | F38: TOUR FD+ | G38: 250 | H38: 140 | I38: 9 | J38: 2 | K38: 0 | M38: 0 | N38: Average | O38: Van (3-6 pax) | P38: 0.1 | Q38: 0.05 | R38: 0 | S38: 0 | T38: 680 | U38: 67.97036 | V38: 37.383698 | W38: 790 | X38: 750 | Y38: 0.1 | Z38: 685 | AA38: 0.3 | AB38: 210 | AC38: 245 | AD38: 485 | AE38: 530 | AF38: 560
A39: michelamenegon@gmail.com | B39: 09 January 2026 | C39: Teresa Pusley | D39: https://docs.google.com/document/d/17ZvQxpUKur0v2uA-01cIHg5J1jMpLI_3rnf-msNtP48/edit?usp=drivesdk | F39: TOUR FD+ | G39: 250 | H39: 140 | I39: 10 | J39: 2 | K39: 0 | M39: 0 | N39: Average | O39: Van (3-6 pax) | P39: 0.1 | Q39: 0.05 | R39: 0 | S39: 0 | T39: 720 | U39: 71.976358 | V39: 39.586997 | W39: 835 | X39: 795 | Y39: 0.1 | Z39: 725 | AA39: 0.3 | AB39: 220 | AC39: 255 | AD39: 510 | AE39: 560 | AF39: 590
A40: michelamenegon@gmail.com | B40: 09 January 2026 | C40: Teresa Pusley | D40: https://docs.google.com/document/d/1JyKm2xJDFSObNr2NnV8OIEm9RFCdYnvdKyv1eTZxQLw/edit?usp=drivesdk | F40: TOUR FD+ | G40: 300 | H40: 140 | I40: 10 | J40: 2 | K40: 0 | M40: 0 | N40: Average | O40: Van (3-6 pax) | P40: 0.1 | Q40: 0.05 | R40: 0 | S40: 0 | T40: 765 | U40: 76.245925 | V40: 41.935259 | W40: 885 | X40: 845 | Y40: 0.1 | Z40: 770 | AA40: 0.3 | AB40: 235 | AC40: 275 | AD40: 545 | AE40: 595 | AF40: 625
A41: michelamenegon@gmail.com | B41: 10 January 2026 | C41: Teresa Pusley | D41: https://docs.google.com/document/d/1krlgdoGz8TTT9tCXxGAonz6ivy-VnQm3hGKC9dI5d1A/edit?usp=drivesdk | F41: TOUR FD+ | G41: 350 | H41: 140 | I41: 11 | J41: 2 | K41: 0 | M41: 0 | N41: Average | O41: Van (3-6 pax) | P41: 0.1 | Q41: 0.05 | R41: 0 | S41: 0 | T41: 850 | U41: 84.625618 | V41: 46.54409 | W41: 980 | X41: 935 | Y41: 0.1 | Z41: 850 | AA41: 0.3 | AB41: 255 | AC41: 295 | AD41: 595 | AE41: 655 | AF41: 690
A42: michelamenegon@gmail.com | B42: 10 January 2026 | C42: Firebird | D42: https://docs.google.com/document/d/1y4yaHj4ZrPrIatpUnTxqJA15YnATpcUH4hqbqJDlAY0/edit?usp=drivesdk | F42: TOUR FD | G42: 250 | H42: 140 | I42: 7 | J42: 2 | K42: 0 | M42: 0 | N42: Average | O42: Van (3-6 pax) | P42: 0.1 | Q42: 0.05 | R42: 0 | S42: 0 | T42: 600 | U42: 59.958363 | V42: 32.9771 | W42: 695 | X42: 660 | Z42: 660 | AA42: 0.3 | AB42: 200 | AC42: 235 | AD42: 480 | AE42: 530 | AF42: 555
A43: michelamenegon@gmail.com | B43: 11 January 2026 | C43: Anila Rayani | D43: https://docs.google.com/document/d/1TJkUZYSVRst5b5mQa1vl-cm3iVKWAVDKZ0bx7W1-kpk/edit?usp=drivesdk | G43: 20 | H43: 40 | I43: 2 | J43: 1 | K43: 0 | M43: 0 | N43: Average | O43: Full (7-8 pax) | P43: 0.1 | Q43: 0.05 | R43: 0.1 | S43: 0 | T43: 285 | U43: 28.363756 | V43: 15.600066 | W43: 330 | X43: 315 | Y43: 0.1 | Z43: 290 | AA43: 0.3 | AB43: 90 | AC43: 105 | AD43: 205 | AE43: 225 | AF43: 240
A44: michelamenegon@gmail.com | B44: 11 January 2026 | C44: Anila Rayani | D44: https://docs.google.com/document/d/1T-kChPPHEl3XSKmbNeo2s5x-zEWyyY-RNM1MaE_838k/edit?usp=drivesdk | G44: 20 | H44: 40 | I44: 1 | J44: 1 | K44: 0 | M44: 0 | N44: Average | O44: Full (7-8 pax) | P44: 0.1 | Q44: 0.05 | R44: 0.1 | S44: 0 | T44: 195 | U44: 19.050432 | V44: 10.477738 | W44: 225 | X44: 215 | Y44: 0.1 | Z44: 200 | AA44: 0.3 | AB44: 60 | AC44: 70 | AD44: 145 | AE44: 160 | AF44: 165
A45: michelamenegon@gmail.com | B45: 11 January 2026 | C45: Anila Rayani | D45: https://docs.google.com/document/d/1m_IG0tKeo4Nfl7W7D2XITfiSKCQ3JtK8CqMOYXK54cE/edit?usp=drivesdk | G45: 20 | H45: 40 | I45: 1 | J45: 1 | K45: 0 | M45: 0 | N45: Average | O45: Full (7-8 pax) | P45: 0.1 | Q45: 0.05 | R45: 0 | S45: 0 | T45: 175 | U45: 17.318575 | V45: 9.5252161 | W45: 205 | X45: 195 | Y45: 0.1 | Z45: 180 | AA45: 0.3 | AB45: 55 | AC45: 65 | AD45: 130 | AE45: 145 | AF45: 150
A46: michelamenegon@gmail.com | B46: 12 January 2026 | C46: Firebird | D46: https://docs.google.com/document/d/17pur8qwdAcqqVMN6YFb8cgHixMycy6A49gUxwvp1Jfs/edit?usp=drivesdk | F46: TOUR FD+ | G46: 250 | H46: 140 | I46: 9 | J46: 2 | K46: 0 | M46: 0 | N46: Average | O46: Full (7-8 pax) | P46: 0.1 | Q46: 0.05 | R46: 0 | S46: 0 | T46: 800 | U46: 79.658017 | V46: 43.811909 | W46: 925 | X46: 880 | Z46: 880 | AA46: 0.3 | AB46: 265 | AC46: 310 | AD46: 640 | AE46: 705 | AF46: 740
A47: michelamenegon@gmail.com | B47: 12 January 2026 | C47: Richard Frostick | D47: https://docs.google.com/document/d/1RKP4PibwXEYT1RTSMyUEDshWrLpx-gUCKylNNGjgYSk/edit?usp=drivesdk | F47: TRF | G47: 150 | I47: 3 | K47: 0 | M47: 0 | N47: Low | O47: Van (3-6 pax) | P47: 0.1 | Q47: 0.05 | R47: 0 | S47: 0 | T47: 190 | U47: 18.836951 | V47: 10.360323 | W47: 220 | X47: 210 | Y47: 0.1 | Z47: 195 | AA47: 0.3 | AB47: 60 | AC47: 70 | AD47: 140 | AE47: 155 | AF47: 160
A48: michelamenegon@gmail.com | B48: 12 January 2026 | C48: Juliana Soncini | D48: https://docs.google.com/document/d/1_EZ6494TMQPWDAlNiw1CedE16nM5tRU4wd0t4HcjPoU/edit?usp=drivesdk | F48: TOUR FD | G48: 250 | I48: 8 | K48: 0 | M48: 0 | N48: Average | O48: Van (3-6 pax) | P48: 0.1 | Q48: 0.05 | R48: 0 | S48: 0 | T48: 545 | U48: 54.432287 | V48: 29.937758 | W48: 630 | X48: 600 | Z48: 600 | AA48: 0.3 | AB48: 180 | AC48: 210 | AD48: 440 | AE48: 485 | AF48: 505
A49: michelamenegon@gmail.com | B49: 13 January 2026 | C49: Jane Koosney | D49: https://docs.google.com/document/d/1v9Jqy6wcUnUcP2L8dSgi6ZDpTwbQbboidJo4ZaFIRf8/edit?usp=drivesdk | G49: 170 | H49: 150 | I49: 6 | J49: 3 | K49: 0 | M49: 0 | N49: Average | O49: Van (3-6 pax) | P49: 0.1 | Q49: 0.05 | R49: 0 | S49: 0 | T49: 520 | U49: 51.567353 | V49: 28.362044 | W49: 600 | X49: 575 | Y49: 0.1 | Z49: 525 | AA49: 0.3 | AB49: 160 | AC49: 185 | AD49: 370 | AE49: 410 | AF49: 430
A50: michelamenegon@gmail.com | B50: 13 January 2026 | C50: James F Herlihy | D50: https://docs.google.com/document/d/1R3KEtpHymu_y5zmUDvJ2S4ZzLlotkvYUwASXuN30bjo/edit?usp=drivesdk | F50: TOUR FD | G50: 250 | H50: 140 | I50: 8 | J50: 2 | K50: 0 | M50: 0 | N50: Low | O50: Van (3-6 pax) | P50: 0.1 | Q50: 0.05 | R50: 0 | S50: 0 | T50: 585 | U50: 58.051889 | V50: 31.928539 | W50: 675 | X50: 645 | Y50: 0.1 | Z50: 590 | AA50: 0.3 | AB50: 180 | AC50: 210 | AD50: 415 | AE50: 460 | AF50: 480
A51: michelamenegon@gmail.com | B51: 13 January 2026 | C51: James F Herlihy | D51: https://docs.google.com/document/d/13MmHcorm8y9rGe6hNA8cAhLj8WrRQ829xP_uC0NIjJg/edit?usp=drivesdk | F51: TOUR FD | G51: 250 | H51: 140 | I51: 8 | J51: 2 | K51: 0 | M51: 0 | N51: Low | O51: Van (3-6 pax) | P51: 0.1 | Q51: 0.05 | R51: 0 | S51: 0 | T51: 585 | U51: 58.051889 | V51: 31.928539 | W51: 675 | X51: 645 | Y51: 0.1 | Z51: 590 | AA51: 0.3 | AB51: 180 | AC51: 210 | AD51: 415 | AE51: 460 | AF51: 480
A52: michelamenegon@gmail.com | B52: 13 January 2026 | C52: Johnny DiVito | D52: https://docs.google.com/document/d/1MlvOsQBotZyI3uXG3YSxaa3O9Jr6lD_pW3_cTbkW9a8/edit?usp=drivesdk | F52: TOUR HD | G52: 150 | I52: 4 | K52: 0 | M52: 0 | N52: Average | O52: Van (3-6 pax) | P52: 0.1 | Q52: 0.05 | R52: 0 | S52: 0 | T52: 310 | U52: 30.573654 | V52: 16.81551 | W52: 355 | X52: 310 | Z52: 310 | AA52: 0.3 | AB52: 95 | AC52: 110 | AD52: 220 | AE52: 240 | AF52: 255
A53: michelamenegon@gmail.com | B53: 13 January 2026 | C53: Dan Friel | D53: https://docs.google.com/document/d/1uob3Od_OX4FxDOTHLvVlya__5tdg5CK9cgOGFYnQ1QY/edit?usp=drivesdk | F53: TOUR HD | G53: 150 | I53: 4 | K53: 0 | M53: 0 | N53: Average | O53: Van (3-6 pax) | P53: 0.1 | Q53: 0.05 | R53: 0 | S53: 0 | T53: 310 | U53: 30.573654 | V53: 16.81551 | W53: 355 | X53: 345 | Y53: 0.1 | Z53: 315 | AA53: 0.3 | AB53: 95 | AC53: 110 | AD53: 225 | AE53: 245 | AF53: 260
A54: michelamenegon@gmail.com | B54: 13 January 2026 | C54: Dan Friel | D54: https://docs.google.com/document/d/1djj96bMom7pWubkvsOuw6t3V0TsggZGF-nOc4ebmUu8/edit?usp=drivesdk | G54: 260 | H54: 240 | I54: 8 | J54: 3 | K54: 30 | M54: 0 | N54: Average | O54: Van (3-6 pax) | P54: 0.1 | Q54: 0.05 | R54: 0 | S54: 0 | T54: 715 | U54: 71.363289 | V54: 39.249809 | W54: 825 | X54: 790 | Y54: 0.1 | Z54: 720 | AA54: 0.3 | AB54: 220 | AC54: 255 | AD54: 510 | AE54: 560 | AF54: 585
A55: michelamenegon@gmail.com | B55: 13 January 2026 | C55: Dan Friel | D55: https://docs.google.com/document/d/12Xjhk6-A93xUMigGor4YLiShomq95JU-2QT4WSOiomE/edit?usp=drivesdk | F55: TOUR FD | G55: 250 | I55: 8 | K55: 0 | M55: 0 | N55: Average | O55: Van (3-6 pax) | P55: 0.1 | Q55: 0.05 | R55: 0 | S55: 0 | T55: 545 | U55: 54.432287 | V55: 29.937758 | W55: 630 | X55: 790 | Y55: 0.1 | Z55: 720 | AA55: 0.3 | AB55: 220 | AC55: 255 | AD55: 560 | AE55: 615 | AF55: 645
A56: michelamenegon@gmail.com | B56: 13 January 2026 | C56: Dan Friel | D56: https://docs.google.com/document/d/13rX6sPXmcljTZBJHGe6Tkg-WfILLZhzX6tJjJq9HYXo/edit?usp=drivesdk | F56: TOUR FD | G56: 250 | I56: 9 | K56: 0 | M56: 0 | N56: Average | O56: Van (3-6 pax) | P56: 0.1 | Q56: 0.05 | R56: 0 | S56: 0 | T56: 585 | U56: 58.438286 | V56: 32.141057 | W56: 675 | X56: 645 | Y56: 0.1 | Z56: 590 | AA56: 0.3 | AB56: 180 | AC56: 210 | AD56: 415 | AE56: 460 | AF56: 480
A57: michelamenegon@gmail.com | B57: 13 January 2026 | C57: Dan Friel | D57: https://docs.google.com/document/d/1-8KhY6GIaKp4cEytsmXPk_MYg6vPePkW6G1tNF_2EiU/edit?usp=drivesdk | G57: 210 | H57: 200 | I57: 8 | J57: 3 | K57: 25 | M57: 0 | N57: Average | O57: Van (3-6 pax) | P57: 0.1 | Q57: 0.05 | R57: 0 | S57: 0 | T57: 670 | U57: 66.994538 | V57: 36.846996 | W57: 775 | X57: 740 | Y57: 0.1 | Z57: 675 | AA57: 0.3 | AB57: 205 | AC57: 240 | AD57: 475 | AE57: 525 | AF57: 550
A58: michelamenegon@gmail.com | B58: 13 January 2026 | C58: Dan Friel | D58: https://docs.google.com/document/d/1hVNK2eLaXT9uileI5Zto4IPhcuspW0PmEFDhYYlfhO0/edit?usp=drivesdk | G58: 250 | H58: 380 | I58: 9 | J58: 4 | K58: 25 | M58: 0 | N58: High | O58: Van (3-6 pax) | P58: 0.1 | Q58: 0.05 | R58: 0 | S58: 0 | T58: 750 | U58: 74.627109 | V58: 41.04491 | W58: 865 | X58: 760 | Y58: 0.1 | Z58: 695 | AA58: 0.3 | AB58: 210 | AC58: 245 | AD58: 470 | AE58: 520 | AF58: 545
A59: michelamenegon@gmail.com | B59: 13 January 2026 | C59: Dan Friel | D59: https://docs.google.com/document/d/1aPSPbgdVC2ReCPGm0-2J_zvpvdNah3peE3DIJi2rtfg/edit?usp=drivesdk | G59: 250 | H59: 380 | I59: 9 | J59: 4 | K59: 60 | M59: 0 | N59: Average | O59: Van (3-6 pax) | P59: 0.1 | Q59: 0.05 | R59: 0 | S59: 0 | T59: 755 | U59: 75.13565 | V59: 41.324608 | W59: 870 | X59: 835 | Y59: 0.1 | Z59: 760 | AA59: 0.3 | AB59: 230 | AC59: 270 | AD59: 535 | AE59: 590 | AF59: 620
A60: michelamenegon@gmail.com | B60: 13 January 2026 | C60: Scott & Bonnie Strapp | D60: https://docs.google.com/document/d/11HocqsBxSXUSMJGCNN3oF-7BWB2u2pJzl1aNvjdCugU/edit?usp=drivesdk | G60: 350 | H60: 30 | I60: 9 | J60: 1 | K60: 0 | M60: 0 | N60: Average | O60: Car (2pax) | P60: 0.1 | Q60: 0.05 | R60: 0 | S60: 0 | T60: 620 | U60: 61.758031 | V60: 33.966917 | W60: 715 | X60: 685 | Y60: 0.1 | Z60: 625 | AA60: 0.3 | AB60: 190 | AC60: 220 | AD60: 440 | AE60: 485 | AF60: 510
A61: michelamenegon@gmail.com | B61: 14 January 2026 | C61: Suzanne Miller | D61: https://docs.google.com/document/d/10_XghKsm9YQRTmBgfyQvggLm9HVFqUew1I2QukK6UDQ/edit?usp=drivesdk | F61: TRF | G61: 150 | I61: 3 | K61: 0 | M61: 0 | N61: Average | O61: Full (7-8 pax) | P61: 0.1 | Q61: 0.05 | R61: 0 | S61: 0 | T61: 255 | U61: 25.358836 | V61: 13.94736 | W61: 295 | X61: 285 | Z61: 285 | AA61: 0.3 | AB61: 90 | AC61: 105 | AD61: 210 | AE61: 230 | AF61: 245
A62: michelamenegon@gmail.com | B62: 14 January 2026 | C62: Suzanne Miller | D62: https://docs.google.com/document/d/1voPJUqYVRcQCn964JQsPdCsjXuURy7dgYTYYn-l_Geg/edit?usp=drivesdk | G62: 300 | I62: 10 | K62: 0 | M62: 0 | N62: Average | O62: Full (7-8 pax) | P62: 0.1 | Q62: 0.05 | R62: 0 | S62: 0 | T62: 805 | U62: 80.056621 | V62: 44.031142 | W62: 925 | X62: 890 | Z62: 890 | AA62: 0.3 | AB62: 270 | AC62: 315 | AD62: 650 | AE62: 715 | AF62: 750
A63: michelamenegon@gmail.com | B63: 14 January 2026 | C63: Suzanne Miller | D63: https://docs.google.com/document/d/1KBow3XWJM-IjmLAT2kkHbeRr47CSacRvh54k2hMapW8/edit?usp=drivesdk | G63: 250 | I63: 8 | K63: 0 | M63: 0 | N63: Average | O63: Full (7-8 pax) | P63: 0.1 | Q63: 0.05 | R63: 0 | S63: 0 | T63: 655 | U63: 65.318745 | V63: 35.92531 | W63: 755 | X63: 725 | Z63: 725 | AA63: 0.3 | AB63: 220 | AC63: 255 | AD63: 530 | AE63: 585 | AF63: 615
A64: michelamenegon@gmail.com | B64: 14 January 2026 | C64: Juliana Soncini | D64: https://docs.google.com/document/d/1wG_wDG9ZJIAjC8NR5BRjtv3GzslZngVV1iLASIer_lM/edit?usp=drivesdk | F64: TOUR FD | G64: 250 | I64: 9 | L64: 0 | N64: High | O64: Van (3-6 pax) | P64: 0.1 | Q64: 0.05 | R64: 0 | S64: 0 | T64: 640 | U64: 63.879092 | V64: 35.1335 | W64: 740 | X64: 640 | Y64: 0.1 | Z64: 585 | AA64: 0.3 | AB64: 180 | AC64: 210 | AD64: 395 | AE64: 435 | AF64: 455
A65: michelamenegon@gmail.com | B65: 14 January 2026 | C65: Dan Friel | D65: https://docs.google.com/document/d/1juEydBtlLxHO1HVxMKwoiuXqacu2pl9nwHBoEz6mkq0/edit?usp=drivesdk | G65: 280 | H65: 250 | I65: 8 | L65: 30 | N65: High | O65: Van (3-6 pax) | P65: 0.1 | Q65: 0.05 | R65: 0 | S65: 0 | T65: 755 | U65: 75.031398 | V65: 41.267269 | W65: 870 | X65: 755 | Y65: 0.1 | Z65: 690 | AA65: 0.3 | AB65: 210 | AC65: 245 | AD65: 465 | AE65: 510 | AF65: 540
A66: michelamenegon@gmail.com | B66: 14 January 2026 | C66: Dan Friel | D66: https://docs.google.com/document/d/1WEjTYB8YZllMU51iCr1A2bPa3WxIKlz9b6TY0fHYrhQ/edit?usp=drivesdk | F66: TOUR HD | G66: 150 | I66: 4 | L66: 0 | N66: High | O66: Van (3-6 pax) | P66: 0.1 | Q66: 0.05 | R66: 0 | S66: 0 | T66: 335 | U66: 33.420167 | V66: 18.381092 | W66: 390 | X66: 335 | Y66: 0.1 | Z66: 305 | AA66: 0.3 | AB66: 95 | AC66: 110 | AD66: 205 | AE66: 225 | AF66: 240
A67: michelamenegon@gmail.com | B67: 14 January 2026 | C67: Dan Friel | D67: https://docs.google.com/document/d/19L2rkW1Zr6Xb1Hikukv-lIrWX0-LpZAQLUjrcU-69vI/edit?usp=drivesdk | G67: 200 | I67: 8 | L67: 0 | N67: High | O67: Van (3-6 pax) | P67: 0.1 | Q67: 0.05 | R67: 0 | S67: 0 | T67: 555 | U67: 55.120275 | V67: 30.316151 | W67: 640 | X67: 555 | Y67: 0.1 | Z67: 505 | AA67: 0.3 | AB67: 155 | AC67: 180 | AD67: 340 | AE67: 375 | AF67: 395
A68: michelamenegon@gmail.com | B68: 14 January 2026 | C68: Dan Friel | D68: https://docs.google.com/document/d/1bxT6bpH0sdOkYteYNM4zlWK50tXpIwA_w16Wraket00/edit?usp=drivesdk | G68: 200 | I68: 8 | L68: 0 | N68: High | O68: Van (3-6 pax) | P68: 0.1 | Q68: 0.05 | R68: 0 | S68: 0 | T68: 555 | U68: 55.120275 | V68: 30.316151 | W68: 640 | X68: 555 | Y68: 0.1 | Z68: 505 | AA68: 0.3 | AB68: 155 | AC68: 180 | AD68: 340 | AE68: 375 | AF68: 395
A69: michelamenegon@gmail.com | B69: 14 January 2026 | C69: Dan Friel | D69: https://docs.google.com/document/d/1BLTHBblgVzL_5veWkkUWshg4A2eaREQYF4IQXMlVtJQ/edit?usp=drivesdk | F69: TOUR FD | G69: 250 | I69: 8 | L69: 0 | N69: High | O69: Van (3-6 pax) | P69: 0.1 | Q69: 0.05 | R69: 0 | S69: 0 | T69: 600 | U69: 59.500121 | V69: 32.725066 | W69: 690 | X69: 600 | Y69: 0.1 | Z69: 550 | AA69: 0.3 | AB69: 165 | AC69: 195 | AD69: 370 | AE69: 410 | AF69: 430
A70: michelamenegon@gmail.com | B70: 14 January 2026 | C70: Dan Friel | D70: https://docs.google.com/document/d/1YXLEnCILiwhhXViEGgsX9Z9fPd0VG58jy5l5M32u80k/edit?usp=drivesdk | F70: TOUR FD | G70: 250 | I70: 9 | L70: 0 | N70: High | O70: Van (3-6 pax) | P70: 0.1 | Q70: 0.05 | R70: 0 | S70: 0 | T70: 640 | U70: 63.879092 | V70: 35.1335 | W70: 740 | X70: 640 | Y70: 0.1 | Z70: 585 | AA70: 0.3 | AB70: 180 | AC70: 210 | AD70: 395 | AE70: 435 | AF70: 455
A71: michelamenegon@gmail.com | B71: 14 January 2026 | C71: Dan Friel | D71: https://docs.google.com/document/d/1M_MQJYLUnriIFxU74npGnXzoUPKS_quYvGevf09KvEQ/edit?usp=drivesdk | G71: 250 | H71: 380 | I71: 9 | L71: 60 | N71: High | O71: Van (3-6 pax) | P71: 0.1 | Q71: 0.05 | R71: 0 | S71: 0 | T71: 800 | U71: 79.74565 | V71: 43.860107 | W71: 925 | X71: 800 | Y71: 0.1 | Z71: 730 | AA71: 0.3 | AB71: 220 | AC71: 255 | AD71: 490 | AE71: 540 | AF71: 570
A72: michelamenegon@gmail.com | B72: 15 January 2026 | C72: Dan Friel | D72: https://docs.google.com/document/d/11pxckvRfIC47tasMicNDC5-O2PegVZGTdIDdeLcSs04/edit?usp=drivesdk | G72: 230 | H72: 200 | I72: 10 | L72: 36 | N72: High | O72: Van (3-6 pax) | P72: 0.1 | Q72: 0.05 | R72: 0 | S72: 0 | T72: 805 | U72: 80.373096 | V72: 44.205203 | W72: 930 | X72: 805 | Y72: 0.1 | Z72: 735 | AA72: 0.3 | AB72: 225 | AC72: 260 | AD72: 495 | AE72: 545 | AF72: 570
A73: michelamenegon@gmail.com | B73: 15 January 2026 | C73: Dan Friel | D73: https://docs.google.com/document/d/1xCE-gDtvrVUODxAzZUOi3ukSw_OzkCbqUTdLBRgkLd4/edit?usp=drivesdk | G73: 230 | H73: 200 | I73: 10 | L73: 36 | N73: High | O73: Van (3-6 pax) | P73: 0.1 | Q73: 0.05 | R73: 0 | S73: 0 | T73: 955 | U73: 95.373096 | V73: 52.455203 | W73: 1105 | X73: 955 | Y73: 0.1 | Z73: 870 | AA73: 0.3 | AB73: 265 | AC73: 310 | AD73: 585 | AE73: 645 | AF73: 675
A74: michelamenegon@gmail.com | B74: 15 January 2026 | C74: Dan Friel | D74: https://docs.google.com/document/d/1JHs7nro6tKU79MvNV76BLkckcS8O2Bmv07BnA3HNDRU/edit?usp=drivesdk | G74: 210 | H74: 200 | I74: 8 | L74: 30 | N74: High | O74: Van (3-6 pax) | P74: 0.1 | Q74: 0.05 | R74: 0 | S74: 0 | T74: 690 | U74: 68.680737 | V74: 37.774406 | W74: 795 | X74: 690 | Y74: 0.1 | Z74: 630 | AA74: 0.3 | AB74: 190 | AC74: 220 | AD74: 425 | AE74: 470 | AF74: 490
A75: michelamenegon@gmail.com | B75: 15 January 2026 | C75: Jane Koosney | D75: https://docs.google.com/document/d/1Td41CnEBGajD9sBuX0Imzp51R9hBK1JMHOhb-Sw9IdI/edit?usp=drivesdk | G75: 170 | H75: 160 | I75: 6 | L75: 0 | N75: High | O75: Van (3-6 pax) | P75: 0.1 | Q75: 0.05 | R75: 0 | S75: 0 | T75: 505 | U75: 50.100159 | V75: 27.555088 | W75: 580 | X75: 505 | Y75: 0.1 | Z75: 460 | AA75: 0.3 | AB75: 140 | AC75: 165 | AD75: 310 | AE75: 340 | AF75: 360
A76: michelamenegon@gmail.com | B76: 15 January 2026 | C76: Torre del Fuggisole | D76: https://docs.google.com/document/d/11P7GB9P3B10ZDOkrLyWj9mfG-6Vvx4weKJxCXbbPhLU/edit?usp=drivesdk | F76: TRF | G76: 500 | I76: 6 | L76: 30 | N76: Average | O76: Car (2pax) | P76: 0.1 | Q76: 0.05 | R76: 0 | S76: 0 | T76: 505 | U76: 50.269475 | V76: 27.648211 | W76: 585 | X76: 505 | Y76: 0.1 | Z76: 460 | AA76: 0.3 | AB76: 140 | AC76: 165 | AD76: 310 | AE76: 340 | AF76: 360
A77: michelamenegon@gmail.com | B77: 15 January 2026 | C77: Betty Nadalini | D77: https://docs.google.com/document/d/19adkAbjKYpcOPfGQw0BVpzjX-gaFD57MV3Pma_Liocw/edit?usp=drivesdk | F77: TRF | G77: 190 | H77: 300 | I77: 3 | K77: 5 | L77: 30 | N77: Average | O77: Car (2pax) | P77: 0.1 | Q77: 0.05 | R77: 0 | S77: 0 | T77: 515 | U77: 51.092673 | V77: 28.10097 | W77: 595 | X77: 515 | Y77: 0.1 | Z77: 470 | AA77: 0.3 | AB77: 145 | AC77: 170 | AD77: 320 | AE77: 350 | AF77: 365
A78: michelamenegon@gmail.com | B78: 15 January 2026 | C78: Betty Nadalini | D78: https://docs.google.com/document/d/1cA4O76Mt7y6Xp7_5opK1xTkn7iB3v3G1V6dDT_z5Mtc/edit?usp=drivesdk | F78: TRF | G78: 500 | I78: 6 | L78: 30 | N78: Average | O78: Car (2pax) | P78: 0.1 | Q78: 0.05 | R78: 0 | S78: 0 | T78: 505 | U78: 50.269475 | V78: 27.648211 | W78: 585 | X78: 505 | Y78: 0.1 | Z78: 460 | AA78: 0.3 | AB78: 140 | AC78: 165 | AD78: 310 | AE78: 340 | AF78: 360
A79: michelamenegon@gmail.com | B79: 15 January 2026 | C79: Dan Friel | D79: https://docs.google.com/document/d/1Mw0uG5EcfNrA6eQxE-uIfcU8GArqOMFNOD8QT-fTYz8/edit?usp=drivesdk | G79: 280 | H79: 250 | I79: 8 | K79: 3 | L79: 35 | N79: High | O79: Van (3-6 pax) | P79: 0.1 | Q79: 0.05 | R79: 0 | S79: 0 | T79: 860 | U79: 85.647928 | V79: 47.10636 | W79: 990 | X79: 860 | Y79: 0.1 | Z79: 785 | AA79: 0.3 | AB79: 240 | AC79: 280 | AD79: 530 | AE79: 580 | AF79: 610
A80: michelamenegon@gmail.com | B80: 16 January 2026 | C80: Susan Lee | D80: https://docs.google.com/document/d/1SW3Xwd85yPtEdqboqxTVNX7Aj9LJuUWPRkkYLzkHygA/edit?usp=drivesdk | G80: 250 | H80: 250 | I80: 6 | K80: 3 | L80: 20 | N80: Average | O80: Car (2pax) | P80: 0.1 | Q80: 0.05 | R80: 0 | S80: 0 | T80: 575 | U80: 57.313691 | V80: 31.52253 | W80: 665 | X80: 575 | Y80: 0.1 | Z80: 525 | AA80: 0.3 | AB80: 160 | AC80: 185 | AD80: 355 | AE80: 390 | AF80: 410
A81: michelamenegon@gmail.com | B81: 16 January 2026 | C81: Rachel Signer | D81: https://docs.google.com/document/d/1VRdZshja8EXmTCvsiANfjyLCgqsTnhxnp-DPMGq6iMQ/edit?usp=drivesdk | G81: 250 | H81: 60 | I81: 8 | K81: 2 | L81: 0 | N81: Average | O81: Full (7-8 pax) | P81: 0.1 | Q81: 0.05 | R81: 0 | S81: 0 | T81: 775 | U81: 77.346145 | V81: 42.54038 | W81: 895 | X81: 730 | Y81: 0.1 | Z81: 665 | AA81: 0.3 | AB81: 200 | AC81: 235 | AD81: 435 | AE81: 480 | AF81: 500
A82: michelamenegon@gmail.com | B82: 16 January 2026 | C82: Rachel Signer | D82: https://docs.google.com/document/d/1UaKeNKFdvm4Xy3MIXdmGmczS9eTHw5iQizgFymDbqeY/edit?usp=drivesdk | G82: 250 | H82: 60 | I82: 7 | K82: 2 | L82: 0 | N82: Average | O82: Full (7-8 pax) | P82: 0.1 | Q82: 0.05 | R82: 0 | S82: 0 | T82: 730 | U82: 72.538947 | V82: 39.896421 | W82: 840 | X82: 730 | Y82: 0.1 | Z82: 665 | AA82: 0.3 | AB82: 200 | AC82: 235 | AD82: 450 | AE82: 495 | AF82: 520
A83: michelamenegon@gmail.com | B83: 16 January 2026 | C83: Rachel Signer | D83: https://docs.google.com/document/d/1fYEwjNmlLUcL6NUhDyi87MaQCmf3nQQOKVVUq1d0hB0/edit?usp=drivesdk | G83: 250 | H83: 60 | I83: 8 | K83: 2 | L83: 0 | N83: Average | O83: Full (7-8 pax) | P83: 0.1 | Q83: 0.05 | R83: 0 | S83: 0 | T83: 775 | U83: 77.346145 | V83: 42.54038 | W83: 895 | X83: 775 | Y83: 0.1 | Z83: 705 | AA83: 0.3 | AB83: 215 | AC83: 250 | AD83: 475 | AE83: 520 | AF83: 550
A84: michelamenegon@gmail.com | B84: 16 January 2026 | C84: Andrea Wong | D84: https://docs.google.com/document/d/136elHAzVM7InWhAcZrCUi7QadizPaNK4KFG-WLGMg-I/edit?usp=drivesdk | F84: TRF | G84: 500 | H84: 30 | I84: 6 | K84: 1 | L84: 30 | N84: High | O84: Car (2pax) | P84: 0.1 | Q84: 0.05 | R84: 0 | S84: 0 | T84: 600 | U84: 59.870036 | V84: 32.92852 | W84: 695 | X84: 600 | Y84: 0.1 | Z84: 550 | AA84: 0.3 | AB84: 165 | AC84: 195 | AD84: 370 | AE84: 410 | AF84: 430
A85: michelamenegon@gmail.com | B85: 16 January 2026 | C85: Andrea Wong | D85: https://docs.google.com/document/d/10UVDoN8LRk1OiYbL45rJGT5nxSW-bZJmlkLTPT25Rxg/edit?usp=drivesdk | F85: TOUR FD | G85: 250 | H85: 120 | I85: 9 | K85: 2 | L85: 0 | N85: High | O85: Car (2pax) | P85: 0.1 | Q85: 0.05 | R85: 0 | S85: 0 | T85: 645 | U85: 64.137828 | V85: 35.275805 | W85: 745 | X85: 605 | Y85: 0.1 | Z85: 550 | AA85: 0.3 | AB85: 165 | AC85: 195 | AD85: 360 | AE85: 395 | AF85: 415
A86: michelamenegon@gmail.com | B86: 16 January 2026 | C86: Andrea Wong | D86: https://docs.google.com/document/d/15nQnt_LCKjKk77WRgbryzjqKR9BNSz4BDLQIFNkoVeY/edit?usp=drivesdk | F86: TOUR FD | G86: 250 | H86: 120 | I86: 9 | K86: 2 | L86: 0 | N86: High | O86: Car (2pax) | P86: 0.1 | Q86: 0.05 | R86: 0 | S86: 0 | T86: 645 | U86: 64.137828 | V86: 35.275805 | W86: 745 | X86: 645 | Y86: 0.1 | Z86: 590 | AA86: 0.3 | AB86: 180 | AC86: 210 | AD86: 400 | AE86: 440 | AF86: 460
A87: michelamenegon@gmail.com | B87: 16 January 2026 | C87: Andrea Wong | D87: https://docs.google.com/document/d/1EKSo69rlMoJ6crl993VIXw0oTkN6i9LlrPoYL9rgu3U/edit?usp=drivesdk | F87: TOUR FD | G87: 250 | H87: 120 | I87: 8 | K87: 2 | L87: 0 | N87: High | O87: Car (2pax) | P87: 0.1 | Q87: 0.05 | R87: 0 | S87: 0 | T87: 605 | U87: 60.415703 | V87: 33.228637 | W87: 700 | X87: 605 | Y87: 0.1 | Z87: 550 | AA87: 0.3 | AB87: 165 | AC87: 195 | AD87: 370 | AE87: 410 | AF87: 430
A88: michelamenegon@gmail.com | B88: 16 January 2026 | C88: Andrea Wong | D88: https://docs.google.com/document/d/1zXUD7TSTxCUkOz9GF6RB-1prbBnwh9jusc2OHDwJlBM/edit?usp=drivesdk | F88: TOUR FD | G88: 250 | H88: 120 | I88: 9 | K88: 2 | L88: 0 | N88: High | O88: Car (2pax) | P88: 0.1 | Q88: 0.05 | R88: 0 | S88: 0 | T88: 645 | U88: 64.137828 | V88: 35.275805 | W88: 745 | X88: 645 | Y88: 0.1 | Z88: 590 | AA88: 0.3 | AB88: 180 | AC88: 210 | AD88: 400 | AE88: 440 | AF88: 460
A89: michelamenegon@gmail.com | B89: 17 January 2026 | C89: Carol Kirven | D89: https://docs.google.com/document/d/1FCZgzNphgUOdpn7D3KDk-bgiJMEAcPAgufZx3XW_UUQ/edit?usp=drivesdk | F89: TOUR HD | G89: 150 | I89: 5 | L89: 0 | N89: Average | O89: Car (2pax) | P89: 0.1 | Q89: 0.05 | R89: 0 | S89: 0 | T89: 300 | U89: 29.522076 | V89: 16.237142 | W89: 345 | X89: 300 | Y89: 0.1 | Z89: 275 | AA89: 0.3 | AB89: 85 | AC89: 100 | AD89: 185 | AE89: 205 | AF89: 215
A90: michelamenegon@gmail.com | B90: 17 January 2026 | C90: Kate Cashman | D90: https://docs.google.com/document/d/1GcL_-h_yXRsNzha7W237chcvXWcQos0chxBzFu5Qr0A/edit?usp=drivesdk | F90: TOUR FD | G90: 250 | H90: 90 | I90: 8 | K90: 2 | L90: 0 | N90: High | O90: Car (2pax) | P90: 0.1 | Q90: 0.05 | R90: 0 | S90: 0 | T90: 605 | U90: 60.415703 | V90: 33.228637 | W90: 700 | X90: 605 | Y90: 0.1 | Z90: 550 | AA90: 0.3 | AB90: 165 | AC90: 195 | AD90: 370 | AE90: 410 | AF90: 430
A91: michelamenegon@gmail.com | B91: 17 January 2026 | C91: Kate Cashman | D91: https://docs.google.com/document/d/1JBQHg8zJuVecle51SjMArvIJOP-T1856PyWL3nLDZ3s/edit?usp=drivesdk | F91: TRF | G91: 80 | H91: 90 | I91: 2 | K91: 2 | L91: 0 | N91: High | O91: Car (2pax) | P91: 0.1 | Q91: 0.05 | R91: 0 | S91: 0 | T91: 235 | U91: 23.345371 | V91: 12.839954 | W91: 270 | X91: 235 | Y91: 0.1 | Z91: 215 | AA91: 0.3 | AB91: 65 | AC91: 80 | AD91: 145 | AE91: 160 | AF91: 170
A92: michelamenegon@gmail.com | B92: 17 January 2026 | C92: Jane Koosney | D92: https://docs.google.com/document/d/1AUGMbQDVIIXwEWXrsuLuwb7wBYlAg2ArWJEXiMuiO_A/edit?usp=drivesdk | F92: TRF | G92: 500 | H92: 60 | I92: 7 | J92: 2 | K92: 1 | L92: 30 | N92: High | O92: Car (2pax) | P92: 0.1 | Q92: 0.05 | R92: 0 | S92: 0 | T92: 790 | U92: 78.773039 | V92: 43.325172 | W92: 910 | X92: 790 | Y92: 0.1 | Z92: 720 | AA92: 0.3 | AB92: 220 | AC92: 255 | AD92: 485 | AE92: 535 | AF92: 560
A93: michelamenegon@gmail.com | B93: 17 January 2026 | C93: Jane Koosney | D93: https://docs.google.com/document/d/1XADovtNCVtqiUq0R1PqeKeAjzgu3MzVGOiO4wfubAng/edit?usp=drivesdk | F93: TRF | G93: 500 | H93: 30 | I93: 7 | J93: 2 | K93: 1 | L93: 30 | N93: High | O93: Van (3-6 pax) | P93: 0.1 | Q93: 0.05 | R93: 0 | S93: 0 | T93: 915 | U93: 91.310811 | V93: 50.220946 | W93: 1055 | X93: 915 | Y93: 0.1 | Z93: 835 | AA93: 0.3 | AB93: 255 | AC93: 295 | AD93: 565 | AE93: 620 | AF93: 650
A94: michelamenegon@gmail.com | B94: 17 January 2026 | C94: Jane Koosney | D94: https://docs.google.com/document/d/1s6XSOd8tM-Q74YBV72y5XaZ7bkdaZcT2VsKbE3eLRDU/edit?usp=drivesdk | F94: TOUR FD | G94: 250 | H94: 80 | I94: 8 | K94: 2 | L94: 0 | N94: High | O94: Van (3-6 pax) | P94: 0.1 | Q94: 0.05 | R94: 0 | S94: 0 | T94: 705 | U94: 70.434121 | V94: 38.738766 | W94: 815 | X94: 705 | Y94: 0.1 | Z94: 645 | AA94: 0.3 | AB94: 195 | AC94: 230 | AD94: 435 | AE94: 480 | AF94: 505
A95: michelamenegon@gmail.com | B95: 17 January 2026 | C95: Kate Cashman | D95: https://docs.google.com/document/d/1v12KvX2TV07I-NnYQAHMQKLjn0f1drJmR9-SSJjOWYI/edit?usp=drivesdk | F95: TRF | G95: 500 | H95: 45 | I95: 6 | K95: 2 | L95: 27 | N95: High | O95: Car (2pax) | P95: 0.1 | Q95: 0.05 | R95: 0 | S95: 0 | T95: 645 | U95: 64.386154 | V95: 35.412385 | W95: 745 | X95: 645 | Y95: 0.1 | Z95: 590 | AA95: 0.3 | AB95: 180 | AC95: 210 | AD95: 400 | AE95: 440 | AF95: 460
A96: michelamenegon@gmail.com | B96: 17 January 2026 | C96: Kate Cashman | D96: https://docs.google.com/document/d/1di0omIzhbljdVVXy35ngbcB_M29WAuFabZ0rahfFQYQ/edit?usp=drivesdk | F96: TRF | G96: 150 | H96: 85 | I96: 3 | K96: 2 | L96: 0 | N96: High | O96: Car (2pax) | P96: 0.1 | Q96: 0.05 | R96: 0 | S96: 0 | T96: 295 | U96: 29.47548 | V96: 16.211514 | W96: 345 | X96: 295 | Y96: 0.1 | Z96: 270 | AA96: 0.3 | AB96: 85 | AC96: 100 | AD96: 185 | AE96: 200 | AF96: 210
A97: tomsiena@gmail.com | B97: 17 January 2026 | C97: Wilson Greenlaw | D97: https://docs.google.com/document/d/1EVjWx-fxaWUIDZxiQjjdSzohAlwOIgllGO1f5bNqi2E/edit?usp=drivesdk | F97: TOUR FD | G97: 250 | I97: 9 | L97: 0 | N97: Low | O97: Van (3-6 pax) | P97: 0.1 | Q97: 0.05 | R97: 0 | S97: 0 | T97: 525 | U97: 52.090679 | V97: 28.649873 | W97: 605 | X97: 490 | Y97: 0.1 | Z97: 450 | AA97: 0.3 | AB97: 135 | AC97: 160 | AD97: 295 | AE97: 325 | AF97: 340
A98: michelamenegon@gmail.com | B98: 18 January 2026 | C98: Robert Alvarez | D98: https://docs.google.com/document/d/10oQEwwtpaFcJzuK1T3bPakWu5Zee1Zayw1t804A4vGg/edit?usp=drivesdk | F98: TOUR FD | G98: 250 | H98: 140 | I98: 8 | K98: 2 | L98: 0 | N98: Average | O98: Car (2pax) | P98: 0.1 | Q98: 0.05 | R98: 0 | S98: 0 | T98: 565 | U98: 56.108044 | V98: 30.859424 | W98: 650 | X98: 565 | Y98: 0.1 | Z98: 515 | AA98: 0.3 | AB98: 155 | AC98: 180 | AD98: 350 | AE98: 385 | AF98: 400
A99: michelamenegon@gmail.com | B99: 18 January 2026 | C99: Jeannine Opatchen | D99: https://docs.google.com/document/d/1o4fr9sX1Tt_b0IAp5A8zXNIVW2cJVm3duN_-aGdkNxA/edit?usp=drivesdk | F99: TOUR FD | G99: 250 | H99: 80 | I99: 8 | K99: 2 | L99: 0 | N99: High | O99: Van (3-6 pax) | P99: 0.1 | Q99: 0.05 | R99: 0 | S99: 0 | T99: 705 | U99: 70.434121 | V99: 38.738766 | W99: 815 | X99: 705 | Y99: 0.1 | Z99: 645 | AA99: 0.3 | AB99: 195 | AC99: 230 | AD99: 435 | AE99: 480 | AF99: 505
A100: michelamenegon@gmail.com | B100: 18 January 2026 | C100: Rachel Signer | D100: https://docs.google.com/document/d/1m1BMUxtaDPjIW0lIGFyDaOxL7G2D3cQJd483EMndLD8/edit?usp=drivesdk | F100: TRF | G100: 60 | I100: 2 | L100: 0 | N100: High | O100: Full (7-8 pax) | P100: 0.1 | Q100: 0.05 | R100: 0 | S100: 0 | T100: 185 | U100: 18.40247 | V100: 10.121358 | W100: 215 | X100: 185 | Y100: 0.1 | Z100: 170 | AA100: 0.3 | AB100: 55 | AC100: 65 | AD100: 115 | AE100: 130 | AF100: 135
...

Sheet Pricing Calculator
A2: COST BREAKDOWN | C2: RECTIFIED | E2: SERVIZIO
A3: Fuel Cost | B3: =(Pricing!C5)*'Base Operating Costs'!$B$13 -> 47.5 | F3: Car (2pax) | G3: Van (3-6 pax) | H3: Full (7-8 pax)
A4: Depreciation | B4: =(Pricing!C5)*'Base Operating Costs'!B14 -> 35.179303 | E4: Low | F4: =('Pricing Calculator'!$C$9*(1+'Pricing Policies'!$C5/100)*'Pricing Policies'!D$4*IF(Pricing!$C$4="TRF",1,(1+Markups!$B$4/100)))+('Pricing Calculator'!$C$14*(1+Markups!$B$5/100)+'Pricing Calculator'!$B$11) -> 433.9574 | G4: =('Pricing Calculator'!$C$9*(1+'Pricing Policies'!$C5/100)*'Pricing Policies'!E$4*IF(Pricing!$C$4="TRF",1,(1+Markups!$B$4/100)))+('Pricing Calculator'!$C$14*(1+Markups!$B$5/100)+'Pricing Calculator'!$B$11) -> 510.53812 | H4: =('Pricing Calculator'!$C$9*(1+'Pricing Policies'!$C5/100)*'Pricing Policies'!F$4*IF(Pricing!$C$4="TRF",1,(1+Markups!$B$4/100)))+('Pricing Calculator'!$C$14*(1+Markups!$B$5/100)+'Pricing Calculator'!$B$11) -> 612.64574
A5: Costi fissi | B5: ='Base Operating Costs'!B15*(Pricing!C5) -> 40.250469 | E5: Average | F5: =('Pricing Calculator'!$C$9*(1+'Pricing Policies'!$C6/100)*'Pricing Policies'!D$4*IF(Pricing!$C$4="TRF",1,(1+Markups!$B$4/100)))+('Pricing Calculator'!$C$14*(1+Markups!$B$5/100)+'Pricing Calculator'!$B$11) -> 462.67517 | G5: =('Pricing Calculator'!$C$9*(1+'Pricing Policies'!$C6/100)*'Pricing Policies'!E$4*IF(Pricing!$C$4="TRF",1,(1+Markups!$B$4/100)))+('Pricing Calculator'!$C$14*(1+Markups!$B$5/100)+'Pricing Calculator'!$B$11) -> 544.32373 | H5: =('Pricing Calculator'!$C$9*(1+'Pricing Policies'!$C6/100)*'Pricing Policies'!F$4*IF(Pricing!$C$4="TRF",1,(1+Markups!$B$4/100)))+('Pricing Calculator'!$C$14*(1+Markups!$B$5/100)+'Pricing Calculator'!$B$11) -> 653.18847
A6: Driver Cost | B6: =Pricing!C7*'Base Operating Costs'!$B$4 -> 176 | E6: High | F6: =('Pricing Calculator'!$C$9*(1+'Pricing Policies'!$C7/100)*'Pricing Policies'!D$4*IF(Pricing!$C$4="TRF",1,(1+Markups!$B$4/100)))+('Pricing Calculator'!$C$14*(1+Markups!$B$5/100)+'Pricing Calculator'!$B$11) -> 505.75182 | G6: =('Pricing Calculator'!$C$9*(1+'Pricing Policies'!$C7/100)*'Pricing Policies'!E$4*IF(Pricing!$C$4="TRF",1,(1+Markups!$B$4/100)))+('Pricing Calculator'!$C$14*(1+Markups!$B$5/100)+'Pricing Calculator'!$B$11) -> 595.00214 | H6: =('Pricing Calculator'!$C$9*(1+'Pricing Policies'!$C7/100)*'Pricing Policies'!F$4*IF(Pricing!$C$4="TRF",1,(1+Markups!$B$4/100)))+('Pricing Calculator'!$C$14*(1+Markups!$B$5/100)+'Pricing Calculator'!$B$11) -> 714.00257
A7: Tolls | B7: =Pricing!C10 -> 0
A8: Service Extension | B8: 0
A9: Total Cost Transport | B9: =B3+B4+B5+B6+B7 -> 298.92977 | C9: =B9*((100+'Pricing Policies'!$I$4*EXP(-1*Pricing!$C$5/'Pricing Policies'!$I$5))/100)*IF(Pricing!$C$5<'Pricing Policies'!$I$7,1,(100-('Pricing Policies'!$I$6/100*Pricing!$C$5)+('Pricing Policies'!$I$7*'Pricing Policies'!$I$6/100))/100) -> 300.31654 | E9: ESPERIENZE | K9: 66
A10: Service extention hour cost | B10: {=Pricing!C8*(INDEX('Pricing Policies'!A17:F22,MATCH(Pricing!B14,'Pricing Policies'!A17:A22,0),MATCH(Pricing!B15,'Pricing Policies'!A17:F17,0)))} -> 0 | F10: Car (2pax) | G10: Van (3-6 pax) | H10: Full (7-8 pax) | K10: 77
A11: Total Extention | B11: =B10 -> 0 | E11: Low | F11: ='Pricing Calculator'!$B$16*(1+'Pricing Policies'!$C12/100)*'Pricing Policies'!D$11 -> 147 | G11: ='Pricing Calculator'!$B$16*(1+'Pricing Policies'!$C12/100)*'Pricing Policies'!E$11 -> 161.7 | H11: ='Pricing Calculator'!$B$16*(1+'Pricing Policies'!$C12/100)*'Pricing Policies'!F$11 -> 176.4 | K11: 88
A12: Only Driver add.km cost | B12: =(Pricing!C6)*'Base Operating Costs'!$B$16 -> 0 | C12: =B12*((100+'Pricing Policies'!$I$9*EXP(-1*Pricing!$C$6/'Pricing Policies'!$I$10))/100)*IF(Pricing!$C$6<'Pricing Policies'!$I$12,1,(100-('Pricing Policies'!$I$11/100*Pricing!$C$6)+('Pricing Policies'!$I$12*'Pricing Policies'!$I$11/100))/100) -> 0 | E12: Average | F12: ='Pricing Calculator'!$B$16*(1+'Pricing Policies'!$C13/100)*'Pricing Policies'!D$11 -> 154 | G12: ='Pricing Calculator'!$B$16*(1+'Pricing Policies'!$C13/100)*'Pricing Policies'!E$11 -> 169.4 | H12: ='Pricing Calculator'!$B$16*(1+'Pricing Policies'!$C13/100)*'Pricing Policies'!F$11 -> 184.8
A13: Only Driver add. hour cost | B13: {=Pricing!C9*(INDEX('Pricing Policies'!A17:F22,MATCH("Vuoto",'Pricing Policies'!A17:A22,0),MATCH(Pricing!B15,'Pricing Policies'!A17:F17,0)))} -> 0 | E13: High | F13: ='Pricing Calculator'!$B$16*(1+'Pricing Policies'!$C14/100)*'Pricing Policies'!D$11 -> 163.8 | G13: ='Pricing Calculator'!$B$16*(1+'Pricing Policies'!$C14/100)*'Pricing Policies'!E$11 -> 180.18 | H13: ='Pricing Calculator'!$B$16*(1+'Pricing Policies'!$C14/100)*'Pricing Policies'!F$11 -> 196.56
A14: Total Only Driver Cost | B14: =B12+B13 -> 0 | C14: =MAX(B13,C12) -> 0
A15: Experiences | B15: =Pricing!C12*Pricing!C11 -> 140
A16: Total Cost Experiences | B16: =B15 -> 140 | E16: ESTENSIONE DI SERVIZIO O TRASFERIMENTO
F17: Car (2pax) | G17: Van (3-6 pax) | H17: Full (7-8 pax)
E18: Vuoto | F18: ='Base Operating Costs'!$B$5*'Pricing Policies'!D$18*'Pricing Policies'!$B19 -> 49.203 | G18: ='Base Operating Costs'!$B$5*'Pricing Policies'!E$18*'Pricing Policies'!$B19 -> 54.67 | H18: ='Base Operating Costs'!$B$5*'Pricing Policies'!F$18*'Pricing Policies'!$B19 -> 60.137
E19: Low | F19: ='Base Operating Costs'!$B$5*'Pricing Policies'!D$18*'Pricing Policies'!$B20 -> 58.905 | G19: ='Base Operating Costs'!$B$5*'Pricing Policies'!E$18*'Pricing Policies'!$B20 -> 65.45 | H19: ='Base Operating Costs'!$B$5*'Pricing Policies'!F$18*'Pricing Policies'!$B20 -> 71.995
E20: Average | F20: ='Base Operating Costs'!$B$5*'Pricing Policies'!D$18*'Pricing Policies'!$B21 -> 69.3 | G20: ='Base Operating Costs'!$B$5*'Pricing Policies'!E$18*'Pricing Policies'!$B21 -> 77 | H20: ='Base Operating Costs'!$B$5*'Pricing Policies'!F$18*'Pricing Policies'!$B21 -> 84.7
E21: High | F21: ='Base Operating Costs'!$B$5*'Pricing Policies'!D$18*'Pricing Policies'!$B22 -> 79.695 | G21: ='Base Operating Costs'!$B$5*'Pricing Policies'!E$18*'Pricing Policies'!$B22 -> 88.55 | H21: ='Base Operating Costs'!$B$5*'Pricing Policies'!F$18*'Pricing Policies'!$B22 -> 97.405
K22: {=(INDEX('Pricing Policies'!A17:F22,MATCH("Vuoto",'Pricing Policies'!A17:A22,0),MATCH(Pricing!B15,'Pricing Policies'!A17:F17,0)))}

Sheet Pricing Policies
A2: SERVIZIO | H2: RETTIFICHE SU BASE CHILOMETRAGGIO
D3: Car (2pax) | E3: Van (3-6 pax) | F3: Full (7-8 pax) | H3: COSTO MACCHINA CON PASSEGGERI
D4: 0.85 | E4: 1 | F4: 1.2 | H4: MAX Addition per 0 km | I4: 120
A5: Low | B5: 0.8 | C5: =Markups!B2*B5 -> 36 | H5: Velocità Decadimento | I5: 45
A6: Average | B6: 1 | C6: =Markups!B2*B6 -> 45 | H6: Velocità attenuazione | I6: 5
A7: High | B7: 1.3 | C7: =Markups!B2*B7 -> 58.5 | H7: Soglia attenuazione | I7: 600
H8: COSTO MACCHINA SOLO DRIVER
A9: ESPERIENZE | H9: MAX Addition per 0 km | I9: 60
D10: Car (2pax) | E10: Van (3-6 pax) | F10: Full (7-8 pax) | H10: Velocità Decadimento | I10: 30
D11: 1 | E11: 1.1 | F11: 1.2 | H11: Velocità attenuazione | I11: 25
A12: Low | B12: 0.5 | C12: =Markups!B3*B12 -> 5 | H12: Soglia attenuazione | I12: 60
A13: Average | B13: 1 | C13: =Markups!B3*B13 -> 10
A14: High | B14: 1.7 | C14: =Markups!B3*B14 -> 17
A16: ESTENSIONE DI SERVIZIO O TRASFERIMENTO
D17: Car (2pax) | E17: Van (3-6 pax) | F17: Full (7-8 pax)
D18: 0.9 | E18: 1 | F18: 1.1
A19: Vuoto | B19: 0.71
A20: Low | B20: 0.85
A21: Average | B21: 1
A22: High | B22: 1.15

Sheet Markups
A1: MARKUPS
A2: Base markup transport | B2: 45
A3: Base markup experiences | B3: 10
A4: Additional tour markup | B4: 25
A5: Only driver markup | B5: 0

Sheet Base Operating Costs
A1: BASE OPERATING COSTS
A2: Fuel Price (€/liter) | B2: =SUM(B8:B9) -> 1.9
A3: Toll Rate (€/km) | B3: ='Annual Fixed Expenses'!B20/'Vehicle Assumptions'!B8 -> 0.0245
A4: Driver Cost (€/hour) | B4: 22
A5: Standard Vehicle Cost (€/hour) | B5: 77
A7: FUEL COST BREAKDOWN (per liter)
A8: Fuel price (per liter) | B8: 1.8
A9: Adblue price(per oil liter) | B9: 0.1
A10: TOTALE COSTO CARBURANTE PER LITRO | B10: =SUM(B8:B9) -> 1.9
A12: CALCULATED COSTS (per km)
A13: Fuel Cost per km | B13: =B2/'Vehicle Assumptions'!B2 -> 0.19
A14: Depreciation per km | B14: =IF(OR('Vehicle Assumptions'!B7=0,'Vehicle Assumptions'!B7>'Vehicle Assumptions'!B6),SUM('Vehicle Depreciation'!I3:I12)/SUM('Vehicle Depreciation'!F3:F12),VLOOKUP('Vehicle Assumptions'!B7,'Vehicle Depreciation'!A2:I12,9)) -> 0.14071721
A15: Costi annuali fissi per km | B15: ='Annual Fixed Expenses'!B14/'Vehicle Assumptions'!B8 -> 0.16100187
A16: Total Variable Cost per km | B16: =B13+B14+B15 -> 0.49171909

Sheet Vehicle Assumptions
A1: VEHICLE ASSUMPTIONS
A2: Fuel Consumption (km/liter) | B2: 10
A3: Vehicle Cost (€) | B3: 67500
A4: Vehicle Residual Value | B4: {=MIN(IF('Vehicle Depreciation'!G3:G12>0,'Vehicle Depreciation'!G3:G12))} -> 28327.869
A5: Vehicle Life (km) | B5: 250000
A6: Vehicle Life (years) | B6: =SUM('Vehicle Depreciation'!F3:F12) -> 3
A7: Vehicle Age (years) | B7: 0
A8: Annual Vehicle Usage (km) | B8: 80000

Sheet Annual Fixed Expenses
A2: ANNUAL FIXED EXPENSES
A3: Assicurazione | B3: 2500
A4: Bollo | B4: 400
A5: Revisione | B5: 100
A6: Tagliandi | B6: 3000
A7: Gomme | B7: ='Annual Fixed Expenses'!B25 -> 2000
A9: Carrozziere | B9: 1000
A10: Meccanico | B10: 1000
A11: Lavaggi | B11: 1200
A12: Incidenza costi forfettari | B12: 0.15
A13: Costi vari forfettari | B13: =SUM(B3:B11)*B12 -> 1680
A14: TOTALE | B14: =SUM(B3:B13) -> 12880.15
A16: COSTO PEDAGGIO PER ANNO
A17: Toll average price (per km) | B17: 0.07
A18: % KM on toll roads | B18: 0.35
A19: Toll share (km) | B19: ='Vehicle Assumptions'!B8*B18 -> 28000
A20: TOTALE COSTO PEDAGGIO PER ANNO | B20: =B17*B19 -> 1960
A22: COSTO GOMME PER ANNO
A23: Cambio ogni KM | B23: 40000
A24: Costo del ricambio gomme | B24: 1000
A25: TOTALE COSTO GOMME PER ANNO | B25: ='Vehicle Assumptions'!B8/B23*B24 -> 2000

Sheet Attenuazione
A1: KM | B1: COSTO | C1: CORRETTO
A2: 0 | B2: =A2*I$21 -> 0 | C2: =B2*((100+$I$22*EXP(-1*A2/$I$23))/100)*IF(A2<$I$25,1,(100-($I$24/100*A2)+($I$25*$I$24/100))/100) -> 0
A3: 10 | B3: =A3*I$21 -> 10 | C3: =B3*((100+$I$22*EXP(-1*A3/$I$23))/100)*IF(A3<$I$25,1,(100-($I$24/100*A3)+($I$25*$I$24/100))/100) -> 19.608849
A4: 20 | B4: =A4*I$21 -> 20 | C4: =B4*((100+$I$22*EXP(-1*A4/$I$23))/100)*IF(A4<$I$25,1,(100-($I$24/100*A4)+($I$25*$I$24/100))/100) -> 35.388329
A5: 30 | B5: =A5*I$21 -> 30 | C5: =B5*((100+$I$22*EXP(-1*A5/$I$23))/100)*IF(A5<$I$25,1,(100-($I$24/100*A5)+($I$25*$I$24/100))/100) -> 48.483016
A6: 40 | B6: =A6*I$21 -> 40 | C6: =B6*((100+$I$22*EXP(-1*A6/$I$23))/100)*IF(A6<$I$25,1,(100-($I$24/100*A6)+($I$25*$I$24/100))/100) -> 59.73339
A7: 50 | B7: =A7*I$21 -> 50 | C7: =B7*((100+$I$22*EXP(-1*A7/$I$23))/100)*IF(A7<$I$25,1,(100-($I$24/100*A7)+($I$25*$I$24/100))/100) -> 69.751579
A8: 60 | B8: =A8*I$21 -> 60 | C8: =B8*((100+$I$22*EXP(-1*A8/$I$23))/100)*IF(A8<$I$25,1,(100-($I$24/100*A8)+($I$25*$I$24/100))/100) -> 78.978994
A9: 70 | B9: =A9*I$21 -> 70 | C9: =B9*((100+$I$22*EXP(-1*A9/$I$23))/100)*IF(A9<$I$25,1,(100-($I$24/100*A9)+($I$25*$I$24/100))/100) -> 87.730055
A10: 80 | B10: =A10*I$21 -> 80 | C10: =B10*((100+$I$22*EXP(-1*A10/$I$23))/100)*IF(A10<$I$25,1,(100-($I$24/100*A10)+($I$25*$I$24/100))/100) -> 96.225278
A11: 90 | B11: =A11*I$21 -> 90 | C11: =B11*((100+$I$22*EXP(-1*A11/$I$23))/100)*IF(A11<$I$25,1,(100-($I$24/100*A11)+($I$25*$I$24/100))/100) -> 104.61621
A12: 100 | B12: =A12*I$21 -> 100 | C12: =B12*((100+$I$22*EXP(-1*A12/$I$23))/100)*IF(A12<$I$25,1,(100-($I$24/100*A12)+($I$25*$I$24/100))/100) -> 113.00416
A13: 110 | B13: =A13*I$21 -> 110 | C13: =B13*((100+$I$22*EXP(-1*A13/$I$23))/100)*IF(A13<$I$25,1,(100-($I$24/100*A13)+($I$25*$I$24/100))/100) -> 121.45421
... A20: 180 | B20: =A20*I$21 -> 180 | C20: =B20*((100+$I$22*EXP(-1*A20/$I$23))/100)*IF(A20<$I$25,1,(100-($I$24/100*A20)+($I$25*$I$24/100))/100) -> 183.95618
A21: 190 | B21: =A21*I$21 -> 190 | C21: =B21*((100+$I$22*EXP(-1*A21/$I$23))/100)*IF(A21<$I$25,1,(100-($I$24/100*A21)+($I$25*$I$24/100))/100) -> 193.34385 | I21: 1
A22: 200 | B22: =A22*I$21 -> 200 | C22: =B22*((100+$I$22*EXP(-1*A22/$I$23))/100)*IF(A22<$I$25,1,(100-($I$24/100*A22)+($I$25*$I$24/100))/100) -> 202.81847 | H22: MAX Addition per 0 km | I22: 120
A23: 210 | B23: =A23*I$21 -> 210 | C23: =B23*((100+$I$22*EXP(-1*A23/$I$23))/100)*IF(A23<$I$25,1,(100-($I$24/100*A23)+($I$25*$I$24/100))/100) -> 212.3697 | H23: Velocità Decadimento | I23: 45
A24: 220 | B24: =A24*I$21 -> 220 | C24: =B24*((100+$I$22*EXP(-1*A24/$I$23))/100)*IF(A24<$I$25,1,(100-($I$24/100*A24)+($I$25*$I$24/100))/100) -> 221.98786 | H24: Velocità attenuazione | I24: 5
A25: 230 | B25: =A25*I$21 -> 230 | C25: =B25*((100+$I$22*EXP(-1*A25/$I$23))/100)*IF(A25<$I$25,1,(100-($I$24/100*A25)+($I$25*$I$24/100))/100) -> 231.66411 | H25: Soglia attenuazione | I25: 600
A26: 240 | B26: =A26*I$21 -> 240 | C26: =B26*((100+$I$22*EXP(-1*A26/$I$23))/100)*IF(A26<$I$25,1,(100-($I$24/100*A26)+($I$25*$I$24/100))/100) -> 241.39045
A27: 250 | B27: =A27*I$21 -> 250 | C27: =B27*((100+$I$22*EXP(-1*A27/$I$23))/100)*IF(A27<$I$25,1,(100-($I$24/100*A27)+($I$25*$I$24/100))/100) -> 251.15978
A28: 260 | B28: =A28*I$21 -> 260 | C28: =B28*((100+$I$22*EXP(-1*A28/$I$23))/100)*IF(A28<$I$25,1,(100-($I$24/100*A28)+($I$25*$I$24/100))/100) -> 260.96582
A29: 270 | B29: =A29*I$21 -> 270 | C29: =B29*((100+$I$22*EXP(-1*A29/$I$23))/100)*IF(A29<$I$25,1,(100-($I$24/100*A29)+($I$25*$I$24/100))/100) -> 270.80312
A30: 280 | B30: =A30*I$21 -> 280 | C30: =B30*((100+$I$22*EXP(-1*A30/$I$23))/100)*IF(A30<$I$25,1,(100-($I$24/100*A30)+($I$25*$I$24/100))/100) -> 280.6669
A31: 290 | B31: =A31*I$21 -> 290 | C31: =B31*((100+$I$22*EXP(-1*A31/$I$23))/100)*IF(A31<$I$25,1,(100-($I$24/100*A31)+($I$25*$I$24/100))/100) -> 290.55309
A32: 300 | B32: =A32*I$21 -> 300 | C32: =B32*((100+$I$22*EXP(-1*A32/$I$23))/100)*IF(A32<$I$25,1,(100-($I$24/100*A32)+($I$25*$I$24/100))/100) -> 300.45815
A33: 310 | B33: =A33*I$21 -> 310 | C33: =B33*((100+$I$22*EXP(-1*A33/$I$23))/100)*IF(A33<$I$25,1,(100-($I$24/100*A33)+($I$25*$I$24/100))/100) -> 310.37908
A34: 320 | B34: =A34*I$21 -> 320 | C34: =B34*((100+$I$22*EXP(-1*A34/$I$23))/100)*IF(A34<$I$25,1,(100-($I$24/100*A34)+($I$25*$I$24/100))/100) -> 320.31334
A35: 330 | B35: =A35*I$21 -> 330 | C35: =B35*((100+$I$22*EXP(-1*A35/$I$23))/100)*IF(A35<$I$25,1,(100-($I$24/100*A35)+($I$25*$I$24/100))/100) -> 330.25874
A36: 340 | B36: =A36*I$21 -> 340 | C36: =B36*((100+$I$22*EXP(-1*A36/$I$23))/100)*IF(A36<$I$25,1,(100-($I$24/100*A36)+($I$25*$I$24/100))/100) -> 340.21346
A37: 350 | B37: =A37*I$21 -> 350 | C37: =B37*((100+$I$22*EXP(-1*A37/$I$23))/100)*IF(A37<$I$25,1,(100-($I$24/100*A37)+($I$25*$I$24/100))/100) -> 350.17596
... A102: 1000 | B102: =A102*I$21 -> 1000 | C102: =B102*((100+$I$22*EXP(-1*A102/$I$23))/100)*IF(A102<$I$25,1,(100-($I$24/100*A102)+($I$25*$I$24/100))/100) -> 800

Sheet Tour List
A1: NOME | C1: DURATION | D1: HRs | E1: KMs | F1: TOLL | G1: ESP A | H1: ESP B | I1: ESP C | J1: ESP D | K1: ESPERIENZE p.p.
A2: Personalizzato | D2: 0 | E2: 0 | F2: 0 | G2: 0 | H2: 0 | I2: 0 | J2: 0 | K2: =SUM(G2:J2) -> 0
A3: =CONCATENATE(B3, " - ",C3) -> Chianti Classico - TOUR HD | B3: Chianti Classico | C3: TOUR HD | D3: 5 | E3: 150 | F3: 0 | G3: 50 | H3: 20 | I3: 0 | J3: 0 | K3: =SUM(G3:J3) -> 70
A4: =CONCATENATE(B4, " - ",C4) -> Montalcino - TOUR HD | B4: Montalcino | C4: TOUR HD | D4: 5 | E4: 150 | F4: 0 | G4: 50 | H4: 20 | I4: 0 | J4: 0 | K4: =SUM(G4:J4) -> 70
A5: =CONCATENATE(B5, " - ",C5) -> Monteriggioni-SanGi - TOUR HD | B5: Monteriggioni-SanGi | C5: TOUR HD | D5: 5 | E5: 150 | F5: 0
A6: =CONCATENATE(B6, " - ",C6) -> Modena - TOUR FD+ | B6: Modena | C6: TOUR FD+ | D6: 10 | E6: 400 | F6: 20
A7: =CONCATENATE(B7, " - ",C7) -> Bolgheri - TOUR FD+ | B7: Bolgheri | C7: TOUR FD+ | D7: 10 | E7: 400 | F7: 0
A8: =CONCATENATE(B8, " - ",C8) -> Suvereto - TOUR FD+ | B8: Suvereto | C8: TOUR FD+ | D8: 10 | E8: 400 | F8: 0
A9: =CONCATENATE(B9, " - ",C9) -> Chianti Classico - TOUR FD | B9: Chianti Classico | C9: TOUR FD | D9: 8 | E9: 250 | F9: 0 | G9: 50 | H9: 20 | I9: 0 | J9: 0 | K9: =SUM(G9:J9) -> 70
A10: =CONCATENATE(B10, " - ",C10) -> Montalcino-Pienza - TOUR FD | B10: Montalcino-Pienza | C10: TOUR FD | D10: 9 | E10: 250 | F10: 0 | G10: 50 | H10: 20 | I10: 0 | J10: 0 | K10: =SUM(G10:J10) -> 70
A11: =CONCATENATE(B11, " - ",C11) -> Pisa-Lucca - TOUR FD | B11: Pisa-Lucca | C11: TOUR FD | D11: 9 | E11: 300 | F11: 0
A12: =CONCATENATE(B12, " - ",C12) -> Monteriggioni-SanGi-Volterra - TOUR FD | B12: Monteriggioni-SanGi-Volterra | C12: TOUR FD | D12: 9 | E12: 250 | F12: 0
A13: =CONCATENATE(B13, " - ",C13) -> Assisi - TOUR FD | B13: Assisi | C13: TOUR FD | D13: 9 | E13: 300 | F13: 0
A14: =CONCATENATE(B14, " - ",C14) -> Siena - TRF | B14: Siena | C14: TRF | D14: 1 | E14: 10 | F14: 0
A15: =CONCATENATE(B15, " - ",C15) -> Siena dintorni - TRF | B15: Siena dintorni | C15: TRF | D15: 2 | E15: 30 | F15: 0
A16: =CONCATENATE(B16, " - ",C16) -> Arezzo - TRF | B16: Arezzo | C16: TRF | D16: 3 | E16: 180 | F16: 0
A17: =CONCATENATE(B17, " - ",C17) -> Chiusi - TRF | B17: Chiusi | C17: TRF | D17: 3 | E17: 180 | F17: 5
A18: =CONCATENATE(B18, " - ",C18) -> Civitavecchia - TRF | B18: Civitavecchia | C18: TRF | D18: 5 | E18: 370 | F18: 5
A19: =CONCATENATE(B19, " - ",C19) -> Cortona - TRF | B19: Cortona | C19: TRF | D19: 3 | E19: 150 | F19: 0
A20: =CONCATENATE(B20, " - ",C20) -> Grosseto - TRF | B20: Grosseto | C20: TRF | D20: 3 | E20: 150 | F20: 0
A21: =CONCATENATE(B21, " - ",C21) -> Como - TRF | B21: Como | C21: TRF | D21: 10 | E21: 840 | F21: 65
A22: =CONCATENATE(B22, " - ",C22) -> Bologna - TRF | B22: Bologna | C22: TRF | D22: 5 | E22: 340 | F22: 20
... A43: =CONCATENATE(B43, " - ",C43) -> Venezia - TRF | B43: Venezia | C43: TRF | D43: 8 | E43: 640 | F43: 45

Sheet Copia di Tour List
M1: Soglia Attenuazione | N1: Tasso attenuazione | O1: Massimo aumento | P1: Velocità decadimento | T1: Selezionare scenario di prezzo: L = LOW; A = AVERAGE; H = HIGH; C = CAR; V = VAN; F = FULL Selezionare solo una colonna | AC1: Pax riferimento | AE1: Selezionare scenario di prezzo: L = LOW; A = AVERAGE; H = HIGH; C = CAR; V = VAN; F = FULL Selezionare solo una colonna | AR1: VAT riferimento | AT1: Card Fees riferimento | AY1: % per Driver
M2: 600 | N2: 10 | O2: 120 | P2: 45 | T2: FALSE | U2: TRUE | V2: FALSE | W2: FALSE | X2: FALSE | Y2: FALSE | Z2: FALSE | AA2: FALSE | AB2: FALSE | AC2: 2 | AE2: FALSE | AF2: TRUE | AG2: FALSE | AH2: FALSE | AI2: FALSE | AJ2: FALSE | AK2: FALSE | AL2: FALSE | AM2: FALSE | AR2: 0.1 | AT2: 0.05 | AY2: 0.25
A3: NOME | C3: DURATION | D3: HRs | E3: KMs | F3: TOLL | G3: ESP A | H3: ESP B | I3: ESP C | J3: ESP D | K3: ESPERIENZE p.p. | M3: Fuel Cost | N3: Depreciation | O3: Costi fissi | P3: Driver Cost | Q3: Tolls | R3: Cost Transport | S3: Cost TransportCorrected | T3: CL | U3: CA | V3: CH | W3: VL | X3: VA | Y3: VH | Z3: FL | AA3: FA | AB3: FH | AC3: Pax | AD3: Costo Esperience | AE3: LL | AF3: LA | AG3: LH | AH3: AL | AI3: AH | AJ3: AA | AK3: HL | AL3: HA | AM3: HH | AN3: TOT TRASP | AO3: TOT ESPERIENZE | AP3: TOT CALCOLATO | AQ3: TOTALE | AR3: VAT | AS3: VAT € | AT3: CC FEES | AU3: CC FEES € | AW3: TOTALE VENDITA | AX3: IMPONIBILE | AY3: COSTO DRIVER | AZ3: COSTO ORA | BA3: COSTO CORRETTO | BC3: COSTO MEDIO | BD3: =AVERAGE(AZ5:AZ45) -> 19.460154 | BF3: 1728 | BG3: =BD5*BF3 -> 33022.173
A4: Personalizzato | D4: 0 | E4: 0 | F4: 0 | G4: 0 | H4: 0 | I4: 0 | J4: 0 | K4: =SUM(G4:J4) -> 0 | M4: =(E4)*'Base Operating Costs'!$B$13 -> 0 | N4: =(E4)*'Base Operating Costs'!$B$14 -> 0 | O4: ='Base Operating Costs'!$B$15*(E4) -> 0 | P4: =D4*'Base Operating Costs'!$B$4 -> 0 | Q4: =F4 -> 0 | S4: =M4+N4+O4+P4+Q4 -> 0 | T4: =S4*(1+'Pricing Policies'!$C$5/100)*'Pricing Policies'!$D$4*IF($C4="TRF",1,(1+Markups!$B$4/100)) -> 0 | U4: =S4*(1+'Pricing Policies'!$C$5/100)*'Pricing Policies'!$E$4*IF($C4="TRF",1,(1+Markups!$B$4/100)) -> 0 | V4: =S4*(1+'Pricing Policies'!$C$5/100)*'Pricing Policies'!$F$4*IF($C4="TRF",1,(1+Markups!$B$4/100)) -> 0 | W4: =S4*(1+'Pricing Policies'!$C$6/100)*'Pricing Policies'!$D$4*IF($C4="TRF",1,(1+Markups!$B$4/100)) -> 0 | X4: =S4*(1+'Pricing Policies'!$C$6/100)*'Pricing Policies'!$E$4*IF($C4="TRF",1,(1+Markups!$B$4/100)) -> 0 | Y4: =S4*(1+'Pricing Policies'!$C$6/100)*'Pricing Policies'!$F$4*IF($C4="TRF",1,(1+Markups!$B$4/100)) -> 0 | Z4: =S4*(1+'Pricing Policies'!$C$7/100)*'Pricing Policies'!$D$4*IF($C4="TRF",1,(1+Markups!$B$4/100)) -> 0 | AA4: =S4*(1+'Pricing Policies'!$C$7/100)*'Pricing Policies'!$E$4*IF($C4="TRF",1,(1+Markups!$B$4/100)) -> 0 | AB4: =S4*(1+'Pricing Policies'!$C$7/100)*'Pricing Policies'!$F$4*IF($C4="TRF",1,(1+Markups!$B$4/100)) -> 0 | AC4: =AC$2 -> 2 | AD4: =AC4*K4 -> 0 | AE4: =AD4*(1+'Pricing Policies'!$C$12/100)*'Pricing Policies'!$D$11 -> 0 | AF4: =AD4*(1+'Pricing Policies'!$C$12/100)*'Pricing Policies'!$E$11 -> 0 | AG4: =AD4*(1+'Pricing Policies'!$C$12/100)*'Pricing Policies'!$F$11 -> 0 | AH4: =AD4*(1+'Pricing Policies'!$C$13/100)*'Pricing Policies'!$D$11 -> 0 | AI4: =AD4*(1+'Pricing Policies'!$C$13/100)*'Pricing Policies'!$E$11 -> 0 | AJ4: =AD4*(1+'Pricing Policies'!$C$13/100)*'Pricing Policies'!$F$11 -> 0 | AK4: =AD4*(1+'Pricing Policies'!$C$14/100)*'Pricing Policies'!$D$11 -> 0 | AL4: =AD4*(1+'Pricing Policies'!$C$14/100)*'Pricing Policies'!$E$11 -> 0 | AM4: =AD4*(1+'Pricing Policies'!$C$14/100)*'Pricing Policies'!$F$11 -> 0 | AN4: =(T$2*T4+U$2*U4+V$2*V4+W$2*W4+X$2*X4+Y$2*Y4+Z$2*Z4+AA$2*AA4+AB$2*AB4) -> 0 | AO4: =(AE$2*AE4+AF$2*AF4+AG$2*AG4+AH$2*AH4+AI$2*AI4+AJ$2*AJ4+AK$2*AK4+AL$2*AL4+AM$2*AM4) -> 0 | AQ4: =AN4+AO4 -> 0 | AR4: =AR$2 -> 0.1 | AS4: =AQ4*AR4 -> 0 | AT4: =AT$2 -> 0.05 | AU4: =(AQ4+AS4)*AT4 -> 0 | AW4: =AQ4+AS4+AU4 -> 0 | AX4: =AW4-AU4-AS4-AD4 -> 0 | AY4: =AX4*AY$2 -> 0 | AZ4: =AY4/D4 -> #DIV/0!
A5: =CONCATENATE(B5, " - ",C5) -> Chianti Classico - TOUR HD | B5: Chianti Classico | C5: TOUR HD | D5: 5 | E5: 150 | F5: 0 | G5: 50 | H5: 20 | I5: 0 | J5: 0 | K5: =SUM(G5:J5) -> 70 | M5: =(E5)*'Base Operating Costs'!$B$13 -> 28.5 | N5: =(E5)*'Base Operating Costs'!$B$14 -> 21.107582 | O5: ='Base Operating Costs'!$B$15*(E5) -> 24.150281 | P5: =D5*'Base Operating Costs'!$B$4 -> 110 | Q5: =F5 -> 0 | R5: =M5+N5+O5+P5+Q5 -> 183.75786 | S5: =R5*((100+O$2*EXP(-1*E5/P$2))/100)*IF(E5<M$2,1,(1-(N$2/100))) -> 191.62432 | T5: =S5*(1+'Pricing Policies'!$C$5/100)*'Pricing Policies'!$D$4*IF($C5="TRF",1,(1+Markups!$B$4/100)) -> 276.89714 | U5: =S5*(1+'Pricing Policies'!$C$5/100)*'Pricing Policies'!$E$4*IF($C5="TRF",1,(1+Markups!$B$4/100)) -> 325.76134 | V5: =S5*(1+'Pricing Policies'!$C$5/100)*'Pricing Policies'!$F$4*IF($C5="TRF",1,(1+Markups!$B$4/100)) -> 390.9136 | W5: =S5*(1+'Pricing Policies'!$C$6/100)*'Pricing Policies'!$D$4*IF($C5="TRF",1,(1+Markups!$B$4/100)) -> 295.22121 | X5: =S5*(1+'Pricing Policies'!$C$6/100)*'Pricing Policies'!$E$4*IF($C5="TRF",1,(1+Markups!$B$4/100)) -> 347.31907 | Y5: =S5*(1+'Pricing Policies'!$C$6/100)*'Pricing Policies'!$F$4*IF($C5="TRF",1,(1+Markups!$B$4/100)) -> 416.78289 | Z5: =S5*(1+'Pricing Policies'!$C$7/100)*'Pricing Policies'!$D$4*IF($C5="TRF",1,(1+Markups!$B$4/100)) -> 322.70732 | AA5: =S5*(1+'Pricing Policies'!$C$7/100)*'Pricing Policies'!$E$4*IF($C5="TRF",1,(1+Markups!$B$4/100)) -> 379.65567 | AB5: =S5*(1+'Pricing Policies'!$C$7/100)*'Pricing Policies'!$F$4*IF($C5="TRF",1,(1+Markups!$B$4/100)) -> 455.58681 | AC5: 0 | AD5: =AC5*K5 -> 0 | AE5: =AD5*(1+'Pricing Policies'!$C$12/100)*'Pricing Policies'!$D$11 -> 0 | AF5: =AD5*(1+'Pricing Policies'!$C$12/100)*'Pricing Policies'!$E$11 -> 0 | AG5: =AD5*(1+'Pricing Policies'!$C$12/100)*'Pricing Policies'!$F$11 -> 0 | AH5: =AD5*(1+'Pricing Policies'!$C$13/100)*'Pricing Policies'!$D$11 -> 0 | AI5: =AD5*(1+'Pricing Policies'!$C$13/100)*'Pricing Policies'!$E$11 -> 0 | AJ5: =AD5*(1+'Pricing Policies'!$C$13/100)*'Pricing Policies'!$F$11 -> 0 | AK5: =AD5*(1+'Pricing Policies'!$C$14/100)*'Pricing Policies'!$D$11 -> 0 | AL5: =AD5*(1+'Pricing Policies'!$C$14/100)*'Pricing Policies'!$E$11 -> 0 | AM5: =AD5*(1+'Pricing Policies'!$C$14/100)*'Pricing Policies'!$F$11 -> 0 | AN5: =(T$2*T5+U$2*U5+V$2*V5+W$2*W5+X$2*X5+Y$2*Y5+Z$2*Z5+AA$2*AA5+AB$2*AB5) -> 325.76134 | AO5: =(AE$2*AE5+AF$2*AF5+AG$2*AG5+AH$2*AH5+AI$2*AI5+AJ$2*AJ5+AK$2*AK5+AL$2*AL5+AM$2*AM5) -> 0 | AP5: =AN5+AO5 -> 325.76134 | AQ5: =CEILING(AP5,5) -> 330 | AR5: =AR$2 -> 0.1 | AS5: =AQ5*AR5 -> 33 | AT5: =AT$2 -> 0.05 | AU5: =(AQ5+AS5)*AT5 -> 18.15 | AV5: =AQ5+AS5+AU5 -> 381.15 | AW5: =CEILING(AV5,5) -> 385 | AX5: =AW5-AU5-AS5-AD5 -> 333.85 | AY5: =AX5*AY$2 -> 83.4625 | AZ5: =AY5/D5 -> 16.6925 | BA5: =IF(AZ5<BD$9,BD$9,IF(AZ5>BD$10,BD$10,AZ5)) -> 16.6925 | BC5: COSTO MEDIO CORRETTO | BD5: =AVERAGE(BA5:BA45) -> 19.110054
A6: =CONCATENATE(B6, " - ",C6) -> Montalcino - TOUR HD | B6: Montalcino | C6: TOUR HD | D6: 5 | E6: 150 | F6: 0 | G6: 50 | H6: 20 | I6: 0 | J6: 0 | K6: =SUM(G6:J6) -> 70 | M6: =(E6)*'Base Operating Costs'!$B$13 -> 28.5 | N6: =(E6)*'Base Operating Costs'!$B$14 -> 21.107582 | O6: ='Base Operating Costs'!$B$15*(E6) -> 24.150281 | P6: =D6*'Base Operating Costs'!$B$4 -> 110 | Q6: =F6 -> 0 | R6: =M6+N6+O6+P6+Q6 -> 183.75786 | S6: =R6*((100+O$2*EXP(-1*E6/P$2))/100)*IF(E6<M$2,1,(1-(N$2/100))) -> 191.62432 | T6: =S6*(1+'Pricing Policies'!$C$5/100)*'Pricing Policies'!$D$4*IF($C6="TRF",1,(1+Markups!$B$4/100)) -> 276.89714 | U6: =S6*(1+'Pricing Policies'!$C$5/100)*'Pricing Policies'!$E$4*IF($C6="TRF",1,(1+Markups!$B$4/100)) -> 325.76134 | V6: =S6*(1+'Pricing Policies'!$C$5/100)*'Pricing Policies'!$F$4*IF($C6="TRF",1,(1+Markups!$B$4/100)) -> 390.9136 | W6: =S6*(1+'Pricing Policies'!$C$6/100)*'Pricing Policies'!$D$4*IF($C6="TRF",1,(1+Markups!$B$4/100)) -> 295.22121 | X6: =S6*(1+'Pricing Policies'!$C$6/100)*'Pricing Policies'!$E$4*IF($C6="TRF",1,(1+Markups!$B$4/100)) -> 347.31907 | Y6: =S6*(1+'Pricing Policies'!$C$6/100)*'Pricing Policies'!$F$4*IF($C6="TRF",1,(1+Markups!$B$4/100)) -> 416.78289 | Z6: =S6*(1+'Pricing Policies'!$C$7/100)*'Pricing Policies'!$D$4*IF($C6="TRF",1,(1+Markups!$B$4/100)) -> 322.70732 | AA6: =S6*(1+'Pricing Policies'!$C$7/100)*'Pricing Policies'!$E$4*IF($C6="TRF",1,(1+Markups!$B$4/100)) -> 379.65567 | AB6: =S6*(1+'Pricing Policies'!$C$7/100)*'Pricing Policies'!$F$4*IF($C6="TRF",1,(1+Markups!$B$4/100)) -> 455.58681 | AC6: =AC$2 -> 2 | AD6: =AC6*K6 -> 140 | AE6: =AD6*(1+'Pricing Policies'!$C$12/100)*'Pricing Policies'!$D$11 -> 147 | AF6: =AD6*(1+'Pricing Policies'!$C$12/100)*'Pricing Policies'!$E$11 -> 161.7 | AG6: =AD6*(1+'Pricing Policies'!$C$12/100)*'Pricing Policies'!$F$11 -> 176.4 | AH6: =AD6*(1+'Pricing Policies'!$C$13/100)*'Pricing Policies'!$D$11 -> 154 | AI6: =AD6*(1+'Pricing Policies'!$C$13/100)*'Pricing Policies'!$E$11 -> 169.4 | AJ6: =AD6*(1+'Pricing Policies'!$C$13/100)*'Pricing Policies'!$F$11 -> 184.8 | AK6: =AD6*(1+'Pricing Policies'!$C$14/100)*'Pricing Policies'!$D$11 -> 163.8 | AL6: =AD6*(1+'Pricing Policies'!$C$14/100)*'Pricing Policies'!$E$11 -> 180.18 | AM6: =AD6*(1+'Pricing Policies'!$C$14/100)*'Pricing Policies'!$F$11 -> 196.56 | AN6: =(T$2*T6+U$2*U6+V$2*V6+W$2*W6+X$2*X6+Y$2*Y6+Z$2*Z6+AA$2*AA6+AB$2*AB6) -> 325.76134 | AO6: =(AE$2*AE6+AF$2*AF6+AG$2*AG6+AH$2*AH6+AI$2*AI6+AJ$2*AJ6+AK$2*AK6+AL$2*AL6+AM$2*AM6) -> 161.7 | AP6: =AN6+AO6 -> 487.46134 | AQ6: =CEILING(AP6,5) -> 490 | AR6: =AR$2 -> 0.1 | AS6: =AQ6*AR6 -> 49 | AT6: =AT$2 -> 0.05 | AU6: =(AQ6+AS6)*AT6 -> 26.95 | AV6: =AQ6+AS6+AU6 -> 565.95 | AW6: =CEILING(AV6,5) -> 570 | AX6: =AW6-AU6-AS6-AD6 -> 354.05 | AY6: =AX6*AY$2 -> 88.5125 | AZ6: =AY6/D6 -> 17.7025 | BA6: =IF(AZ6<BD$9,BD$9,IF(AZ6>BD$10,BD$10,AZ6)) -> 17.7025 | BC6: COSTO MINIMO | BD6: =MIN(AZ5:AZ45) -> 15.409722
A7: =CONCATENATE(B7, " - ",C7) -> Monteriggioni-SanGi - TOUR HD | B7: Monteriggioni-SanGi | C7: TOUR HD | D7: 5 | E7: 150 | F7: 0 | M7: =(E7)*'Base Operating Costs'!$B$13 -> 28.5 | N7: =(E7)*'Base Operating Costs'!$B$14 -> 21.107582 | O7: ='Base Operating Costs'!$B$15*(E7) -> 24.150281 | P7: =D7*'Base Operating Costs'!$B$4 -> 110 | Q7: =F7 -> 0 | R7: =M7+N7+O7+P7+Q7 -> 183.75786 | S7: =R7*((100+O$2*EXP(-1*E7/P$2))/100)*IF(E7<M$2,1,(1-(N$2/100))) -> 191.62432 | T7: =S7*(1+'Pricing Policies'!$C$5/100)*'Pricing Policies'!$D$4*IF($C7="TRF",1,(1+Markups!$B$4/100)) -> 276.89714 | U7: =S7*(1+'Pricing Policies'!$C$5/100)*'Pricing Policies'!$E$4*IF($C7="TRF",1,(1+Markups!$B$4/100)) -> 325.76134 | V7: =S7*(1+'Pricing Policies'!$C$5/100)*'Pricing Policies'!$F$4*IF($C7="TRF",1,(1+Markups!$B$4/100)) -> 390.9136 | W7: =S7*(1+'Pricing Policies'!$C$6/100)*'Pricing Policies'!$D$4*IF($C7="TRF",1,(1+Markups!$B$4/100)) -> 295.22121 | X7: =S7*(1+'Pricing Policies'!$C$6/100)*'Pricing Policies'!$E$4*IF($C7="TRF",1,(1+Markups!$B$4/100)) -> 347.31907 | Y7: =S7*(1+'Pricing Policies'!$C$6/100)*'Pricing Policies'!$F$4*IF($C7="TRF",1,(1+Markups!$B$4/100)) -> 416.78289 | Z7: =S7*(1+'Pricing Policies'!$C$7/100)*'Pricing Policies'!$D$4*IF($C7="TRF",1,(1+Markups!$B$4/100)) -> 322.70732 | AA7: =S7*(1+'Pricing Policies'!$C$7/100)*'Pricing Policies'!$E$4*IF($C7="TRF",1,(1+Markups!$B$4/100)) -> 379.65567 | AB7: =S7*(1+'Pricing Policies'!$C$7/100)*'Pricing Policies'!$F$4*IF($C7="TRF",1,(1+Markups!$B$4/100)) -> 455.58681 | AC7: =AC$2 -> 2 | AD7: =AC7*K7 -> 0 | AE7: =AD7*(1+'Pricing Policies'!$C$12/100)*'Pricing Policies'!$D$11 -> 0 | AF7: =AD7*(1+'Pricing Policies'!$C$12/100)*'Pricing Policies'!$E$11 -> 0 | AG7: =AD7*(1+'Pricing Policies'!$C$12/100)*'Pricing Policies'!$F$11 -> 0 | AH7: =AD7*(1+'Pricing Policies'!$C$13/100)*'Pricing Policies'!$D$11 -> 0 | AI7: =AD7*(1+'Pricing Policies'!$C$13/100)*'Pricing Policies'!$E$11 -> 0 | AJ7: =AD7*(1+'Pricing Policies'!$C$13/100)*'Pricing Policies'!$F$11 -> 0 | AK7: =AD7*(1+'Pricing Policies'!$C$14/100)*'Pricing Policies'!$D$11 -> 0 | AL7: =AD7*(1+'Pricing Policies'!$C$14/100)*'Pricing Policies'!$E$11 -> 0 | AM7: =AD7*(1+'Pricing Policies'!$C$14/100)*'Pricing Policies'!$F$11 -> 0 | AN7: =(T$2*T7+U$2*U7+V$2*V7+W$2*W7+X$2*X7+Y$2*Y7+Z$2*Z7+AA$2*AA7+AB$2*AB7) -> 325.76134 | AO7: =(AE$2*AE7+AF$2*AF7+AG$2*AG7+AH$2*AH7+AI$2*AI7+AJ$2*AJ7+AK$2*AK7+AL$2*AL7+AM$2*AM7) -> 0 | AP7: =AN7+AO7 -> 325.76134 | AQ7: =CEILING(AP7,5) -> 330 | AR7: =AR$2 -> 0.1 | AS7: =AQ7*AR7 -> 33 | AT7: =AT$2 -> 0.05 | AU7: =(AQ7+AS7)*AT7 -> 18.15 | AV7: =AQ7+AS7+AU7 -> 381.15 | AW7: =CEILING(AV7,5) -> 385 | AX7: =AW7-AU7-AS7-AD7 -> 333.85 | AY7: =AX7*AY$2 -> 83.4625 | AZ7: =AY7/D7 -> 16.6925 | BA7: =IF(AZ7<BD$9,BD$9,IF(AZ7>BD$10,BD$10,AZ7)) -> 16.6925 | BC7: COSTO MASSIMO | BD7: =MAX(AZ5:AZ45) -> 29.29375
A8: =CONCATENATE(B8, " - ",C8) -> Modena - TOUR FD+ | B8: Modena | C8: TOUR FD+ | D8: 10 | E8: 400 | F8: 20 | M8: =(E8)*'Base Operating Costs'!$B$13 -> 76 | N8: =(E8)*'Base Operating Costs'!$B$14 -> 56.286885 | O8: ='Base Operating Costs'!$B$15*(E8) -> 64.40075 | P8: =D8*'Base Operating Costs'!$B$4 -> 220 | Q8: =F8 -> 20 | R8: =M8+N8+O8+P8+Q8 -> 436.68764 | S8: =R8*((100+O$2*EXP(-1*E8/P$2))/100)*IF(E8<M$2,1,(1-(N$2/100))) -> 436.75991 | T8: =S8*(1+'Pricing Policies'!$C$5/100)*'Pricing Policies'!$D$4*IF($C8="TRF",1,(1+Markups!$B$4/100)) -> 631.11806 | U8: =S8*(1+'Pricing Policies'!$C$5/100)*'Pricing Policies'!$E$4*IF($C8="TRF",1,(1+Markups!$B$4/100)) -> 742.49184 | V8: =S8*(1+'Pricing Policies'!$C$5/100)*'Pricing Policies'!$F$4*IF($C8="TRF",1,(1+Markups!$B$4/100)) -> 890.99021 | W8: =S8*(1+'Pricing Policies'!$C$6/100)*'Pricing Policies'!$D$4*IF($C8="TRF",1,(1+Markups!$B$4/100)) -> 672.88323 | X8: =S8*(1+'Pricing Policies'!$C$6/100)*'Pricing Policies'!$E$4*IF($C8="TRF",1,(1+Markups!$B$4/100)) -> 791.62733 | Y8: =S8*(1+'Pricing Policies'!$C$6/100)*'Pricing Policies'!$F$4*IF($C8="TRF",1,(1+Markups!$B$4/100)) -> 949.95279 | Z8: =S8*(1+'Pricing Policies'!$C$7/100)*'Pricing Policies'!$D$4*IF($C8="TRF",1,(1+Markups!$B$4/100)) -> 735.53098 | AA8: =S8*(1+'Pricing Policies'!$C$7/100)*'Pricing Policies'!$E$4*IF($C8="TRF",1,(1+Markups!$B$4/100)) -> 865.33056 | AB8: =S8*(1+'Pricing Policies'!$C$7/100)*'Pricing Policies'!$F$4*IF($C8="TRF",1,(1+Markups!$B$4/100)) -> 1038.3967 | AC8: =AC$2 -> 2 | AD8: =AC8*K8 -> 0 | AE8: =AD8*(1+'Pricing Policies'!$C$12/100)*'Pricing Policies'!$D$11 -> 0 | AF8: =AD8*(1+'Pricing Policies'!$C$12/100)*'Pricing Policies'!$E$11 -> 0 | AG8: =AD8*(1+'Pricing Policies'!$C$12/100)*'Pricing Policies'!$F$11 -> 0 | AH8: =AD8*(1+'Pricing Policies'!$C$13/100)*'Pricing Policies'!$D$11 -> 0 | AI8: =AD8*(1+'Pricing Policies'!$C$13/100)*'Pricing Policies'!$E$11 -> 0 | AJ8: =AD8*(1+'Pricing Policies'!$C$13/100)*'Pricing Policies'!$F$11 -> 0 | AK8: =AD8*(1+'Pricing Policies'!$C$14/100)*'Pricing Policies'!$D$11 -> 0 | AL8: =AD8*(1+'Pricing Policies'!$C$14/100)*'Pricing Policies'!$E$11 -> 0 | AM8: =AD8*(1+'Pricing Policies'!$C$14/100)*'Pricing Policies'!$F$11 -> 0 | AN8: =(T$2*T8+U$2*U8+V$2*V8+W$2*W8+X$2*X8+Y$2*Y8+Z$2*Z8+AA$2*AA8+AB$2*AB8) -> 742.49184 | AO8: =(AE$2*AE8+AF$2*AF8+AG$2*AG8+AH$2*AH8+AI$2*AI8+AJ$2*AJ8+AK$2*AK8+AL$2*AL8+AM$2*AM8) -> 0 | AP8: =AN8+AO8 -> 742.49184 | AQ8: =CEILING(AP8,5) -> 745 | AR8: =AR$2 -> 0.1 | AS8: =AQ8*AR8 -> 74.5 | AT8: =AT$2 -> 0.05 | AU8: =(AQ8+AS8)*AT8 -> 40.975 | AV8: =AQ8+AS8+AU8 -> 860.475 | AW8: =CEILING(AV8,5) -> 865 | AX8: =AW8-AU8-AS8-AD8 -> 749.525 | AY8: =AX8*AY$2 -> 187.38125 | AZ8: =AY8/D8 -> 18.738125 | BA8: =IF(AZ8<BD$9,BD$9,IF(AZ8>BD$10,BD$10,AZ8)) -> 18.738125
A9: =CONCATENATE(B9, " - ",C9) -> Bolgheri - TOUR FD+ | B9: Bolgheri | C9: TOUR FD+ | D9: 10 | E9: 400 | F9: 0 | M9: =(E9)*'Base Operating Costs'!$B$13 -> 76 | N9: =(E9)*'Base Operating Costs'!$B$14 -> 56.286885 | O9: ='Base Operating Costs'!$B$15*(E9) -> 64.40075 | P9: =D9*'Base Operating Costs'!$B$4 -> 220 | Q9: =F9 -> 0 | R9: =M9+N9+O9+P9+Q9 -> 416.68764 | S9: =R9*((100+O$2*EXP(-1*E9/P$2))/100)*IF(E9<M$2,1,(1-(N$2/100))) -> 416.7566 | T9: =S9*(1+'Pricing Policies'!$C$5/100)*'Pricing Policies'!$D$4*IF($C9="TRF",1,(1+Markups!$B$4/100)) -> 602.21328 | U9: =S9*(1+'Pricing Policies'!$C$5/100)*'Pricing Policies'!$E$4*IF($C9="TRF",1,(1+Markups!$B$4/100)) -> 708.48621 | V9: =S9*(1+'Pricing Policies'!$C$5/100)*'Pricing Policies'!$F$4*IF($C9="TRF",1,(1+Markups!$B$4/100)) -> 850.18345 | W9: =S9*(1+'Pricing Policies'!$C$6/100)*'Pricing Policies'!$D$4*IF($C9="TRF",1,(1+Markups!$B$4/100)) -> 642.06563 | X9: =S9*(1+'Pricing Policies'!$C$6/100)*'Pricing Policies'!$E$4*IF($C9="TRF",1,(1+Markups!$B$4/100)) -> 755.37133 | Y9: =S9*(1+'Pricing Policies'!$C$6/100)*'Pricing Policies'!$F$4*IF($C9="TRF",1,(1+Markups!$B$4/100)) -> 906.44559 | Z9: =S9*(1+'Pricing Policies'!$C$7/100)*'Pricing Policies'!$D$4*IF($C9="TRF",1,(1+Markups!$B$4/100)) -> 701.84415 | AA9: =S9*(1+'Pricing Policies'!$C$7/100)*'Pricing Policies'!$E$4*IF($C9="TRF",1,(1+Markups!$B$4/100)) -> 825.699 | AB9: =S9*(1+'Pricing Policies'!$C$7/100)*'Pricing Policies'!$F$4*IF($C9="TRF",1,(1+Markups!$B$4/100)) -> 990.8388 | AC9: =AC$2 -> 2 | AD9: =AC9*K9 -> 0 | AE9: =AD9*(1+'Pricing Policies'!$C$12/100)*'Pricing Policies'!$D$11 -> 0 | AF9: =AD9*(1+'Pricing Policies'!$C$12/100)*'Pricing Policies'!$E$11 -> 0 | AG9: =AD9*(1+'Pricing Policies'!$C$12/100)*'Pricing Policies'!$F$11 -> 0 | AH9: =AD9*(1+'Pricing Policies'!$C$13/100)*'Pricing Policies'!$D$11 -> 0 | AI9: =AD9*(1+'Pricing Policies'!$C$13/100)*'Pricing Policies'!$E$11 -> 0 | AJ9: =AD9*(1+'Pricing Policies'!$C$13/100)*'Pricing Policies'!$F$11 -> 0 | AK9: =AD9*(1+'Pricing Policies'!$C$14/100)*'Pricing Policies'!$D$11 -> 0 | AL9: =AD9*(1+'Pricing Policies'!$C$14/100)*'Pricing Policies'!$E$11 -> 0 | AM9: =AD9*(1+'Pricing Policies'!$C$14/100)*'Pricing Policies'!$F$11 -> 0 | AN9: =(T$2*T9+U$2*U9+V$2*V9+W$2*W9+X$2*X9+Y$2*Y9+Z$2*Z9+AA$2*AA9+AB$2*AB9) -> 708.48621 | AO9: =(AE$2*AE9+AF$2*AF9+AG$2*AG9+AH$2*AH9+AI$2*AI9+AJ$2*AJ9+AK$2*AK9+AL$2*AL9+AM$2*AM9) -> 0 | AP9: =AN9+AO9 -> 708.48621 | AQ9: =CEILING(AP9,5) -> 710 | AR9: =AR$2 -> 0.1 | AS9: =AQ9*AR9 -> 71 | AT9: =AT$2 -> 0.05 | AU9: =(AQ9+AS9)*AT9 -> 39.05 | AV9: =AQ9+AS9+AU9 -> 820.05 | AW9: =CEILING(AV9,5) -> 825 | AX9: =AW9-AU9-AS9-AD9 -> 714.95 | AY9: =AX9*AY$2 -> 178.7375 | AZ9: =AY9/D9 -> 17.87375 | BA9: =IF(AZ9<BD$9,BD$9,IF(AZ9>BD$10,BD$10,AZ9)) -> 17.87375 | BC9: Costo minimo garantito | BD9: 15
A10: =CONCATENATE(B10, " - ",C10) -> Suvereto - TOUR FD+ | B10: Suvereto | C10: TOUR FD+ | D10: 10 | E10: 400 | F10: 0 | M10: =(E10)*'Base Operating Costs'!$B$13 -> 76 | N10: =(E10)*'Base Operating Costs'!$B$14 -> 56.286885 | O10: ='Base Operating Costs'!$B$15*(E10) -> 64.40075 | P10: =D10*'Base Operating Costs'!$B$4 -> 220 | Q10: =F10 -> 0 | R10: =M10+N10+O10+P10+Q10 -> 416.68764 | S10: =R10*((100+O$2*EXP(-1*E10/P$2))/100)*IF(E10<M$2,1,(1-(N$2/100))) -> 416.7566 | T10: =S10*(1+'Pricing Policies'!$C$5/100)*'Pricing Policies'!$D$4*IF($C10="TRF",1,(1+Markups!$B$4/100)) -> 602.21328 | U10: =S10*(1+'Pricing Policies'!$C$5/100)*'Pricing Policies'!$E$4*IF($C10="TRF",1,(1+Markups!$B$4/100)) -> 708.48621 | V10: =S10*(1+'Pricing Policies'!$C$5/100)*'Pricing Policies'!$F$4*IF($C10="TRF",1,(1+Markups!$B$4/100)) -> 850.18345 | W10: =S10*(1+'Pricing Policies'!$C$6/100)*'Pricing Policies'!$D$4*IF($C10="TRF",1,(1+Markups!$B$4/100)) -> 642.06563 | X10: =S10*(1+'Pricing Policies'!$C$6/100)*'Pricing Policies'!$E$4*IF($C10="TRF",1,(1+Markups!$B$4/100)) -> 755.37133 | Y10: =S10*(1+'Pricing Policies'!$C$6/100)*'Pricing Policies'!$F$4*IF($C10="TRF",1,(1+Markups!$B$4/100)) -> 906.44559 | Z10: =S10*(1+'Pricing Policies'!$C$7/100)*'Pricing Policies'!$D$4*IF($C10="TRF",1,(1+Markups!$B$4/100)) -> 701.84415 | AA10: =S10*(1+'Pricing Policies'!$C$7/100)*'Pricing Policies'!$E$4*IF($C10="TRF",1,(1+Markups!$B$4/100)) -> 825.699 | AB10: =S10*(1+'Pricing Policies'!$C$7/100)*'Pricing Policies'!$F$4*IF($C10="TRF",1,(1+Markups!$B$4/100)) -> 990.8388 | AC10: =AC$2 -> 2 | AD10: =AC10*K10 -> 0 | AE10: =AD10*(1+'Pricing Policies'!$C$12/100)*'Pricing Policies'!$D$11 -> 0 | AF10: =AD10*(1+'Pricing Policies'!$C$12/100)*'Pricing Policies'!$E$11 -> 0 | AG10: =AD10*(1+'Pricing Policies'!$C$12/100)*'Pricing Policies'!$F$11 -> 0 | AH10: =AD10*(1+'Pricing Policies'!$C$13/100)*'Pricing Policies'!$D$11 -> 0 | AI10: =AD10*(1+'Pricing Policies'!$C$13/100)*'Pricing Policies'!$E$11 -> 0 | AJ10: =AD10*(1+'Pricing Policies'!$C$13/100)*'Pricing Policies'!$F$11 -> 0 | AK10: =AD10*(1+'Pricing Policies'!$C$14/100)*'Pricing Policies'!$D$11 -> 0 | AL10: =AD10*(1+'Pricing Policies'!$C$14/100)*'Pricing Policies'!$E$11 -> 0 | AM10: =AD10*(1+'Pricing Policies'!$C$14/100)*'Pricing Policies'!$F$11 -> 0 | AN10: =(T$2*T10+U$2*U10+V$2*V10+W$2*W10+X$2*X10+Y$2*Y10+Z$2*Z10+AA$2*AA10+AB$2*AB10) -> 708.48621 | AO10: =(AE$2*AE10+AF$2*AF10+AG$2*AG10+AH$2*AH10+AI$2*AI10+AJ$2*AJ10+AK$2*AK10+AL$2*AL10+AM$2*AM10) -> 0 | AP10: =AN10+AO10 -> 708.48621 | AQ10: =CEILING(AP10,5) -> 710 | AR10: =AR$2 -> 0.1 | AS10: =AQ10*AR10 -> 71 | AT10: =AT$2 -> 0.05 | AU10: =(AQ10+AS10)*AT10 -> 39.05 | AV10: =AQ10+AS10+AU10 -> 820.05 | AW10: =CEILING(AV10,5) -> 825 | AX10: =AW10-AU10-AS10-AD10 -> 714.95 | AY10: =AX10*AY$2 -> 178.7375 | AZ10: =AY10/D10 -> 17.87375 | BA10: =IF(AZ10<BD$9,BD$9,IF(AZ10>BD$10,BD$10,AZ10)) -> 17.87375 | BC10: Costo massimo riconosciuto | BD10: 22
A11: =CONCATENATE(B11, " - ",C11) -> Chianti Classico - TOUR FD | B11: Chianti Classico | C11: TOUR FD | D11: 8 | E11: 250 | F11: 0 | G11: 50 | H11: 20 | I11: 0 | J11: 0 | K11: =SUM(G11:J11) -> 70 | M11: =(E11)*'Base Operating Costs'!$B$13 -> 47.5 | N11: =(E11)*'Base Operating Costs'!$B$14 -> 35.179303 | O11: ='Base Operating Costs'!$B$15*(E11) -> 40.250469 | P11: =D11*'Base Operating Costs'!$B$4 -> 176 | Q11: =F11 -> 0 | R11: =M11+N11+O11+P11+Q11 -> 298.92977 | S11: =R11*((100+O$2*EXP(-1*E11/P$2))/100)*IF(E11<M$2,1,(1-(N$2/100))) -> 300.31654 | T11: =S11*(1+'Pricing Policies'!$C$5/100)*'Pricing Policies'!$D$4*IF($C11="TRF",1,(1+Markups!$B$4/100)) -> 433.9574 | U11: =S11*(1+'Pricing Policies'!$C$5/100)*'Pricing Policies'!$E$4*IF($C11="TRF",1,(1+Markups!$B$4/100)) -> 510.53812 | V11: =S11*(1+'Pricing Policies'!$C$5/100)*'Pricing Policies'!$F$4*IF($C11="TRF",1,(1+Markups!$B$4/100)) -> 612.64574 | W11: =S11*(1+'Pricing Policies'!$C$6/100)*'Pricing Policies'!$D$4*IF($C11="TRF",1,(1+Markups!$B$4/100)) -> 462.67517 | X11: =S11*(1+'Pricing Policies'!$C$6/100)*'Pricing Policies'!$E$4*IF($C11="TRF",1,(1+Markups!$B$4/100)) -> 544.32373 | Y11: =S11*(1+'Pricing Policies'!$C$6/100)*'Pricing Policies'!$F$4*IF($C11="TRF",1,(1+Markups!$B$4/100)) -> 653.18847 | Z11: =S11*(1+'Pricing Policies'!$C$7/100)*'Pricing Policies'!$D$4*IF($C11="TRF",1,(1+Markups!$B$4/100)) -> 505.75182 | AA11: =S11*(1+'Pricing Policies'!$C$7/100)*'Pricing Policies'!$E$4*IF($C11="TRF",1,(1+Markups!$B$4/100)) -> 595.00214 | AB11: =S11*(1+'Pricing Policies'!$C$7/100)*'Pricing Policies'!$F$4*IF($C11="TRF",1,(1+Markups!$B$4/100)) -> 714.00257 | AC11: =AC$2 -> 2 | AD11: =AC11*K11 -> 140 | AE11: =AD11*(1+'Pricing Policies'!$C$12/100)*'Pricing Policies'!$D$11 -> 147 | AF11: =AD11*(1+'Pricing Policies'!$C$12/100)*'Pricing Policies'!$E$11 -> 161.7 | AG11: =AD11*(1+'Pricing Policies'!$C$12/100)*'Pricing Policies'!$F$11 -> 176.4 | AH11: =AD11*(1+'Pricing Policies'!$C$13/100)*'Pricing Policies'!$D$11 -> 154 | AI11: =AD11*(1+'Pricing Policies'!$C$13/100)*'Pricing Policies'!$E$11 -> 169.4 | AJ11: =AD11*(1+'Pricing Policies'!$C$13/100)*'Pricing Policies'!$F$11 -> 184.8 | AK11: =AD11*(1+'Pricing Policies'!$C$14/100)*'Pricing Policies'!$D$11 -> 163.8 | AL11: =AD11*(1+'Pricing Policies'!$C$14/100)*'Pricing Policies'!$E$11 -> 180.18 | AM11: =AD11*(1+'Pricing Policies'!$C$14/100)*'Pricing Policies'!$F$11 -> 196.56 | AN11: =(T$2*T11+U$2*U11+V$2*V11+W$2*W11+X$2*X11+Y$2*Y11+Z$2*Z11+AA$2*AA11+AB$2*AB11) -> 510.53812 | AO11: =(AE$2*AE11+AF$2*AF11+AG$2*AG11+AH$2*AH11+AI$2*AI11+AJ$2*AJ11+AK$2*AK11+AL$2*AL11+AM$2*AM11) -> 161.7 | AP11: =AN11+AO11 -> 672.23812 | AQ11: =CEILING(AP11,5) -> 675 | AR11: =AR$2 -> 0.1 | AS11: =AQ11*AR11 -> 67.5 | AT11: =AT$2 -> 0.05 | AU11: =(AQ11+AS11)*AT11 -> 37.125 | AV11: =AQ11+AS11+AU11 -> 779.625 | AW11: =CEILING(AV11,5) -> 780 | AX11: =AW11-AU11-AS11-AD11 -> 535.375 | AY11: =AX11*AY$2 -> 133.84375 | AZ11: =AY11/D11 -> 16.730469 | BA11: =IF(AZ11<BD$9,BD$9,IF(AZ11>BD$10,BD$10,AZ11)) -> 16.730469
A12: =CONCATENATE(B12, " - ",C12) -> Montalcino-Pienza - TOUR FD | B12: Montalcino-Pienza | C12: TOUR FD | D12: 9 | E12: 250 | F12: 0 | G12: 50 | H12: 20 | I12: 0 | J12: 0 | K12: =SUM(G12:J12) -> 70 | M12: =(E12)*'Base Operating Costs'!$B$13 -> 47.5 | N12: =(E12)*'Base Operating Costs'!$B$14 -> 35.179303 | O12: ='Base Operating Costs'!$B$15*(E12) -> 40.250469 | P12: =D12*'Base Operating Costs'!$B$4 -> 198 | Q12: =F12 -> 0 | R12: =M12+N12+O12+P12+Q12 -> 320.92977 | S12: =R12*((100+O$2*EXP(-1*E12/P$2))/100)*IF(E12<M$2,1,(1-(N$2/100))) -> 322.4186 | T12: =S12*(1+'Pricing Policies'!$C$5/100)*'Pricing Policies'!$D$4*IF($C12="TRF",1,(1+Markups!$B$4/100)) -> 465.89488 | U12: =S12*(1+'Pricing Policies'!$C$5/100)*'Pricing Policies'!$E$4*IF($C12="TRF",1,(1+Markups!$B$4/100)) -> 548.11162 | V12: =S12*(1+'Pricing Policies'!$C$5/100)*'Pricing Policies'!$F$4*IF($C12="TRF",1,(1+Markups!$B$4/100)) -> 657.73394 | W12: =S12*(1+'Pricing Policies'!$C$6/100)*'Pricing Policies'!$D$4*IF($C12="TRF",1,(1+Markups!$B$4/100)) -> 496.72615 | X12: =S12*(1+'Pricing Policies'!$C$6/100)*'Pricing Policies'!$E$4*IF($C12="TRF",1,(1+Markups!$B$4/100)) -> 584.38371 | Y12: =S12*(1+'Pricing Policies'!$C$6/100)*'Pricing Policies'!$F$4*IF($C12="TRF",1,(1+Markups!$B$4/100)) -> 701.26045 | Z12: =S12*(1+'Pricing Policies'!$C$7/100)*'Pricing Policies'!$D$4*IF($C12="TRF",1,(1+Markups!$B$4/100)) -> 542.97307 | AA12: =S12*(1+'Pricing Policies'!$C$7/100)*'Pricing Policies'!$E$4*IF($C12="TRF",1,(1+Markups!$B$4/100)) -> 638.79185 | AB12: =S12*(1+'Pricing Policies'!$C$7/100)*'Pricing Policies'!$F$4*IF($C12="TRF",1,(1+Markups!$B$4/100)) -> 766.55022 | AC12: =AC$2 -> 2 | AD12: =AC12*K12 -> 140 | AE12: =AD12*(1+'Pricing Policies'!$C$12/100)*'Pricing Policies'!$D$11 -> 147 | AF12: =AD12*(1+'Pricing Policies'!$C$12/100)*'Pricing Policies'!$E$11 -> 161.7 | AG12: =AD12*(1+'Pricing Policies'!$C$12/100)*'Pricing Policies'!$F$11 -> 176.4 | AH12: =AD12*(1+'Pricing Policies'!$C$13/100)*'Pricing Policies'!$D$11 -> 154 | AI12: =AD12*(1+'Pricing Policies'!$C$13/100)*'Pricing Policies'!$E$11 -> 169.4 | AJ12: =AD12*(1+'Pricing Policies'!$C$13/100)*'Pricing Policies'!$F$11 -> 184.8 | AK12: =AD12*(1+'Pricing Policies'!$C$14/100)*'Pricing Policies'!$D$11 -> 163.8 | AL12: =AD12*(1+'Pricing Policies'!$C$14/100)*'Pricing Policies'!$E$11 -> 180.18 | AM12: =AD12*(1+'Pricing Policies'!$C$14/100)*'Pricing Policies'!$F$11 -> 196.56 | AN12: =(T$2*T12+U$2*U12+V$2*V12+W$2*W12+X$2*X12+Y$2*Y12+Z$2*Z12+AA$2*AA12+AB$2*AB12) -> 548.11162 | AO12: =(AE$2*AE12+AF$2*AF12+AG$2*AG12+AH$2*AH12+AI$2*AI12+AJ$2*AJ12+AK$2*AK12+AL$2*AL12+AM$2*AM12) -> 161.7 | AP12: =AN12+AO12 -> 709.81162 | AQ12: =CEILING(AP12,5) -> 710 | AR12: =AR$2 -> 0.1 | AS12: =AQ12*AR12 -> 71 | AT12: =AT$2 -> 0.05 | AU12: =(AQ12+AS12)*AT12 -> 39.05 | AV12: =AQ12+AS12+AU12 -> 820.05 | AW12: =CEILING(AV12,5) -> 825 | AX12: =AW12-AU12-AS12-AD12 -> 574.95 | AY12: =AX12*AY$2 -> 143.7375 | AZ12: =AY12/D12 -> 15.970833 | BA12: =IF(AZ12<BD$9,BD$9,IF(AZ12>BD$10,BD$10,AZ12)) -> 15.970833
A13: =CONCATENATE(B13, " - ",C13) -> Pisa-Lucca - TOUR FD | B13: Pisa-Lucca | C13: TOUR FD | D13: 9 | E13: 300 | F13: 0 | M13: =(E13)*'Base Operating Costs'!$B$13 -> 57 | N13: =(E13)*'Base Operating Costs'!$B$14 -> 42.215164 | O13: ='Base Operating Costs'!$B$15*(E13) -> 48.300562 | P13: =D13*'Base Operating Costs'!$B$4 -> 198 | Q13: =F13 -> 0 | R13: =M13+N13+O13+P13+Q13 -> 345.51573 | S13: =R13*((100+O$2*EXP(-1*E13/P$2))/100)*IF(E13<M$2,1,(1-(N$2/100))) -> 346.04338 | T13: =S13*(1+'Pricing Policies'!$C$5/100)*'Pricing Policies'!$D$4*IF($C13="TRF",1,(1+Markups!$B$4/100)) -> 500.03269 | U13: =S13*(1+'Pricing Policies'!$C$5/100)*'Pricing Policies'!$E$4*IF($C13="TRF",1,(1+Markups!$B$4/100)) -> 588.27375 | V13: =S13*(1+'Pricing Policies'!$C$5/100)*'Pricing Policies'!$F$4*IF($C13="TRF",1,(1+Markups!$B$4/100)) -> 705.9285 | W13: =S13*(1+'Pricing Policies'!$C$6/100)*'Pricing Policies'!$D$4*IF($C13="TRF",1,(1+Markups!$B$4/100)) -> 533.12309 | X13: =S13*(1+'Pricing Policies'!$C$6/100)*'Pricing Policies'!$E$4*IF($C13="TRF",1,(1+Markups!$B$4/100)) -> 627.20363 | Y13: =S13*(1+'Pricing Policies'!$C$6/100)*'Pricing Policies'!$F$4*IF($C13="TRF",1,(1+Markups!$B$4/100)) -> 752.64436 | Z13: =S13*(1+'Pricing Policies'!$C$7/100)*'Pricing Policies'!$D$4*IF($C13="TRF",1,(1+Markups!$B$4/100)) -> 582.75869 | AA13: =S13*(1+'Pricing Policies'!$C$7/100)*'Pricing Policies'!$E$4*IF($C13="TRF",1,(1+Markups!$B$4/100)) -> 685.59846 | AB13: =S13*(1+'Pricing Policies'!$C$7/100)*'Pricing Policies'!$F$4*IF($C13="TRF",1,(1+Markups!$B$4/100)) -> 822.71815 | AC13: =AC$2 -> 2 | AD13: =AC13*K13 -> 0 | AE13: =AD13*(1+'Pricing Policies'!$C$12/100)*'Pricing Policies'!$D$11 -> 0 | AF13: =AD13*(1+'Pricing Policies'!$C$12/100)*'Pricing Policies'!$E$11 -> 0 | AG13: =AD13*(1+'Pricing Policies'!$C$12/100)*'Pricing Policies'!$F$11 -> 0 | AH13: =AD13*(1+'Pricing Policies'!$C$13/100)*'Pricing Policies'!$D$11 -> 0 | AI13: =AD13*(1+'Pricing Policies'!$C$13/100)*'Pricing Policies'!$E$11 -> 0 | AJ13: =AD13*(1+'Pricing Policies'!$C$13/100)*'Pricing Policies'!$F$11 -> 0 | AK13: =AD13*(1+'Pricing Policies'!$C$14/100)*'Pricing Policies'!$D$11 -> 0 | AL13: =AD13*(1+'Pricing Policies'!$C$14/100)*'Pricing Policies'!$E$11 -> 0 | AM13: =AD13*(1+'Pricing Policies'!$C$14/100)*'Pricing Policies'!$F$11 -> 0 | AN13: =(T$2*T13+U$2*U13+V$2*V13+W$2*W13+X$2*X13+Y$2*Y13+Z$2*Z13+AA$2*AA13+AB$2*AB13) -> 588.27375 | AO13: =(AE$2*AE13+AF$2*AF13+AG$2*AG13+AH$2*AH13+AI$2*AI13+AJ$2*AJ13+AK$2*AK13+AL$2*AL13+AM$2*AM13) -> 0 | AP13: =AN13+AO13 -> 588.27375 | AQ13: =CEILING(AP13,5) -> 590 | AR13: =AR$2 -> 0.1 | AS13: =AQ13*AR13 -> 59 | AT13: =AT$2 -> 0.05 | AU13: =(AQ13+AS13)*AT13 -> 32.45 | AV13: =AQ13+AS13+AU13 -> 681.45 | AW13: =CEILING(AV13,5) -> 685 | AX13: =AW13-AU13-AS13-AD13 -> 593.55 | AY13: =AX13*AY$2 -> 148.3875 | AZ13: =AY13/D13 -> 16.4875 | BA13: =IF(AZ13<BD$9,BD$9,IF(AZ13>BD$10,BD$10,AZ13)) -> 16.4875
A14: =CONCATENATE(B14, " - ",C14) -> Monteriggioni-SanGi-Volterra - TOUR FD | B14: Monteriggioni-SanGi-Volterra | C14: TOUR FD | D14: 9 | E14: 250 | F14: 0 | M14: =(E14)*'Base Operating Costs'!$B$13 -> 47.5 | N14: =(E14)*'Base Operating Costs'!$B$14 -> 35.179303 | O14: ='Base Operating Costs'!$B$15*(E14) -> 40.250469 | P14: =D14*'Base Operating Costs'!$B$4 -> 198 | Q14: =F14 -> 0 | R14: =M14+N14+O14+P14+Q14 -> 320.92977 | S14: =R14*((100+O$2*EXP(-1*E14/P$2))/100)*IF(E14<M$2,1,(1-(N$2/100))) -> 322.4186 | T14: =S14*(1+'Pricing Policies'!$C$5/100)*'Pricing Policies'!$D$4*IF($C14="TRF",1,(1+Markups!$B$4/100)) -> 465.89488 | U14: =S14*(1+'Pricing Policies'!$C$5/100)*'Pricing Policies'!$E$4*IF($C14="TRF",1,(1+Markups!$B$4/100)) -> 548.11162 | V14: =S14*(1+'Pricing Policies'!$C$5/100)*'Pricing Policies'!$F$4*IF($C14="TRF",1,(1+Markups!$B$4/100)) -> 657.73394 | W14: =S14*(1+'Pricing Policies'!$C$6/100)*'Pricing Policies'!$D$4*IF($C14="TRF",1,(1+Markups!$B$4/100)) -> 496.72615 | X14: =S14*(1+'Pricing Policies'!$C$6/100)*'Pricing Policies'!$E$4*IF($C14="TRF",1,(1+Markups!$B$4/100)) -> 584.38371 | Y14: =S14*(1+'Pricing Policies'!$C$6/100)*'Pricing Policies'!$F$4*IF($C14="TRF",1,(1+Markups!$B$4/100)) -> 701.26045 | Z14: =S14*(1+'Pricing Policies'!$C$7/100)*'Pricing Policies'!$D$4*IF($C14="TRF",1,(1+Markups!$B$4/100)) -> 542.97307 | AA14: =S14*(1+'Pricing Policies'!$C$7/100)*'Pricing Policies'!$E$4*IF($C14="TRF",1,(1+Markups!$B$4/100)) -> 638.79185 | AB14: =S14*(1+'Pricing Policies'!$C$7/100)*'Pricing Policies'!$F$4*IF($C14="TRF",1,(1+Markups!$B$4/100)) -> 766.55022 | AC14: =AC$2 -> 2 | AD14: =AC14*K14 -> 0 | AE14: =AD14*(1+'Pricing Policies'!$C$12/100)*'Pricing Policies'!$D$11 -> 0 | AF14: =AD14*(1+'Pricing Policies'!$C$12/100)*'Pricing Policies'!$E$11 -> 0 | AG14: =AD14*(1+'Pricing Policies'!$C$12/100)*'Pricing Policies'!$F$11 -> 0 | AH14: =AD14*(1+'Pricing Policies'!$C$13/100)*'Pricing Policies'!$D$11 -> 0 | AI14: =AD14*(1+'Pricing Policies'!$C$13/100)*'Pricing Policies'!$E$11 -> 0 | AJ14: =AD14*(1+'Pricing Policies'!$C$13/100)*'Pricing Policies'!$F$11 -> 0 | AK14: =AD14*(1+'Pricing Policies'!$C$14/100)*'Pricing Policies'!$D$11 -> 0 | AL14: =AD14*(1+'Pricing Policies'!$C$14/100)*'Pricing Policies'!$E$11 -> 0 | AM14: =AD14*(1+'Pricing Policies'!$C$14/100)*'Pricing Policies'!$F$11 -> 0 | AN14: =(T$2*T14+U$2*U14+V$2*V14+W$2*W14+X$2*X14+Y$2*Y14+Z$2*Z14+AA$2*AA14+AB$2*AB14) -> 548.11162 | AO14: =(AE$2*AE14+AF$2*AF14+AG$2*AG14+AH$2*AH14+AI$2*AI14+AJ$2*AJ14+AK$2*AK14+AL$2*AL14+AM$2*AM14) -> 0 | AP14: =AN14+AO14 -> 548.11162 | AQ14: =CEILING(AP14,5) -> 550 | AR14: =AR$2 -> 0.1 | AS14: =AQ14*AR14 -> 55 | AT14: =AT$2 -> 0.05 | AU14: =(AQ14+AS14)*AT14 -> 30.25 | AV14: =AQ14+AS14+AU14 -> 635.25 | AW14: =CEILING(AV14,5) -> 640 | AX14: =AW14-AU14-AS14-AD14 -> 554.75 | AY14: =AX14*AY$2 -> 138.6875 | AZ14: =AY14/D14 -> 15.409722 | BA14: =IF(AZ14<BD$9,BD$9,IF(AZ14>BD$10,BD$10,AZ14)) -> 15.409722
A15: =CONCATENATE(B15, " - ",C15) -> Assisi - TOUR FD | B15: Assisi | C15: TOUR FD | D15: 9 | E15: 300 | F15: 0 | M15: =(E15)*'Base Operating Costs'!$B$13 -> 57 | N15: =(E15)*'Base Operating Costs'!$B$14 -> 42.215164 | O15: ='Base Operating Costs'!$B$15*(E15) -> 48.300562 | P15: =D15*'Base Operating Costs'!$B$4 -> 198 | Q15: =F15 -> 0 | R15: =M15+N15+O15+P15+Q15 -> 345.51573 | S15: =R15*((100+O$2*EXP(-1*E15/P$2))/100)*IF(E15<M$2,1,(1-(N$2/100))) -> 346.04338 | T15: =S15*(1+'Pricing Policies'!$C$5/100)*'Pricing Policies'!$D$4*IF($C15="TRF",1,(1+Markups!$B$4/100)) -> 500.03269 | U15: =S15*(1+'Pricing Policies'!$C$5/100)*'Pricing Policies'!$E$4*IF($C15="TRF",1,(1+Markups!$B$4/100)) -> 588.27375 | V15: =S15*(1+'Pricing Policies'!$C$5/100)*'Pricing Policies'!$F$4*IF($C15="TRF",1,(1+Markups!$B$4/100)) -> 705.9285 | W15: =S15*(1+'Pricing Policies'!$C$6/100)*'Pricing Policies'!$D$4*IF($C15="TRF",1,(1+Markups!$B$4/100)) -> 533.12309 | X15: =S15*(1+'Pricing Policies'!$C$6/100)*'Pricing Policies'!$E$4*IF($C15="TRF",1,(1+Markups!$B$4/100)) -> 627.20363 | Y15: =S15*(1+'Pricing Policies'!$C$6/100)*'Pricing Policies'!$F$4*IF($C15="TRF",1,(1+Markups!$B$4/100)) -> 752.64436 | Z15: =S15*(1+'Pricing Policies'!$C$7/100)*'Pricing Policies'!$D$4*IF($C15="TRF",1,(1+Markups!$B$4/100)) -> 582.75869 | AA15: =S15*(1+'Pricing Policies'!$C$7/100)*'Pricing Policies'!$E$4*IF($C15="TRF",1,(1+Markups!$B$4/100)) -> 685.59846 | AB15: =S15*(1+'Pricing Policies'!$C$7/100)*'Pricing Policies'!$F$4*IF($C15="TRF",1,(1+Markups!$B$4/100)) -> 822.71815 | AC15: =AC$2 -> 2 | AD15: =AC15*K15 -> 0 | AE15: =AD15*(1+'Pricing Policies'!$C$12/100)*'Pricing Policies'!$D$11 -> 0 | AF15: =AD15*(1+'Pricing Policies'!$C$12/100)*'Pricing Policies'!$E$11 -> 0 | AG15: =AD15*(1+'Pricing Policies'!$C$12/100)*'Pricing Policies'!$F$11 -> 0 | AH15: =AD15*(1+'Pricing Policies'!$C$13/100)*'Pricing Policies'!$D$11 -> 0 | AI15: =AD15*(1+'Pricing Policies'!$C$13/100)*'Pricing Policies'!$E$11 -> 0 | AJ15: =AD15*(1+'Pricing Policies'!$C$13/100)*'Pricing Policies'!$F$11 -> 0 | AK15: =AD15*(1+'Pricing Policies'!$C$14/100)*'Pricing Policies'!$D$11 -> 0 | AL15: =AD15*(1+'Pricing Policies'!$C$14/100)*'Pricing Policies'!$E$11 -> 0 | AM15: =AD15*(1+'Pricing Policies'!$C$14/100)*'Pricing Policies'!$F$11 -> 0 | AN15: =(T$2*T15+U$2*U15+V$2*V15+W$2*W15+X$2*X15+Y$2*Y15+Z$2*Z15+AA$2*AA15+AB$2*AB15) -> 588.27375 | AO15: =(AE$2*AE15+AF$2*AF15+AG$2*AG15+AH$2*AH15+AI$2*AI15+AJ$2*AJ15+AK$2*AK15+AL$2*AL15+AM$2*AM15) -> 0 | AP15: =AN15+AO15 -> 588.27375 | AQ15: =CEILING(AP15,5) -> 590 | AR15: =AR$2 -> 0.1 | AS15: =AQ15*AR15 -> 59 | AT15: =AT$2 -> 0.05 | AU15: =(AQ15+AS15)*AT15 -> 32.45 | AV15: =AQ15+AS15+AU15 -> 681.45 | AW15: =CEILING(AV15,5) -> 685 | AX15: =AW15-AU15-AS15-AD15 -> 593.55 | AY15: =AX15*AY$2 -> 148.3875 | AZ15: =AY15/D15 -> 16.4875 | BA15: =IF(AZ15<BD$9,BD$9,IF(AZ15>BD$10,BD$10,AZ15)) -> 16.4875
A16: =CONCATENATE(B16, " - ",C16) -> Siena - TRF | B16: Siena | C16: TRF | D16: 1 | E16: 10 | F16: 0 | M16: =(E16)*'Base Operating Costs'!$B$13 -> 1.9 | N16: =(E16)*'Base Operating Costs'!$B$14 -> 1.4071721 | O16: ='Base Operating Costs'!$B$15*(E16) -> 1.6100188 | P16: =D16*'Base Operating Costs'!$B$4 -> 22 | Q16: =F16 -> 0 | R16: =M16+N16+O16+P16+Q16 -> 26.917191 | S16: =R16*((100+O$2*EXP(-1*E16/P$2))/100)*IF(E16<M$2,1,(1-(N$2/100))) -> 52.781513 | T16: =S16*(1+'Pricing Policies'!$C$5/100)*'Pricing Policies'!$D$4*IF($C16="TRF",1,(1+Markups!$B$4/100)) -> 61.015429 | U16: =S16*(1+'Pricing Policies'!$C$5/100)*'Pricing Policies'!$E$4*IF($C16="TRF",1,(1+Markups!$B$4/100)) -> 71.782857 | V16: =S16*(1+'Pricing Policies'!$C$5/100)*'Pricing Policies'!$F$4*IF($C16="TRF",1,(1+Markups!$B$4/100)) -> 86.139429 | W16: =S16*(1+'Pricing Policies'!$C$6/100)*'Pricing Policies'!$D$4*IF($C16="TRF",1,(1+Markups!$B$4/100)) -> 65.053214 | X16: =S16*(1+'Pricing Policies'!$C$6/100)*'Pricing Policies'!$E$4*IF($C16="TRF",1,(1+Markups!$B$4/100)) -> 76.533193 | Y16: =S16*(1+'Pricing Policies'!$C$6/100)*'Pricing Policies'!$F$4*IF($C16="TRF",1,(1+Markups!$B$4/100)) -> 91.839832 | Z16: =S16*(1+'Pricing Policies'!$C$7/100)*'Pricing Policies'!$D$4*IF($C16="TRF",1,(1+Markups!$B$4/100)) -> 71.109893 | AA16: =S16*(1+'Pricing Policies'!$C$7/100)*'Pricing Policies'!$E$4*IF($C16="TRF",1,(1+Markups!$B$4/100)) -> 83.658698 | AB16: =S16*(1+'Pricing Policies'!$C$7/100)*'Pricing Policies'!$F$4*IF($C16="TRF",1,(1+Markups!$B$4/100)) -> 100.39044 | AC16: =AC$2 -> 2 | AD16: =AC16*K16 -> 0 | AE16: =AD16*(1+'Pricing Policies'!$C$12/100)*'Pricing Policies'!$D$11 -> 0 | AF16: =AD16*(1+'Pricing Policies'!$C$12/100)*'Pricing Policies'!$E$11 -> 0 | AG16: =AD16*(1+'Pricing Policies'!$C$12/100)*'Pricing Policies'!$F$11 -> 0 | AH16: =AD16*(1+'Pricing Policies'!$C$13/100)*'Pricing Policies'!$D$11 -> 0 | AI16: =AD16*(1+'Pricing Policies'!$C$13/100)*'Pricing Policies'!$E$11 -> 0 | AJ16: =AD16*(1+'Pricing Policies'!$C$13/100)*'Pricing Policies'!$F$11 -> 0 | AK16: =AD16*(1+'Pricing Policies'!$C$14/100)*'Pricing Policies'!$D$11 -> 0 | AL16: =AD16*(1+'Pricing Policies'!$C$14/100)*'Pricing Policies'!$E$11 -> 0 | AM16: =AD16*(1+'Pricing Policies'!$C$14/100)*'Pricing Policies'!$F$11 -> 0 | AN16: =(T$2*T16+U$2*U16+V$2*V16+W$2*W16+X$2*X16+Y$2*Y16+Z$2*Z16+AA$2*AA16+AB$2*AB16) -> 71.782857 | AO16: =(AE$2*AE16+AF$2*AF16+AG$2*AG16+AH$2*AH16+AI$2*AI16+AJ$2*AJ16+AK$2*AK16+AL$2*AL16+AM$2*AM16) -> 0 | AP16: =AN16+AO16 -> 71.782857 | AQ16: =CEILING(AP16,5) -> 75 | AR16: =AR$2 -> 0.1 | AS16: =AQ16*AR16 -> 7.5 | AT16: =AT$2 -> 0.05 | AU16: =(AQ16+AS16)*AT16 -> 4.125 | AV16: =AQ16+AS16+AU16 -> 86.625 | AW16: =CEILING(AV16,5) -> 90 | AX16: =AW16-AU16-AS16-AD16 -> 78.375 | AY16: =AX16*AY$2 -> 19.59375 | AZ16: =AY16/D16 -> 19.59375 | BA16: =IF(AZ16<BD$9,BD$9,IF(AZ16>BD$10,BD$10,AZ16)) -> 19.59375
A17: =CONCATENATE(B17, " - ",C17) -> Siena dintorni - TRF | B17: Siena dintorni | C17: TRF | D17: 2 | E17: 30 | F17: 0 | M17: =(E17)*'Base Operating Costs'!$B$13 -> 5.7 | N17: =(E17)*'Base Operating Costs'!$B$14 -> 4.2215164 | O17: ='Base Operating Costs'!$B$15*(E17) -> 4.8300563 | P17: =D17*'Base Operating Costs'!$B$4 -> 44 | Q17: =F17 -> 0 | R17: =M17+N17+O17+P17+Q17 -> 58.751573 | S17: =R17*((100+O$2*EXP(-1*E17/P$2))/100)*IF(E17<M$2,1,(1-(N$2/100))) -> 94.948448 | T17: =S17*(1+'Pricing Policies'!$C$5/100)*'Pricing Policies'!$D$4*IF($C17="TRF",1,(1+Markups!$B$4/100)) -> 109.76041 | U17: =S17*(1+'Pricing Policies'!$C$5/100)*'Pricing Policies'!$E$4*IF($C17="TRF",1,(1+Markups!$B$4/100)) -> 129.12989 | V17: =S17*(1+'Pricing Policies'!$C$5/100)*'Pricing Policies'!$F$4*IF($C17="TRF",1,(1+Markups!$B$4/100)) -> 154.95587 | W17: =S17*(1+'Pricing Policies'!$C$6/100)*'Pricing Policies'!$D$4*IF($C17="TRF",1,(1+Markups!$B$4/100)) -> 117.02396 | X17: =S17*(1+'Pricing Policies'!$C$6/100)*'Pricing Policies'!$E$4*IF($C17="TRF",1,(1+Markups!$B$4/100)) -> 137.67525 | Y17: =S17*(1+'Pricing Policies'!$C$6/100)*'Pricing Policies'!$F$4*IF($C17="TRF",1,(1+Markups!$B$4/100)) -> 165.2103 | Z17: =S17*(1+'Pricing Policies'!$C$7/100)*'Pricing Policies'!$D$4*IF($C17="TRF",1,(1+Markups!$B$4/100)) -> 127.9193 | AA17: =S17*(1+'Pricing Policies'!$C$7/100)*'Pricing Policies'!$E$4*IF($C17="TRF",1,(1+Markups!$B$4/100)) -> 150.49329 | AB17: =S17*(1+'Pricing Policies'!$C$7/100)*'Pricing Policies'!$F$4*IF($C17="TRF",1,(1+Markups!$B$4/100)) -> 180.59195 | AC17: =AC$2 -> 2 | AD17: =AC17*K17 -> 0 | AE17: =AD17*(1+'Pricing Policies'!$C$12/100)*'Pricing Policies'!$D$11 -> 0 | AF17: =AD17*(1+'Pricing Policies'!$C$12/100)*'Pricing Policies'!$E$11 -> 0 | AG17: =AD17*(1+'Pricing Policies'!$C$12/100)*'Pricing Policies'!$F$11 -> 0 | AH17: =AD17*(1+'Pricing Policies'!$C$13/100)*'Pricing Policies'!$D$11 -> 0 | AI17: =AD17*(1+'Pricing Policies'!$C$13/100)*'Pricing Policies'!$E$11 -> 0 | AJ17: =AD17*(1+'Pricing Policies'!$C$13/100)*'Pricing Policies'!$F$11 -> 0 | AK17: =AD17*(1+'Pricing Policies'!$C$14/100)*'Pricing Policies'!$D$11 -> 0 | AL17: =AD17*(1+'Pricing Policies'!$C$14/100)*'Pricing Policies'!$E$11 -> 0 | AM17: =AD17*(1+'Pricing Policies'!$C$14/100)*'Pricing Policies'!$F$11 -> 0 | AN17: =(T$2*T17+U$2*U17+V$2*V17+W$2*W17+X$2*X17+Y$2*Y17+Z$2*Z17+AA$2*AA17+AB$2*AB17) -> 129.12989 | AO17: =(AE$2*AE17+AF$2*AF17+AG$2*AG17+AH$2*AH17+AI$2*AI17+AJ$2*AJ17+AK$2*AK17+AL$2*AL17+AM$2*AM17) -> 0 | AP17: =AN17+AO17 -> 129.12989 | AQ17: =CEILING(AP17,5) -> 130 | AR17: =AR$2 -> 0.1 | AS17: =AQ17*AR17 -> 13 | AT17: =AT$2 -> 0.05 | AU17: =(AQ17+AS17)*AT17 -> 7.15 | AV17: =AQ17+AS17+AU17 -> 150.15 | AW17: =CEILING(AV17,5) -> 155 | AX17: =AW17-AU17-AS17-AD17 -> 134.85 | AY17: =AX17*AY$2 -> 33.7125 | AZ17: =AY17/D17 -> 16.85625 | BA17: =IF(AZ17<BD$9,BD$9,IF(AZ17>BD$10,BD$10,AZ17)) -> 16.85625
A18: =CONCATENATE(B18, " - ",C18) -> Arezzo - TRF | B18: Arezzo | C18: TRF | D18: 3 | E18: 180 | F18: 0 | M18: =(E18)*'Base Operating Costs'!$B$13 -> 34.2 | N18: =(E18)*'Base Operating Costs'!$B$14 -> 25.329098 | O18: ='Base Operating Costs'!$B$15*(E18) -> 28.980338 | P18: =D18*'Base Operating Costs'!$B$4 -> 66 | Q18: =F18 -> 0 | R18: =M18+N18+O18+P18+Q18 -> 154.50944 | S18: =R18*((100+O$2*EXP(-1*E18/P$2))/100)*IF(E18<M$2,1,(1-(N$2/100))) -> 157.90536 | T18: =S18*(1+'Pricing Policies'!$C$5/100)*'Pricing Policies'!$D$4*IF($C18="TRF",1,(1+Markups!$B$4/100)) -> 182.5386 | U18: =S18*(1+'Pricing Policies'!$C$5/100)*'Pricing Policies'!$E$4*IF($C18="TRF",1,(1+Markups!$B$4/100)) -> 214.75129 | V18: =S18*(1+'Pricing Policies'!$C$5/100)*'Pricing Policies'!$F$4*IF($C18="TRF",1,(1+Markups!$B$4/100)) -> 257.70155 | W18: =S18*(1+'Pricing Policies'!$C$6/100)*'Pricing Policies'!$D$4*IF($C18="TRF",1,(1+Markups!$B$4/100)) -> 194.61836 | X18: =S18*(1+'Pricing Policies'!$C$6/100)*'Pricing Policies'!$E$4*IF($C18="TRF",1,(1+Markups!$B$4/100)) -> 228.96278 | Y18: =S18*(1+'Pricing Policies'!$C$6/100)*'Pricing Policies'!$F$4*IF($C18="TRF",1,(1+Markups!$B$4/100)) -> 274.75533 | Z18: =S18*(1+'Pricing Policies'!$C$7/100)*'Pricing Policies'!$D$4*IF($C18="TRF",1,(1+Markups!$B$4/100)) -> 212.738 | AA18: =S18*(1+'Pricing Policies'!$C$7/100)*'Pricing Policies'!$E$4*IF($C18="TRF",1,(1+Markups!$B$4/100)) -> 250.28 | AB18: =S18*(1+'Pricing Policies'!$C$7/100)*'Pricing Policies'!$F$4*IF($C18="TRF",1,(1+Markups!$B$4/100)) -> 300.336 | AC18: =AC$2 -> 2 | AD18: =AC18*K18 -> 0 | AE18: =AD18*(1+'Pricing Policies'!$C$12/100)*'Pricing Policies'!$D$11 -> 0 | AF18: =AD18*(1+'Pricing Policies'!$C$12/100)*'Pricing Policies'!$E$11 -> 0 | AG18: =AD18*(1+'Pricing Policies'!$C$12/100)*'Pricing Policies'!$F$11 -> 0 | AH18: =AD18*(1+'Pricing Policies'!$C$13/100)*'Pricing Policies'!$D$11 -> 0 | AI18: =AD18*(1+'Pricing Policies'!$C$13/100)*'Pricing Policies'!$E$11 -> 0 | AJ18: =AD18*(1+'Pricing Policies'!$C$13/100)*'Pricing Policies'!$F$11 -> 0 | AK18: =AD18*(1+'Pricing Policies'!$C$14/100)*'Pricing Policies'!$D$11 -> 0 | AL18: =AD18*(1+'Pricing Policies'!$C$14/100)*'Pricing Policies'!$E$11 -> 0 | AM18: =AD18*(1+'Pricing Policies'!$C$14/100)*'Pricing Policies'!$F$11 -> 0 | AN18: =(T$2*T18+U$2*U18+V$2*V18+W$2*W18+X$2*X18+Y$2*Y18+Z$2*Z18+AA$2*AA18+AB$2*AB18) -> 214.75129 | AO18: =(AE$2*AE18+AF$2*AF18+AG$2*AG18+AH$2*AH18+AI$2*AI18+AJ$2*AJ18+AK$2*AK18+AL$2*AL18+AM$2*AM18) -> 0 | AP18: =AN18+AO18 -> 214.75129 | AQ18: =CEILING(AP18,5) -> 215 | AR18: =AR$2 -> 0.1 | AS18: =AQ18*AR18 -> 21.5 | AT18: =AT$2 -> 0.05 | AU18: =(AQ18+AS18)*AT18 -> 11.825 | AV18: =AQ18+AS18+AU18 -> 248.325 | AW18: =CEILING(AV18,5) -> 250 | AX18: =AW18-AU18-AS18-AD18 -> 216.675 | AY18: =AX18*AY$2 -> 54.16875 | AZ18: =AY18/D18 -> 18.05625 | BA18: =IF(AZ18<BD$9,BD$9,IF(AZ18>BD$10,BD$10,AZ18)) -> 18.05625
A19: =CONCATENATE(B19, " - ",C19) -> Chiusi - TRF | B19: Chiusi | C19: TRF | D19: 3 | E19: 180 | F19: 5 | M19: =(E19)*'Base Operating Costs'!$B$13 -> 34.2 | N19: =(E19)*'Base Operating Costs'!$B$14 -> 25.329098 | O19: ='Base Operating Costs'!$B$15*(E19) -> 28.980338 | P19: =D19*'Base Operating Costs'!$B$4 -> 66 | Q19: =F19 -> 5 | R19: =M19+N19+O19+P19+Q19 -> 159.50944 | S19: =R19*((100+O$2*EXP(-1*E19/P$2))/100)*IF(E19<M$2,1,(1-(N$2/100))) -> 163.01526 | T19: =S19*(1+'Pricing Policies'!$C$5/100)*'Pricing Policies'!$D$4*IF($C19="TRF",1,(1+Markups!$B$4/100)) -> 188.44564 | U19: =S19*(1+'Pricing Policies'!$C$5/100)*'Pricing Policies'!$E$4*IF($C19="TRF",1,(1+Markups!$B$4/100)) -> 221.70075 | V19: =S19*(1+'Pricing Policies'!$C$5/100)*'Pricing Policies'!$F$4*IF($C19="TRF",1,(1+Markups!$B$4/100)) -> 266.0409 | W19: =S19*(1+'Pricing Policies'!$C$6/100)*'Pricing Policies'!$D$4*IF($C19="TRF",1,(1+Markups!$B$4/100)) -> 200.9163 | X19: =S19*(1+'Pricing Policies'!$C$6/100)*'Pricing Policies'!$E$4*IF($C19="TRF",1,(1+Markups!$B$4/100)) -> 236.37212 | Y19: =S19*(1+'Pricing Policies'!$C$6/100)*'Pricing Policies'!$F$4*IF($C19="TRF",1,(1+Markups!$B$4/100)) -> 283.64655 | Z19: =S19*(1+'Pricing Policies'!$C$7/100)*'Pricing Policies'!$D$4*IF($C19="TRF",1,(1+Markups!$B$4/100)) -> 219.6223 | AA19: =S19*(1+'Pricing Policies'!$C$7/100)*'Pricing Policies'!$E$4*IF($C19="TRF",1,(1+Markups!$B$4/100)) -> 258.37918 | AB19: =S19*(1+'Pricing Policies'!$C$7/100)*'Pricing Policies'!$F$4*IF($C19="TRF",1,(1+Markups!$B$4/100)) -> 310.05502 | AC19: =AC$2 -> 2 | AD19: =AC19*K19 -> 0 | AE19: =AD19*(1+'Pricing Policies'!$C$12/100)*'Pricing Policies'!$D$11 -> 0 | AF19: =AD19*(1+'Pricing Policies'!$C$12/100)*'Pricing Policies'!$E$11 -> 0 | AG19: =AD19*(1+'Pricing Policies'!$C$12/100)*'Pricing Policies'!$F$11 -> 0 | AH19: =AD19*(1+'Pricing Policies'!$C$13/100)*'Pricing Policies'!$D$11 -> 0 | AI19: =AD19*(1+'Pricing Policies'!$C$13/100)*'Pricing Policies'!$E$11 -> 0 | AJ19: =AD19*(1+'Pricing Policies'!$C$13/100)*'Pricing Policies'!$F$11 -> 0 | AK19: =AD19*(1+'Pricing Policies'!$C$14/100)*'Pricing Policies'!$D$11 -> 0 | AL19: =AD19*(1+'Pricing Policies'!$C$14/100)*'Pricing Policies'!$E$11 -> 0 | AM19: =AD19*(1+'Pricing Policies'!$C$14/100)*'Pricing Policies'!$F$11 -> 0 | AN19: =(T$2*T19+U$2*U19+V$2*V19+W$2*W19+X$2*X19+Y$2*Y19+Z$2*Z19+AA$2*AA19+AB$2*AB19) -> 221.70075 | AO19: =(AE$2*AE19+AF$2*AF19+AG$2*AG19+AH$2*AH19+AI$2*AI19+AJ$2*AJ19+AK$2*AK19+AL$2*AL19+AM$2*AM19) -> 0 | AP19: =AN19+AO19 -> 221.70075 | AQ19: =CEILING(AP19,5) -> 225 | AR19: =AR$2 -> 0.1 | AS19: =AQ19*AR19 -> 22.5 | AT19: =AT$2 -> 0.05 | AU19: =(AQ19+AS19)*AT19 -> 12.375 | AV19: =AQ19+AS19+AU19 -> 259.875 | AW19: =CEILING(AV19,5) -> 260 | AX19: =AW19-AU19-AS19-AD19 -> 225.125 | AY19: =AX19*AY$2 -> 56.28125 | AZ19: =AY19/D19 -> 18.760417 | BA19: =IF(AZ19<BD$9,BD$9,IF(AZ19>BD$10,BD$10,AZ19)) -> 18.760417
A20: =CONCATENATE(B20, " - ",C20) -> Civitavecchia - TRF | B20: Civitavecchia | C20: TRF | D20: 5 | E20: 370 | F20: 5 | M20: =(E20)*'Base Operating Costs'!$B$13 -> 70.3 | N20: =(E20)*'Base Operating Costs'!$B$14 -> 52.065369 | O20: ='Base Operating Costs'!$B$15*(E20) -> 59.570694 | P20: =D20*'Base Operating Costs'!$B$4 -> 110 | Q20: =F20 -> 5 | R20: =M20+N20+O20+P20+Q20 -> 296.93606 | S20: =R20*((100+O$2*EXP(-1*E20/P$2))/100)*IF(E20<M$2,1,(1-(N$2/100))) -> 297.03178 | T20: =S20*(1+'Pricing Policies'!$C$5/100)*'Pricing Policies'!$D$4*IF($C20="TRF",1,(1+Markups!$B$4/100)) -> 343.36873 | U20: =S20*(1+'Pricing Policies'!$C$5/100)*'Pricing Policies'!$E$4*IF($C20="TRF",1,(1+Markups!$B$4/100)) -> 403.96322 | V20: =S20*(1+'Pricing Policies'!$C$5/100)*'Pricing Policies'!$F$4*IF($C20="TRF",1,(1+Markups!$B$4/100)) -> 484.75586 | W20: =S20*(1+'Pricing Policies'!$C$6/100)*'Pricing Policies'!$D$4*IF($C20="TRF",1,(1+Markups!$B$4/100)) -> 366.09167 | X20: =S20*(1+'Pricing Policies'!$C$6/100)*'Pricing Policies'!$E$4*IF($C20="TRF",1,(1+Markups!$B$4/100)) -> 430.69608 | Y20: =S20*(1+'Pricing Policies'!$C$6/100)*'Pricing Policies'!$F$4*IF($C20="TRF",1,(1+Markups!$B$4/100)) -> 516.83529 | Z20: =S20*(1+'Pricing Policies'!$C$7/100)*'Pricing Policies'!$D$4*IF($C20="TRF",1,(1+Markups!$B$4/100)) -> 400.17606 | AA20: =S20*(1+'Pricing Policies'!$C$7/100)*'Pricing Policies'!$E$4*IF($C20="TRF",1,(1+Markups!$B$4/100)) -> 470.79537 | AB20: =S20*(1+'Pricing Policies'!$C$7/100)*'Pricing Policies'!$F$4*IF($C20="TRF",1,(1+Markups!$B$4/100)) -> 564.95444 | AC20: =AC$2 -> 2 | AD20: =AC20*K20 -> 0 | AE20: =AD20*(1+'Pricing Policies'!$C$12/100)*'Pricing Policies'!$D$11 -> 0 | AF20: =AD20*(1+'Pricing Policies'!$C$12/100)*'Pricing Policies'!$E$11 -> 0 | AG20: =AD20*(1+'Pricing Policies'!$C$12/100)*'Pricing Policies'!$F$11 -> 0 | AH20: =AD20*(1+'Pricing Policies'!$C$13/100)*'Pricing Policies'!$D$11 -> 0 | AI20: =AD20*(1+'Pricing Policies'!$C$13/100)*'Pricing Policies'!$E$11 -> 0 | AJ20: =AD20*(1+'Pricing Policies'!$C$13/100)*'Pricing Policies'!$F$11 -> 0 | AK20: =AD20*(1+'Pricing Policies'!$C$14/100)*'Pricing Policies'!$D$11 -> 0 | AL20: =AD20*(1+'Pricing Policies'!$C$14/100)*'Pricing Policies'!$E$11 -> 0 | AM20: =AD20*(1+'Pricing Policies'!$C$14/100)*'Pricing Policies'!$F$11 -> 0 | AN20: =(T$2*T20+U$2*U20+V$2*V20+W$2*W20+X$2*X20+Y$2*Y20+Z$2*Z20+AA$2*AA20+AB$2*AB20) -> 403.96322 | AO20: =(AE$2*AE20+AF$2*AF20+AG$2*AG20+AH$2*AH20+AI$2*AI20+AJ$2*AJ20+AK$2*AK20+AL$2*AL20+AM$2*AM20) -> 0 | AP20: =AN20+AO20 -> 403.96322 | AQ20: =CEILING(AP20,5) -> 405 | AR20: =AR$2 -> 0.1 | AS20: =AQ20*AR20 -> 40.5 | AT20: =AT$2 -> 0.05 | AU20: =(AQ20+AS20)*AT20 -> 22.275 | AV20: =AQ20+AS20+AU20 -> 467.775 | AW20: =CEILING(AV20,5) -> 470 | AX20: =AW20-AU20-AS20-AD20 -> 407.225 | AY20: =AX20*AY$2 -> 101.80625 | AZ20: =AY20/D20 -> 20.36125 | BA20: =IF(AZ20<BD$9,BD$9,IF(AZ20>BD$10,BD$10,AZ20)) -> 20.36125
A21: =CONCATENATE(B21, " - ",C21) -> Cortona - TRF | B21: Cortona | C21: TRF | D21: 3 | E21: 150 | F21: 0 | M21: =(E21)*'Base Operating Costs'!$B$13 -> 28.5 | N21: =(E21)*'Base Operating Costs'!$B$14 -> 21.107582 | O21: ='Base Operating Costs'!$B$15*(E21) -> 24.150281 | P21: =D21*'Base Operating Costs'!$B$4 -> 66 | Q21: =F21 -> 0 | R21: =M21+N21+O21+P21+Q21 -> 139.75786 | S21: =R21*((100+O$2*EXP(-1*E21/P$2))/100)*IF(E21<M$2,1,(1-(N$2/100))) -> 145.74073 | T21: =S21*(1+'Pricing Policies'!$C$5/100)*'Pricing Policies'!$D$4*IF($C21="TRF",1,(1+Markups!$B$4/100)) -> 168.47628 | U21: =S21*(1+'Pricing Policies'!$C$5/100)*'Pricing Policies'!$E$4*IF($C21="TRF",1,(1+Markups!$B$4/100)) -> 198.20739 | V21: =S21*(1+'Pricing Policies'!$C$5/100)*'Pricing Policies'!$F$4*IF($C21="TRF",1,(1+Markups!$B$4/100)) -> 237.84887 | W21: =S21*(1+'Pricing Policies'!$C$6/100)*'Pricing Policies'!$D$4*IF($C21="TRF",1,(1+Markups!$B$4/100)) -> 179.62545 | X21: =S21*(1+'Pricing Policies'!$C$6/100)*'Pricing Policies'!$E$4*IF($C21="TRF",1,(1+Markups!$B$4/100)) -> 211.32406 | Y21: =S21*(1+'Pricing Policies'!$C$6/100)*'Pricing Policies'!$F$4*IF($C21="TRF",1,(1+Markups!$B$4/100)) -> 253.58887 | Z21: =S21*(1+'Pricing Policies'!$C$7/100)*'Pricing Policies'!$D$4*IF($C21="TRF",1,(1+Markups!$B$4/100)) -> 196.3492 | AA21: =S21*(1+'Pricing Policies'!$C$7/100)*'Pricing Policies'!$E$4*IF($C21="TRF",1,(1+Markups!$B$4/100)) -> 230.99905 | AB21: =S21*(1+'Pricing Policies'!$C$7/100)*'Pricing Policies'!$F$4*IF($C21="TRF",1,(1+Markups!$B$4/100)) -> 277.19887 | AC21: =AC$2 -> 2 | AD21: =AC21*K21 -> 0 | AE21: =AD21*(1+'Pricing Policies'!$C$12/100)*'Pricing Policies'!$D$11 -> 0 | AF21: =AD21*(1+'Pricing Policies'!$C$12/100)*'Pricing Policies'!$E$11 -> 0 | AG21: =AD21*(1+'Pricing Policies'!$C$12/100)*'Pricing Policies'!$F$11 -> 0 | AH21: =AD21*(1+'Pricing Policies'!$C$13/100)*'Pricing Policies'!$D$11 -> 0 | AI21: =AD21*(1+'Pricing Policies'!$C$13/100)*'Pricing Policies'!$E$11 -> 0 | AJ21: =AD21*(1+'Pricing Policies'!$C$13/100)*'Pricing Policies'!$F$11 -> 0 | AK21: =AD21*(1+'Pricing Policies'!$C$14/100)*'Pricing Policies'!$D$11 -> 0 | AL21: =AD21*(1+'Pricing Policies'!$C$14/100)*'Pricing Policies'!$E$11 -> 0 | AM21: =AD21*(1+'Pricing Policies'!$C$14/100)*'Pricing Policies'!$F$11 -> 0 | AN21: =(T$2*T21+U$2*U21+V$2*V21+W$2*W21+X$2*X21+Y$2*Y21+Z$2*Z21+AA$2*AA21+AB$2*AB21) -> 198.20739 | AO21: =(AE$2*AE21+AF$2*AF21+AG$2*AG21+AH$2*AH21+AI$2*AI21+AJ$2*AJ21+AK$2*AK21+AL$2*AL21+AM$2*AM21) -> 0 | AP21: =AN21+AO21 -> 198.20739 | AQ21: =CEILING(AP21,5) -> 200 | AR21: =AR$2 -> 0.1 | AS21: =AQ21*AR21 -> 20 | AT21: =AT$2 -> 0.05 | AU21: =(AQ21+AS21)*AT21 -> 11 | AV21: =AQ21+AS21+AU21 -> 231 | AW21: =CEILING(AV21,5) -> 235 | AX21: =AW21-AU21-AS21-AD21 -> 204 | AY21: =AX21*AY$2 -> 51 | AZ21: =AY21/D21 -> 17 | BA21: =IF(AZ21<BD$9,BD$9,IF(AZ21>BD$10,BD$10,AZ21)) -> 17
A22: =CONCATENATE(B22, " - ",C22) -> Grosseto - TRF | B22: Grosseto | C22: TRF | D22: 3 | E22: 150 | F22: 0 | M22: =(E22)*'Base Operating Costs'!$B$13 -> 28.5 | N22: =(E22)*'Base Operating Costs'!$B$14 -> 21.107582 | O22: ='Base Operating Costs'!$B$15*(E22) -> 24.150281 | P22: =D22*'Base Operating Costs'!$B$4 -> 66 | Q22: =F22 -> 0 | R22: =M22+N22+O22+P22+Q22 -> 139.75786 | S22: =R22*((100+O$2*EXP(-1*E22/P$2))/100)*IF(E22<M$2,1,(1-(N$2/100))) -> 145.74073 | T22: =S22*(1+'Pricing Policies'!$C$5/100)*'Pricing Policies'!$D$4*IF($C22="TRF",1,(1+Markups!$B$4/100)) -> 168.47628 | U22: =S22*(1+'Pricing Policies'!$C$5/100)*'Pricing Policies'!$E$4*IF($C22="TRF",1,(1+Markups!$B$4/100)) -> 198.20739 | V22: =S22*(1+'Pricing Policies'!$C$5/100)*'Pricing Policies'!$F$4*IF($C22="TRF",1,(1+Markups!$B$4/100)) -> 237.84887 | W22: =S22*(1+'Pricing Policies'!$C$6/100)*'Pricing Policies'!$D$4*IF($C22="TRF",1,(1+Markups!$B$4/100)) -> 179.62545 | X22: =S22*(1+'Pricing Policies'!$C$6/100)*'Pricing Policies'!$E$4*IF($C22="TRF",1,(1+Markups!$B$4/100)) -> 211.32406 | Y22: =S22*(1+'Pricing Policies'!$C$6/100)*'Pricing Policies'!$F$4*IF($C22="TRF",1,(1+Markups!$B$4/100)) -> 253.58887 | Z22: =S22*(1+'Pricing Policies'!$C$7/100)*'Pricing Policies'!$D$4*IF($C22="TRF",1,(1+Markups!$B$4/100)) -> 196.3492 | AA22: =S22*(1+'Pricing Policies'!$C$7/100)*'Pricing Policies'!$E$4*IF($C22="TRF",1,(1+Markups!$B$4/100)) -> 230.99905 | AB22: =S22*(1+'Pricing Policies'!$C$7/100)*'Pricing Policies'!$F$4*IF($C22="TRF",1,(1+Markups!$B$4/100)) -> 277.19887 | AC22: =AC$2 -> 2 | AD22: =AC22*K22 -> 0 | AE22: =AD22*(1+'Pricing Policies'!$C$12/100)*'Pricing Policies'!$D$11 -> 0 | AF22: =AD22*(1+'Pricing Policies'!$C$12/100)*'Pricing Policies'!$E$11 -> 0 | AG22: =AD22*(1+'Pricing Policies'!$C$12/100)*'Pricing Policies'!$F$11 -> 0 | AH22: =AD22*(1+'Pricing Policies'!$C$13/100)*'Pricing Policies'!$D$11 -> 0 | AI22: =AD22*(1+'Pricing Policies'!$C$13/100)*'Pricing Policies'!$E$11 -> 0 | AJ22: =AD22*(1+'Pricing Policies'!$C$13/100)*'Pricing Policies'!$F$11 -> 0 | AK22: =AD22*(1+'Pricing Policies'!$C$14/100)*'Pricing Policies'!$D$11 -> 0 | AL22: =AD22*(1+'Pricing Policies'!$C$14/100)*'Pricing Policies'!$E$11 -> 0 | AM22: =AD22*(1+'Pricing Policies'!$C$14/100)*'Pricing Policies'!$F$11 -> 0 | AN22: =(T$2*T22+U$2*U22+V$2*V22+W$2*W22+X$2*X22+Y$2*Y22+Z$2*Z22+AA$2*AA22+AB$2*AB22) -> 198.20739 | AO22: =(AE$2*AE22+AF$2*AF22+AG$2*AG22+AH$2*AH22+AI$2*AI22+AJ$2*AJ22+AK$2*AK22+AL$2*AL22+AM$2*AM22) -> 0 | AP22: =AN22+AO22 -> 198.20739 | AQ22: =CEILING(AP22,5) -> 200 | AR22: =AR$2 -> 0.1 | AS22: =AQ22*AR22 -> 20 | AT22: =AT$2 -> 0.05 | AU22: =(AQ22+AS22)*AT22 -> 11 | AV22: =AQ22+AS22+AU22 -> 231 | AW22: =CEILING(AV22,5) -> 235 | AX22: =AW22-AU22-AS22-AD22 -> 204 | AY22: =AX22*AY$2 -> 51 | AZ22: =AY22/D22 -> 17 | BA22: =IF(AZ22<BD$9,BD$9,IF(AZ22>BD$10,BD$10,AZ22)) -> 17
A23: =CONCATENATE(B23, " - ",C23) -> Como - TRF | B23: Como | C23: TRF | D23: 10 | E23: 840 | F23: 65 | M23: =(E23)*'Base Operating Costs'!$B$13 -> 159.6 | N23: =(E23)*'Base Operating Costs'!$B$14 -> 118.20246 | O23: ='Base Operating Costs'!$B$15*(E23) -> 135.24158 | P23: =D23*'Base Operating Costs'!$B$4 -> 220 | Q23: =F23 -> 65 | R23: =M23+N23+O23+P23+Q23 -> 698.04403 | S23: =R23*((100+O$2*EXP(-1*E23/P$2))/100)*IF(E23<M$2,1,(1-(N$2/100))) -> 628.23964 | T23: =S23*(1+'Pricing Policies'!$C$5/100)*'Pricing Policies'!$D$4*IF($C23="TRF",1,(1+Markups!$B$4/100)) -> 726.24502 | U23: =S23*(1+'Pricing Policies'!$C$5/100)*'Pricing Policies'!$E$4*IF($C23="TRF",1,(1+Markups!$B$4/100)) -> 854.40591 | V23: =S23*(1+'Pricing Policies'!$C$5/100)*'Pricing Policies'!$F$4*IF($C23="TRF",1,(1+Markups!$B$4/100)) -> 1025.2871 | W23: =S23*(1+'Pricing Policies'!$C$6/100)*'Pricing Policies'!$D$4*IF($C23="TRF",1,(1+Markups!$B$4/100)) -> 774.30535 | X23: =S23*(1+'Pricing Policies'!$C$6/100)*'Pricing Policies'!$E$4*IF($C23="TRF",1,(1+Markups!$B$4/100)) -> 910.94747 | Y23: =S23*(1+'Pricing Policies'!$C$6/100)*'Pricing Policies'!$F$4*IF($C23="TRF",1,(1+Markups!$B$4/100)) -> 1093.137 | Z23: =S23*(1+'Pricing Policies'!$C$7/100)*'Pricing Policies'!$D$4*IF($C23="TRF",1,(1+Markups!$B$4/100)) -> 846.39585 | AA23: =S23*(1+'Pricing Policies'!$C$7/100)*'Pricing Policies'!$E$4*IF($C23="TRF",1,(1+Markups!$B$4/100)) -> 995.75982 | AB23: =S23*(1+'Pricing Policies'!$C$7/100)*'Pricing Policies'!$F$4*IF($C23="TRF",1,(1+Markups!$B$4/100)) -> 1194.9118 | AC23: =AC$2 -> 2 | AD23: =AC23*K23 -> 0 | AE23: =AD23*(1+'Pricing Policies'!$C$12/100)*'Pricing Policies'!$D$11 -> 0 | AF23: =AD23*(1+'Pricing Policies'!$C$12/100)*'Pricing Policies'!$E$11 -> 0 | AG23: =AD23*(1+'Pricing Policies'!$C$12/100)*'Pricing Policies'!$F$11 -> 0 | AH23: =AD23*(1+'Pricing Policies'!$C$13/100)*'Pricing Policies'!$D$11 -> 0 | AI23: =AD23*(1+'Pricing Policies'!$C$13/100)*'Pricing Policies'!$E$11 -> 0 | AJ23: =AD23*(1+'Pricing Policies'!$C$13/100)*'Pricing Policies'!$F$11 -> 0 | AK23: =AD23*(1+'Pricing Policies'!$C$14/100)*'Pricing Policies'!$D$11 -> 0 | AL23: =AD23*(1+'Pricing Policies'!$C$14/100)*'Pricing Policies'!$E$11 -> 0 | AM23: =AD23*(1+'Pricing Policies'!$C$14/100)*'Pricing Policies'!$F$11 -> 0 | AN23: =(T$2*T23+U$2*U23+V$2*V23+W$2*W23+X$2*X23+Y$2*Y23+Z$2*Z23+AA$2*AA23+AB$2*AB23) -> 854.40591 | AO23: =(AE$2*AE23+AF$2*AF23+AG$2*AG23+AH$2*AH23+AI$2*AI23+AJ$2*AJ23+AK$2*AK23+AL$2*AL23+AM$2*AM23) -> 0 | AP23: =AN23+AO23 -> 854.40591 | AQ23: =CEILING(AP23,5) -> 855 | AR23: =AR$2 -> 0.1 | AS23: =AQ23*AR23 -> 85.5 | AT23: =AT$2 -> 0.05 | AU23: =(AQ23+AS23)*AT23 -> 47.025 | AV23: =AQ23+AS23+AU23 -> 987.525 | AW23: =CEILING(AV23,5) -> 990 | AX23: =AW23-AU23-AS23-AD23 -> 857.475 | AY23: =AX23*AY$2 -> 214.36875 | AZ23: =AY23/D23 -> 21.436875 | BA23: =IF(AZ23<BD$9,BD$9,IF(AZ23>BD$10,BD$10,AZ23)) -> 21.436875
A24: =CONCATENATE(B24, " - ",C24) -> Bologna - TRF | B24: Bologna | C24: TRF | D24: 5 | E24: 340 | F24: 20 | M24: =(E24)*'Base Operating Costs'!$B$13 -> 64.6 | N24: =(E24)*'Base Operating Costs'!$B$14 -> 47.843852 | O24: ='Base Operating Costs'!$B$15*(E24) -> 54.740637 | P24: =D24*'Base Operating Costs'!$B$4 -> 110 | Q24: =F24 -> 20 | R24: =M24+N24+O24+P24+Q24 -> 297.18449 | S24: =R24*((100+O$2*EXP(-1*E24/P$2))/100)*IF(E24<M$2,1,(1-(N$2/100))) -> 297.37107 | T24: =S24*(1+'Pricing Policies'!$C$5/100)*'Pricing Policies'!$D$4*IF($C24="TRF",1,(1+Markups!$B$4/100)) -> 343.76096 | U24: =S24*(1+'Pricing Policies'!$C$5/100)*'Pricing Policies'!$E$4*IF($C24="TRF",1,(1+Markups!$B$4/100)) -> 404.42466 | V24: =S24*(1+'Pricing Policies'!$C$5/100)*'Pricing Policies'!$F$4*IF($C24="TRF",1,(1+Markups!$B$4/100)) -> 485.30959 | W24: =S24*(1+'Pricing Policies'!$C$6/100)*'Pricing Policies'!$D$4*IF($C24="TRF",1,(1+Markups!$B$4/100)) -> 366.50985 | X24: =S24*(1+'Pricing Policies'!$C$6/100)*'Pricing Policies'!$E$4*IF($C24="TRF",1,(1+Markups!$B$4/100)) -> 431.18806 | Y24: =S24*(1+'Pricing Policies'!$C$6/100)*'Pricing Policies'!$F$4*IF($C24="TRF",1,(1+Markups!$B$4/100)) -> 517.42567 | Z24: =S24*(1+'Pricing Policies'!$C$7/100)*'Pricing Policies'!$D$4*IF($C24="TRF",1,(1+Markups!$B$4/100)) -> 400.63318 | AA24: =S24*(1+'Pricing Policies'!$C$7/100)*'Pricing Policies'!$E$4*IF($C24="TRF",1,(1+Markups!$B$4/100)) -> 471.33315 | AB24: =S24*(1+'Pricing Policies'!$C$7/100)*'Pricing Policies'!$F$4*IF($C24="TRF",1,(1+Markups!$B$4/100)) -> 565.59978 | AC24: =AC$2 -> 2 | AD24: =AC24*K24 -> 0 | AE24: =AD24*(1+'Pricing Policies'!$C$12/100)*'Pricing Policies'!$D$11 -> 0 | AF24: =AD24*(1+'Pricing Policies'!$C$12/100)*'Pricing Policies'!$E$11 -> 0 | AG24: =AD24*(1+'Pricing Policies'!$C$12/100)*'Pricing Policies'!$F$11 -> 0 | AH24: =AD24*(1+'Pricing Policies'!$C$13/100)*'Pricing Policies'!$D$11 -> 0 | AI24: =AD24*(1+'Pricing Policies'!$C$13/100)*'Pricing Policies'!$E$11 -> 0 | AJ24: =AD24*(1+'Pricing Policies'!$C$13/100)*'Pricing Policies'!$F$11 -> 0 | AK24: =AD24*(1+'Pricing Policies'!$C$14/100)*'Pricing Policies'!$D$11 -> 0 | AL24: =AD24*(1+'Pricing Policies'!$C$14/100)*'Pricing Policies'!$E$11 -> 0 | AM24: =AD24*(1+'Pricing Policies'!$C$14/100)*'Pricing Policies'!$F$11 -> 0 | AN24: =(T$2*T24+U$2*U24+V$2*V24+W$2*W24+X$2*X24+Y$2*Y24+Z$2*Z24+AA$2*AA24+AB$2*AB24) -> 404.42466 | AO24: =(AE$2*AE24+AF$2*AF24+AG$2*AG24+AH$2*AH24+AI$2*AI24+AJ$2*AJ24+AK$2*AK24+AL$2*AL24+AM$2*AM24) -> 0 | AP24: =AN24+AO24 -> 404.42466 | AQ24: =CEILING(AP24,5) -> 405 | AR24: =AR$2 -> 0.1 | AS24: =AQ24*AR24 -> 40.5 | AT24: =AT$2 -> 0.05 | AU24: =(AQ24+AS24)*AT24 -> 22.275 | AV24: =AQ24+AS24+AU24 -> 467.775 | AW24: =CEILING(AV24,5) -> 470 | AX24: =AW24-AU24-AS24-AD24 -> 407.225 | AY24: =AX24*AY$2 -> 101.80625 | AZ24: =AY24/D24 -> 20.36125 | BA24: =IF(AZ24<BD$9,BD$9,IF(AZ24>BD$10,BD$10,AZ24)) -> 20.36125
... A45: =CONCATENATE(B45, " - ",C45) -> Venezia - TRF | B45: Venezia | C45: TRF | D45: 8 | E45: 640 | F45: 45 | M45: =(E45)*'Base Operating Costs'!$B$13 -> 121.6 | N45: =(E45)*'Base Operating Costs'!$B$14 -> 90.059016 | O45: ='Base Operating Costs'!$B$15*(E45) -> 103.0412 | P45: =D45*'Base Operating Costs'!$B$4 -> 176 | Q45: =F45 -> 45 | R45: =M45+N45+O45+P45+Q45 -> 535.70022 | S45: =R45*((100+O$2*EXP(-1*E45/P$2))/100)*IF(E45<M$2,1,(1-(N$2/100))) -> 482.13058 | T45: =S45*(1+'Pricing Policies'!$C$5/100)*'Pricing Policies'!$D$4*IF($C45="TRF",1,(1+Markups!$B$4/100)) -> 557.34295 | U45: =S45*(1+'Pricing Policies'!$C$5/100)*'Pricing Policies'!$E$4*IF($C45="TRF",1,(1+Markups!$B$4/100)) -> 655.69759 | V45: =S45*(1+'Pricing Policies'!$C$5/100)*'Pricing Policies'!$F$4*IF($C45="TRF",1,(1+Markups!$B$4/100)) -> 786.83711 | W45: =S45*(1+'Pricing Policies'!$C$6/100)*'Pricing Policies'!$D$4*IF($C45="TRF",1,(1+Markups!$B$4/100)) -> 594.22594 | X45: =S45*(1+'Pricing Policies'!$C$6/100)*'Pricing Policies'!$E$4*IF($C45="TRF",1,(1+Markups!$B$4/100)) -> 699.08934 | Y45: =S45*(1+'Pricing Policies'!$C$6/100)*'Pricing Policies'!$F$4*IF($C45="TRF",1,(1+Markups!$B$4/100)) -> 838.90721 | Z45: =S45*(1+'Pricing Policies'!$C$7/100)*'Pricing Policies'!$D$4*IF($C45="TRF",1,(1+Markups!$B$4/100)) -> 649.55042 | AA45: =S45*(1+'Pricing Policies'!$C$7/100)*'Pricing Policies'!$E$4*IF($C45="TRF",1,(1+Markups!$B$4/100)) -> 764.17697 | AB45: =S45*(1+'Pricing Policies'!$C$7/100)*'Pricing Policies'!$F$4*IF($C45="TRF",1,(1+Markups!$B$4/100)) -> 917.01236 | AC45: =AC$2 -> 2 | AD45: =AC45*K45 -> 0 | AE45: =AD45*(1+'Pricing Policies'!$C$12/100)*'Pricing Policies'!$D$11 -> 0 | AF45: =AD45*(1+'Pricing Policies'!$C$12/100)*'Pricing Policies'!$E$11 -> 0 | AG45: =AD45*(1+'Pricing Policies'!$C$12/100)*'Pricing Policies'!$F$11 -> 0 | AH45: =AD45*(1+'Pricing Policies'!$C$13/100)*'Pricing Policies'!$D$11 -> 0 | AI45: =AD45*(1+'Pricing Policies'!$C$13/100)*'Pricing Policies'!$E$11 -> 0 | AJ45: =AD45*(1+'Pricing Policies'!$C$13/100)*'Pricing Policies'!$F$11 -> 0 | AK45: =AD45*(1+'Pricing Policies'!$C$14/100)*'Pricing Policies'!$D$11 -> 0 | AL45: =AD45*(1+'Pricing Policies'!$C$14/100)*'Pricing Policies'!$E$11 -> 0 | AM45: =AD45*(1+'Pricing Policies'!$C$14/100)*'Pricing Policies'!$F$11 -> 0 | AN45: =(T$2*T45+U$2*U45+V$2*V45+W$2*W45+X$2*X45+Y$2*Y45+Z$2*Z45+AA$2*AA45+AB$2*AB45) -> 655.69759 | AO45: =(AE$2*AE45+AF$2*AF45+AG$2*AG45+AH$2*AH45+AI$2*AI45+AJ$2*AJ45+AK$2*AK45+AL$2*AL45+AM$2*AM45) -> 0 | AP45: =AN45+AO45 -> 655.69759 | AQ45: =CEILING(AP45,5) -> 660 | AR45: =AR$2 -> 0.1 | AS45: =AQ45*AR45 -> 66 | AT45: =AT$2 -> 0.05 | AU45: =(AQ45+AS45)*AT45 -> 36.3 | AV45: =AQ45+AS45+AU45 -> 762.3 | AW45: =CEILING(AV45,5) -> 765 | AX45: =AW45-AU45-AS45-AD45 -> 662.7 | AY45: =AX45*AY$2 -> 165.675 | AZ45: =AY45/D45 -> 20.709375 | BA45: =IF(AZ45<BD$9,BD$9,IF(AZ45>BD$10,BD$10,AZ45)) -> 20.709375
M46: =(E46)*'Base Operating Costs'!$B$13 -> 0 | N46: =(E46)*'Base Operating Costs'!$B$14 -> 0 | O46: ='Base Operating Costs'!$B$15*(E46) -> 0 | P46: =D46*'Base Operating Costs'!$B$4 -> 0 | Q46: =F46 | S46: =M46+N46+O46+P46+Q46 -> 0 | T46: =S46*(1+'Pricing Policies'!$C$5/100)*'Pricing Policies'!$D$4*IF($C46="TRF",1,(1+Markups!$B$4/100)) -> 0 | U46: =S46*(1+'Pricing Policies'!$C$5/100)*'Pricing Policies'!$E$4*IF($C46="TRF",1,(1+Markups!$B$4/100)) -> 0 | V46: =S46*(1+'Pricing Policies'!$C$5/100)*'Pricing Policies'!$F$4*IF($C46="TRF",1,(1+Markups!$B$4/100)) -> 0 | W46: =S46*(1+'Pricing Policies'!$C$6/100)*'Pricing Policies'!$D$4*IF($C46="TRF",1,(1+Markups!$B$4/100)) -> 0 | X46: =S46*(1+'Pricing Policies'!$C$6/100)*'Pricing Policies'!$E$4*IF($C46="TRF",1,(1+Markups!$B$4/100)) -> 0 | Y46: =S46*(1+'Pricing Policies'!$C$6/100)*'Pricing Policies'!$F$4*IF($C46="TRF",1,(1+Markups!$B$4/100)) -> 0 | Z46: =S46*(1+'Pricing Policies'!$C$7/100)*'Pricing Policies'!$D$4*IF($C46="TRF",1,(1+Markups!$B$4/100)) -> 0 | AA46: =S46*(1+'Pricing Policies'!$C$7/100)*'Pricing Policies'!$E$4*IF($C46="TRF",1,(1+Markups!$B$4/100)) -> 0 | AB46: =S46*(1+'Pricing Policies'!$C$7/100)*'Pricing Policies'!$F$4*IF($C46="TRF",1,(1+Markups!$B$4/100)) -> 0 | AC46: =AC$2 -> 2 | AD46: =AC46*K46 -> 0 | AE46: =AD46*(1+'Pricing Policies'!$C$12/100)*'Pricing Policies'!$D$11 -> 0 | AF46: =AD46*(1+'Pricing Policies'!$C$12/100)*'Pricing Policies'!$E$11 -> 0 | AG46: =AD46*(1+'Pricing Policies'!$C$12/100)*'Pricing Policies'!$F$11 -> 0 | AH46: =AD46*(1+'Pricing Policies'!$C$13/100)*'Pricing Policies'!$D$11 -> 0 | AI46: =AD46*(1+'Pricing Policies'!$C$13/100)*'Pricing Policies'!$E$11 -> 0 | AJ46: =AD46*(1+'Pricing Policies'!$C$13/100)*'Pricing Policies'!$F$11 -> 0 | AK46: =AD46*(1+'Pricing Policies'!$C$14/100)*'Pricing Policies'!$D$11 -> 0 | AL46: =AD46*(1+'Pricing Policies'!$C$14/100)*'Pricing Policies'!$E$11 -> 0 | AM46: =AD46*(1+'Pricing Policies'!$C$14/100)*'Pricing Policies'!$F$11 -> 0 | AN46: =(T$2*T46+U$2*U46+V$2*V46+W$2*W46+X$2*X46+Y$2*Y46+Z$2*Z46+AA$2*AA46+AB$2*AB46) -> 0 | AO46: =(AE$2*AE46+AF$2*AF46+AG$2*AG46+AH$2*AH46+AI$2*AI46+AJ$2*AJ46+AK$2*AK46+AL$2*AL46+AM$2*AM46) -> 0 | AQ46: =AN46+AO46 -> 0 | AR46: =AR$2 -> 0.1 | AS46: =AQ46*AR46 -> 0 | AT46: =AT$2 -> 0.05 | AU46: =(AQ46+AS46)*AT46 -> 0 | AW46: =AQ46+AS46+AU46 -> 0 | AX46: =AW46-AU46-AS46-AD46 -> 0 | AY46: =AX46*AY$2 -> 0 | AZ46: =AY46/D46 -> #DIV/0!
M47: =(E47)*'Base Operating Costs'!$B$13 -> 0 | N47: =(E47)*'Base Operating Costs'!$B$14 -> 0 | O47: ='Base Operating Costs'!$B$15*(E47) -> 0 | P47: =D47*'Base Operating Costs'!$B$4 -> 0 | Q47: =F47 | S47: =M47+N47+O47+P47+Q47 -> 0 | T47: =S47*(1+'Pricing Policies'!$C$5/100)*'Pricing Policies'!$D$4*IF($C47="TRF",1,(1+Markups!$B$4/100)) -> 0 | U47: =S47*(1+'Pricing Policies'!$C$5/100)*'Pricing Policies'!$E$4*IF($C47="TRF",1,(1+Markups!$B$4/100)) -> 0 | V47: =S47*(1+'Pricing Policies'!$C$5/100)*'Pricing Policies'!$F$4*IF($C47="TRF",1,(1+Markups!$B$4/100)) -> 0 | W47: =S47*(1+'Pricing Policies'!$C$6/100)*'Pricing Policies'!$D$4*IF($C47="TRF",1,(1+Markups!$B$4/100)) -> 0 | X47: =S47*(1+'Pricing Policies'!$C$6/100)*'Pricing Policies'!$E$4*IF($C47="TRF",1,(1+Markups!$B$4/100)) -> 0 | Y47: =S47*(1+'Pricing Policies'!$C$6/100)*'Pricing Policies'!$F$4*IF($C47="TRF",1,(1+Markups!$B$4/100)) -> 0 | Z47: =S47*(1+'Pricing Policies'!$C$7/100)*'Pricing Policies'!$D$4*IF($C47="TRF",1,(1+Markups!$B$4/100)) -> 0 | AA47: =S47*(1+'Pricing Policies'!$C$7/100)*'Pricing Policies'!$E$4*IF($C47="TRF",1,(1+Markups!$B$4/100)) -> 0 | AB47: =S47*(1+'Pricing Policies'!$C$7/100)*'Pricing Policies'!$F$4*IF($C47="TRF",1,(1+Markups!$B$4/100)) -> 0 | AC47: =AC$2 -> 2 | AD47: =AC47*K47 -> 0 | AE47: =AD47*(1+'Pricing Policies'!$C$12/100)*'Pricing Policies'!$D$11 -> 0 | AF47: =AD47*(1+'Pricing Policies'!$C$12/100)*'Pricing Policies'!$E$11 -> 0 | AG47: =AD47*(1+'Pricing Policies'!$C$12/100)*'Pricing Policies'!$F$11 -> 0 | AH47: =AD47*(1+'Pricing Policies'!$C$13/100)*'Pricing Policies'!$D$11 -> 0 | AI47: =AD47*(1+'Pricing Policies'!$C$13/100)*'Pricing Policies'!$E$11 -> 0 | AJ47: =AD47*(1+'Pricing Policies'!$C$13/100)*'Pricing Policies'!$F$11 -> 0 | AK47: =AD47*(1+'Pricing Policies'!$C$14/100)*'Pricing Policies'!$D$11 -> 0 | AL47: =AD47*(1+'Pricing Policies'!$C$14/100)*'Pricing Policies'!$E$11 -> 0 | AM47: =AD47*(1+'Pricing Policies'!$C$14/100)*'Pricing Policies'!$F$11 -> 0 | AN47: =(T$2*T47+U$2*U47+V$2*V47+W$2*W47+X$2*X47+Y$2*Y47+Z$2*Z47+AA$2*AA47+AB$2*AB47) -> 0 | AO47: =(AE$2*AE47+AF$2*AF47+AG$2*AG47+AH$2*AH47+AI$2*AI47+AJ$2*AJ47+AK$2*AK47+AL$2*AL47+AM$2*AM47) -> 0 | AQ47: =AN47+AO47 -> 0 | AR47: =AR$2 -> 0.1 | AS47: =AQ47*AR47 -> 0 | AT47: =AT$2 -> 0.05 | AU47: =(AQ47+AS47)*AT47 -> 0 | AW47: =AQ47+AS47+AU47 -> 0 | AX47: =AW47-AU47-AS47-AD47 -> 0 | AY47: =AX47*AY$2 -> 0 | AZ47: =AY47/D47 -> #DIV/0!
M48: =(E48)*'Base Operating Costs'!$B$13 -> 0 | N48: =(E48)*'Base Operating Costs'!$B$14 -> 0 | O48: ='Base Operating Costs'!$B$15*(E48) -> 0 | P48: =D48*'Base Operating Costs'!$B$4 -> 0 | Q48: =F48 | S48: =M48+N48+O48+P48+Q48 -> 0 | T48: =S48*(1+'Pricing Policies'!$C$5/100)*'Pricing Policies'!$D$4*IF($C48="TRF",1,(1+Markups!$B$4/100)) -> 0 | U48: =S48*(1+'Pricing Policies'!$C$5/100)*'Pricing Policies'!$E$4*IF($C48="TRF",1,(1+Markups!$B$4/100)) -> 0 | V48: =S48*(1+'Pricing Policies'!$C$5/100)*'Pricing Policies'!$F$4*IF($C48="TRF",1,(1+Markups!$B$4/100)) -> 0 | W48: =S48*(1+'Pricing Policies'!$C$6/100)*'Pricing Policies'!$D$4*IF($C48="TRF",1,(1+Markups!$B$4/100)) -> 0 | X48: =S48*(1+'Pricing Policies'!$C$6/100)*'Pricing Policies'!$E$4*IF($C48="TRF",1,(1+Markups!$B$4/100)) -> 0 | Y48: =S48*(1+'Pricing Policies'!$C$6/100)*'Pricing Policies'!$F$4*IF($C48="TRF",1,(1+Markups!$B$4/100)) -> 0 | Z48: =S48*(1+'Pricing Policies'!$C$7/100)*'Pricing Policies'!$D$4*IF($C48="TRF",1,(1+Markups!$B$4/100)) -> 0 | AA48: =S48*(1+'Pricing Policies'!$C$7/100)*'Pricing Policies'!$E$4*IF($C48="TRF",1,(1+Markups!$B$4/100)) -> 0 | AB48: =S48*(1+'Pricing Policies'!$C$7/100)*'Pricing Policies'!$F$4*IF($C48="TRF",1,(1+Markups!$B$4/100)) -> 0 | AC48: =AC$2 -> 2 | AD48: =AC48*K48 -> 0 | AE48: =AD48*(1+'Pricing Policies'!$C$12/100)*'Pricing Policies'!$D$11 -> 0 | AF48: =AD48*(1+'Pricing Policies'!$C$12/100)*'Pricing Policies'!$E$11 -> 0 | AG48: =AD48*(1+'Pricing Policies'!$C$12/100)*'Pricing Policies'!$F$11 -> 0 | AH48: =AD48*(1+'Pricing Policies'!$C$13/100)*'Pricing Policies'!$D$11 -> 0 | AI48: =AD48*(1+'Pricing Policies'!$C$13/100)*'Pricing Policies'!$E$11 -> 0 | AJ48: =AD48*(1+'Pricing Policies'!$C$13/100)*'Pricing Policies'!$F$11 -> 0 | AK48: =AD48*(1+'Pricing Policies'!$C$14/100)*'Pricing Policies'!$D$11 -> 0 | AL48: =AD48*(1+'Pricing Policies'!$C$14/100)*'Pricing Policies'!$E$11 -> 0 | AM48: =AD48*(1+'Pricing Policies'!$C$14/100)*'Pricing Policies'!$F$11 -> 0 | AN48: =(T$2*T48+U$2*U48+V$2*V48+W$2*W48+X$2*X48+Y$2*Y48+Z$2*Z48+AA$2*AA48+AB$2*AB48) -> 0 | AO48: =(AE$2*AE48+AF$2*AF48+AG$2*AG48+AH$2*AH48+AI$2*AI48+AJ$2*AJ48+AK$2*AK48+AL$2*AL48+AM$2*AM48) -> 0 | AQ48: =AN48+AO48 -> 0 | AR48: =AR$2 -> 0.1 | AS48: =AQ48*AR48 -> 0 | AT48: =AT$2 -> 0.05 | AU48: =(AQ48+AS48)*AT48 -> 0 | AW48: =AQ48+AS48+AU48 -> 0 | AX48: =AW48-AU48-AS48-AD48 -> 0 | AY48: =AX48*AY$2 -> 0 | AZ48: =AY48/D48 -> #DIV/0!
M49: =(E49)*'Base Operating Costs'!$B$13 -> 0 | N49: =(E49)*'Base Operating Costs'!$B$14 -> 0 | O49: ='Base Operating Costs'!$B$15*(E49) -> 0 | P49: =D49*'Base Operating Costs'!$B$4 -> 0 | Q49: =F49 | S49: =M49+N49+O49+P49+Q49 -> 0 | T49: =S49*(1+'Pricing Policies'!$C$5/100)*'Pricing Policies'!$D$4*IF($C49="TRF",1,(1+Markups!$B$4/100)) -> 0 | U49: =S49*(1+'Pricing Policies'!$C$5/100)*'Pricing Policies'!$E$4*IF($C49="TRF",1,(1+Markups!$B$4/100)) -> 0 | V49: =S49*(1+'Pricing Policies'!$C$5/100)*'Pricing Policies'!$F$4*IF($C49="TRF",1,(1+Markups!$B$4/100)) -> 0 | W49: =S49*(1+'Pricing Policies'!$C$6/100)*'Pricing Policies'!$D$4*IF($C49="TRF",1,(1+Markups!$B$4/100)) -> 0 | X49: =S49*(1+'Pricing Policies'!$C$6/100)*'Pricing Policies'!$E$4*IF($C49="TRF",1,(1+Markups!$B$4/100)) -> 0 | Y49: =S49*(1+'Pricing Policies'!$C$6/100)*'Pricing Policies'!$F$4*IF($C49="TRF",1,(1+Markups!$B$4/100)) -> 0 | Z49: =S49*(1+'Pricing Policies'!$C$7/100)*'Pricing Policies'!$D$4*IF($C49="TRF",1,(1+Markups!$B$4/100)) -> 0 | AA49: =S49*(1+'Pricing Policies'!$C$7/100)*'Pricing Policies'!$E$4*IF($C49="TRF",1,(1+Markups!$B$4/100)) -> 0 | AB49: =S49*(1+'Pricing Policies'!$C$7/100)*'Pricing Policies'!$F$4*IF($C49="TRF",1,(1+Markups!$B$4/100)) -> 0 | AC49: =AC$2 -> 2 | AD49: =AC49*K49 -> 0 | AE49: =AD49*(1+'Pricing Policies'!$C$12/100)*'Pricing Policies'!$D$11 -> 0 | AF49: =AD49*(1+'Pricing Policies'!$C$12/100)*'Pricing Policies'!$E$11 -> 0 | AG49: =AD49*(1+'Pricing Policies'!$C$12/100)*'Pricing Policies'!$F$11 -> 0 | AH49: =AD49*(1+'Pricing Policies'!$C$13/100)*'Pricing Policies'!$D$11 -> 0 | AI49: =AD49*(1+'Pricing Policies'!$C$13/100)*'Pricing Policies'!$E$11 -> 0 | AJ49: =AD49*(1+'Pricing Policies'!$C$13/100)*'Pricing Policies'!$F$11 -> 0 | AK49: =AD49*(1+'Pricing Policies'!$C$14/100)*'Pricing Policies'!$D$11 -> 0 | AL49: =AD49*(1+'Pricing Policies'!$C$14/100)*'Pricing Policies'!$E$11 -> 0 | AM49: =AD49*(1+'Pricing Policies'!$C$14/100)*'Pricing Policies'!$F$11 -> 0 | AN49: =(T$2*T49+U$2*U49+V$2*V49+W$2*W49+X$2*X49+Y$2*Y49+Z$2*Z49+AA$2*AA49+AB$2*AB49) -> 0 | AO49: =(AE$2*AE49+AF$2*AF49+AG$2*AG49+AH$2*AH49+AI$2*AI49+AJ$2*AJ49+AK$2*AK49+AL$2*AL49+AM$2*AM49) -> 0 | AQ49: =AN49+AO49 -> 0 | AR49: =AR$2 -> 0.1 | AS49: =AQ49*AR49 -> 0 | AT49: =AT$2 -> 0.05 | AU49: =(AQ49+AS49)*AT49 -> 0 | AW49: =AQ49+AS49+AU49 -> 0 | AX49: =AW49-AU49-AS49-AD49 -> 0 | AY49: =AX49*AY$2 -> 0 | AZ49: =AY49/D49 -> #DIV/0!
M50: =(E50)*'Base Operating Costs'!$B$13 -> 0 | N50: =(E50)*'Base Operating Costs'!$B$14 -> 0 | O50: ='Base Operating Costs'!$B$15*(E50) -> 0 | P50: =D50*'Base Operating Costs'!$B$4 -> 0 | Q50: =F50 | S50: =M50+N50+O50+P50+Q50 -> 0 | T50: =S50*(1+'Pricing Policies'!$C$5/100)*'Pricing Policies'!$D$4*IF($C50="TRF",1,(1+Markups!$B$4/100)) -> 0 | U50: =S50*(1+'Pricing Policies'!$C$5/100)*'Pricing Policies'!$E$4*IF($C50="TRF",1,(1+Markups!$B$4/100)) -> 0 | V50: =S50*(1+'Pricing Policies'!$C$5/100)*'Pricing Policies'!$F$4*IF($C50="TRF",1,(1+Markups!$B$4/100)) -> 0 | W50: =S50*(1+'Pricing Policies'!$C$6/100)*'Pricing Policies'!$D$4*IF($C50="TRF",1,(1+Markups!$B$4/100)) -> 0 | X50: =S50*(1+'Pricing Policies'!$C$6/100)*'Pricing Policies'!$E$4*IF($C50="TRF",1,(1+Markups!$B$4/100)) -> 0 | Y50: =S50*(1+'Pricing Policies'!$C$6/100)*'Pricing Policies'!$F$4*IF($C50="TRF",1,(1+Markups!$B$4/100)) -> 0 | Z50: =S50*(1+'Pricing Policies'!$C$7/100)*'Pricing Policies'!$D$4*IF($C50="TRF",1,(1+Markups!$B$4/100)) -> 0 | AA50: =S50*(1+'Pricing Policies'!$C$7/100)*'Pricing Policies'!$E$4*IF($C50="TRF",1,(1+Markups!$B$4/100)) -> 0 | AB50: =S50*(1+'Pricing Policies'!$C$7/100)*'Pricing Policies'!$F$4*IF($C50="TRF",1,(1+Markups!$B$4/100)) -> 0 | AC50: =AC$2 -> 2 | AD50: =AC50*K50 -> 0 | AE50: =AD50*(1+'Pricing Policies'!$C$12/100)*'Pricing Policies'!$D$11 -> 0 | AF50: =AD50*(1+'Pricing Policies'!$C$12/100)*'Pricing Policies'!$E$11 -> 0 | AG50: =AD50*(1+'Pricing Policies'!$C$12/100)*'Pricing Policies'!$F$11 -> 0 | AH50: =AD50*(1+'Pricing Policies'!$C$13/100)*'Pricing Policies'!$D$11 -> 0 | AI50: =AD50*(1+'Pricing Policies'!$C$13/100)*'Pricing Policies'!$E$11 -> 0 | AJ50: =AD50*(1+'Pricing Policies'!$C$13/100)*'Pricing Policies'!$F$11 -> 0 | AK50: =AD50*(1+'Pricing Policies'!$C$14/100)*'Pricing Policies'!$D$11 -> 0 | AL50: =AD50*(1+'Pricing Policies'!$C$14/100)*'Pricing Policies'!$E$11 -> 0 | AM50: =AD50*(1+'Pricing Policies'!$C$14/100)*'Pricing Policies'!$F$11 -> 0 | AN50: =(T$2*T50+U$2*U50+V$2*V50+W$2*W50+X$2*X50+Y$2*Y50+Z$2*Z50+AA$2*AA50+AB$2*AB50) -> 0 | AO50: =(AE$2*AE50+AF$2*AF50+AG$2*AG50+AH$2*AH50+AI$2*AI50+AJ$2*AJ50+AK$2*AK50+AL$2*AL50+AM$2*AM50) -> 0 | AQ50: =AN50+AO50 -> 0 | AR50: =AR$2 -> 0.1 | AS50: =AQ50*AR50 -> 0 | AT50: =AT$2 -> 0.05 | AU50: =(AQ50+AS50)*AT50 -> 0 | AW50: =AQ50+AS50+AU50 -> 0 | AX50: =AW50-AU50-AS50-AD50 -> 0 | AY50: =AX50*AY$2 -> 0 | AZ50: =AY50/D50 -> #DIV/0!
M51: =(E51)*'Base Operating Costs'!$B$13 -> 0 | N51: =(E51)*'Base Operating Costs'!$B$14 -> 0 | O51: ='Base Operating Costs'!$B$15*(E51) -> 0 | P51: =D51*'Base Operating Costs'!$B$4 -> 0 | Q51: =F51 | S51: =M51+N51+O51+P51+Q51 -> 0 | T51: =S51*(1+'Pricing Policies'!$C$5/100)*'Pricing Policies'!$D$4*IF($C51="TRF",1,(1+Markups!$B$4/100)) -> 0 | U51: =S51*(1+'Pricing Policies'!$C$5/100)*'Pricing Policies'!$E$4*IF($C51="TRF",1,(1+Markups!$B$4/100)) -> 0 | V51: =S51*(1+'Pricing Policies'!$C$5/100)*'Pricing Policies'!$F$4*IF($C51="TRF",1,(1+Markups!$B$4/100)) -> 0 | W51: =S51*(1+'Pricing Policies'!$C$6/100)*'Pricing Policies'!$D$4*IF($C51="TRF",1,(1+Markups!$B$4/100)) -> 0 | X51: =S51*(1+'Pricing Policies'!$C$6/100)*'Pricing Policies'!$E$4*IF($C51="TRF",1,(1+Markups!$B$4/100)) -> 0 | Y51: =S51*(1+'Pricing Policies'!$C$6/100)*'Pricing Policies'!$F$4*IF($C51="TRF",1,(1+Markups!$B$4/100)) -> 0 | Z51: =S51*(1+'Pricing Policies'!$C$7/100)*'Pricing Policies'!$D$4*IF($C51="TRF",1,(1+Markups!$B$4/100)) -> 0 | AA51: =S51*(1+'Pricing Policies'!$C$7/100)*'Pricing Policies'!$E$4*IF($C51="TRF",1,(1+Markups!$B$4/100)) -> 0 | AB51: =S51*(1+'Pricing Policies'!$C$7/100)*'Pricing Policies'!$F$4*IF($C51="TRF",1,(1+Markups!$B$4/100)) -> 0 | AC51: =AC$2 -> 2 | AD51: =AC51*K51 -> 0 | AE51: =AD51*(1+'Pricing Policies'!$C$12/100)*'Pricing Policies'!$D$11 -> 0 | AF51: =AD51*(1+'Pricing Policies'!$C$12/100)*'Pricing Policies'!$E$11 -> 0 | AG51: =AD51*(1+'Pricing Policies'!$C$12/100)*'Pricing Policies'!$F$11 -> 0 | AH51: =AD51*(1+'Pricing Policies'!$C$13/100)*'Pricing Policies'!$D$11 -> 0 | AI51: =AD51*(1+'Pricing Policies'!$C$13/100)*'Pricing Policies'!$E$11 -> 0 | AJ51: =AD51*(1+'Pricing Policies'!$C$13/100)*'Pricing Policies'!$F$11 -> 0 | AK51: =AD51*(1+'Pricing Policies'!$C$14/100)*'Pricing Policies'!$D$11 -> 0 | AL51: =AD51*(1+'Pricing Policies'!$C$14/100)*'Pricing Policies'!$E$11 -> 0 | AM51: =AD51*(1+'Pricing Policies'!$C$14/100)*'Pricing Policies'!$F$11 -> 0 | AN51: =(T$2*T51+U$2*U51+V$2*V51+W$2*W51+X$2*X51+Y$2*Y51+Z$2*Z51+AA$2*AA51+AB$2*AB51) -> 0 | AO51: =(AE$2*AE51+AF$2*AF51+AG$2*AG51+AH$2*AH51+AI$2*AI51+AJ$2*AJ51+AK$2*AK51+AL$2*AL51+AM$2*AM51) -> 0 | AQ51: =AN51+AO51 -> 0 | AR51: =AR$2 -> 0.1 | AS51: =AQ51*AR51 -> 0 | AT51: =AT$2 -> 0.05 | AU51: =(AQ51+AS51)*AT51 -> 0 | AW51: =AQ51+AS51+AU51 -> 0 | AX51: =AW51-AU51-AS51-AD51 -> 0 | AY51: =AX51*AY$2 -> 0 | AZ51: =AY51/D51 -> #DIV/0!
M52: =(E52)*'Base Operating Costs'!$B$13 -> 0 | N52: =(E52)*'Base Operating Costs'!$B$14 -> 0 | O52: ='Base Operating Costs'!$B$15*(E52) -> 0 | P52: =D52*'Base Operating Costs'!$B$4 -> 0 | Q52: =F52 | S52: =M52+N52+O52+P52+Q52 -> 0 | T52: =S52*(1+'Pricing Policies'!$C$5/100)*'Pricing Policies'!$D$4*IF($C52="TRF",1,(1+Markups!$B$4/100)) -> 0 | U52: =S52*(1+'Pricing Policies'!$C$5/100)*'Pricing Policies'!$E$4*IF($C52="TRF",1,(1+Markups!$B$4/100)) -> 0 | V52: =S52*(1+'Pricing Policies'!$C$5/100)*'Pricing Policies'!$F$4*IF($C52="TRF",1,(1+Markups!$B$4/100)) -> 0 | W52: =S52*(1+'Pricing Policies'!$C$6/100)*'Pricing Policies'!$D$4*IF($C52="TRF",1,(1+Markups!$B$4/100)) -> 0 | X52: =S52*(1+'Pricing Policies'!$C$6/100)*'Pricing Policies'!$E$4*IF($C52="TRF",1,(1+Markups!$B$4/100)) -> 0 | Y52: =S52*(1+'Pricing Policies'!$C$6/100)*'Pricing Policies'!$F$4*IF($C52="TRF",1,(1+Markups!$B$4/100)) -> 0 | Z52: =S52*(1+'Pricing Policies'!$C$7/100)*'Pricing Policies'!$D$4*IF($C52="TRF",1,(1+Markups!$B$4/100)) -> 0 | AA52: =S52*(1+'Pricing Policies'!$C$7/100)*'Pricing Policies'!$E$4*IF($C52="TRF",1,(1+Markups!$B$4/100)) -> 0 | AB52: =S52*(1+'Pricing Policies'!$C$7/100)*'Pricing Policies'!$F$4*IF($C52="TRF",1,(1+Markups!$B$4/100)) -> 0 | AC52: =AC$2 -> 2 | AD52: =AC52*K52 -> 0 | AE52: =AD52*(1+'Pricing Policies'!$C$12/100)*'Pricing Policies'!$D$11 -> 0 | AF52: =AD52*(1+'Pricing Policies'!$C$12/100)*'Pricing Policies'!$E$11 -> 0 | AG52: =AD52*(1+'Pricing Policies'!$C$12/100)*'Pricing Policies'!$F$11 -> 0 | AH52: =AD52*(1+'Pricing Policies'!$C$13/100)*'Pricing Policies'!$D$11 -> 0 | AI52: =AD52*(1+'Pricing Policies'!$C$13/100)*'Pricing Policies'!$E$11 -> 0 | AJ52: =AD52*(1+'Pricing Policies'!$C$13/100)*'Pricing Policies'!$F$11 -> 0 | AK52: =AD52*(1+'Pricing Policies'!$C$14/100)*'Pricing Policies'!$D$11 -> 0 | AL52: =AD52*(1+'Pricing Policies'!$C$14/100)*'Pricing Policies'!$E$11 -> 0 | AM52: =AD52*(1+'Pricing Policies'!$C$14/100)*'Pricing Policies'!$F$11 -> 0 | AN52: =(T$2*T52+U$2*U52+V$2*V52+W$2*W52+X$2*X52+Y$2*Y52+Z$2*Z52+AA$2*AA52+AB$2*AB52) -> 0 | AO52: =(AE$2*AE52+AF$2*AF52+AG$2*AG52+AH$2*AH52+AI$2*AI52+AJ$2*AJ52+AK$2*AK52+AL$2*AL52+AM$2*AM52) -> 0 | AQ52: =AN52+AO52 -> 0 | AR52: =AR$2 -> 0.1 | AS52: =AQ52*AR52 -> 0 | AT52: =AT$2 -> 0.05 | AU52: =(AQ52+AS52)*AT52 -> 0 | AW52: =AQ52+AS52+AU52 -> 0 | AX52: =AW52-AU52-AS52-AD52 -> 0 | AY52: =AX52*AY$2 -> 0 | AZ52: =AY52/D52 -> #DIV/0!
M53: =(E53)*'Base Operating Costs'!$B$13 -> 0 | N53: =(E53)*'Base Operating Costs'!$B$14 -> 0 | O53: ='Base Operating Costs'!$B$15*(E53) -> 0 | P53: =D53*'Base Operating Costs'!$B$4 -> 0 | Q53: =F53 | S53: =M53+N53+O53+P53+Q53 -> 0 | T53: =S53*(1+'Pricing Policies'!$C$5/100)*'Pricing Policies'!$D$4*IF($C53="TRF",1,(1+Markups!$B$4/100)) -> 0 | U53: =S53*(1+'Pricing Policies'!$C$5/100)*'Pricing Policies'!$E$4*IF($C53="TRF",1,(1+Markups!$B$4/100)) -> 0 | V53: =S53*(1+'Pricing Policies'!$C$5/100)*'Pricing Policies'!$F$4*IF($C53="TRF",1,(1+Markups!$B$4/100)) -> 0 | W53: =S53*(1+'Pricing Policies'!$C$6/100)*'Pricing Policies'!$D$4*IF($C53="TRF",1,(1+Markups!$B$4/100)) -> 0 | X53: =S53*(1+'Pricing Policies'!$C$6/100)*'Pricing Policies'!$E$4*IF($C53="TRF",1,(1+Markups!$B$4/100)) -> 0 | Y53: =S53*(1+'Pricing Policies'!$C$6/100)*'Pricing Policies'!$F$4*IF($C53="TRF",1,(1+Markups!$B$4/100)) -> 0 | Z53: =S53*(1+'Pricing Policies'!$C$7/100)*'Pricing Policies'!$D$4*IF($C53="TRF",1,(1+Markups!$B$4/100)) -> 0 | AA53: =S53*(1+'Pricing Policies'!$C$7/100)*'Pricing Policies'!$E$4*IF($C53="TRF",1,(1+Markups!$B$4/100)) -> 0 | AB53: =S53*(1+'Pricing Policies'!$C$7/100)*'Pricing Policies'!$F$4*IF($C53="TRF",1,(1+Markups!$B$4/100)) -> 0 | AC53: =AC$2 -> 2 | AD53: =AC53*K53 -> 0 | AE53: =AD53*(1+'Pricing Policies'!$C$12/100)*'Pricing Policies'!$D$11 -> 0 | AF53: =AD53*(1+'Pricing Policies'!$C$12/100)*'Pricing Policies'!$E$11 -> 0 | AG53: =AD53*(1+'Pricing Policies'!$C$12/100)*'Pricing Policies'!$F$11 -> 0 | AH53: =AD53*(1+'Pricing Policies'!$C$13/100)*'Pricing Policies'!$D$11 -> 0 | AI53: =AD53*(1+'Pricing Policies'!$C$13/100)*'Pricing Policies'!$E$11 -> 0 | AJ53: =AD53*(1+'Pricing Policies'!$C$13/100)*'Pricing Policies'!$F$11 -> 0 | AK53: =AD53*(1+'Pricing Policies'!$C$14/100)*'Pricing Policies'!$D$11 -> 0 | AL53: =AD53*(1+'Pricing Policies'!$C$14/100)*'Pricing Policies'!$E$11 -> 0 | AM53: =AD53*(1+'Pricing Policies'!$C$14/100)*'Pricing Policies'!$F$11 -> 0 | AN53: =(T$2*T53+U$2*U53+V$2*V53+W$2*W53+X$2*X53+Y$2*Y53+Z$2*Z53+AA$2*AA53+AB$2*AB53) -> 0 | AO53: =(AE$2*AE53+AF$2*AF53+AG$2*AG53+AH$2*AH53+AI$2*AI53+AJ$2*AJ53+AK$2*AK53+AL$2*AL53+AM$2*AM53) -> 0 | AQ53: =AN53+AO53 -> 0 | AR53: =AR$2 -> 0.1 | AS53: =AQ53*AR53 -> 0 | AT53: =AT$2 -> 0.05 | AU53: =(AQ53+AS53)*AT53 -> 0 | AW53: =AQ53+AS53+AU53 -> 0 | AX53: =AW53-AU53-AS53-AD53 -> 0 | AY53: =AX53*AY$2 -> 0 | AZ53: =AY53/D53 -> #DIV/0!
M54: =(E54)*'Base Operating Costs'!$B$13 -> 0 | N54: =(E54)*'Base Operating Costs'!$B$14 -> 0 | O54: ='Base Operating Costs'!$B$15*(E54) -> 0 | P54: =D54*'Base Operating Costs'!$B$4 -> 0 | Q54: =F54 | S54: =M54+N54+O54+P54+Q54 -> 0 | T54: =S54*(1+'Pricing Policies'!$C$5/100)*'Pricing Policies'!$D$4*IF($C54="TRF",1,(1+Markups!$B$4/100)) -> 0 | U54: =S54*(1+'Pricing Policies'!$C$5/100)*'Pricing Policies'!$E$4*IF($C54="TRF",1,(1+Markups!$B$4/100)) -> 0 | V54: =S54*(1+'Pricing Policies'!$C$5/100)*'Pricing Policies'!$F$4*IF($C54="TRF",1,(1+Markups!$B$4/100)) -> 0 | W54: =S54*(1+'Pricing Policies'!$C$6/100)*'Pricing Policies'!$D$4*IF($C54="TRF",1,(1+Markups!$B$4/100)) -> 0 | X54: =S54*(1+'Pricing Policies'!$C$6/100)*'Pricing Policies'!$E$4*IF($C54="TRF",1,(1+Markups!$B$4/100)) -> 0 | Y54: =S54*(1+'Pricing Policies'!$C$6/100)*'Pricing Policies'!$F$4*IF($C54="TRF",1,(1+Markups!$B$4/100)) -> 0 | Z54: =S54*(1+'Pricing Policies'!$C$7/100)*'Pricing Policies'!$D$4*IF($C54="TRF",1,(1+Markups!$B$4/100)) -> 0 | AA54: =S54*(1+'Pricing Policies'!$C$7/100)*'Pricing Policies'!$E$4*IF($C54="TRF",1,(1+Markups!$B$4/100)) -> 0 | AB54: =S54*(1+'Pricing Policies'!$C$7/100)*'Pricing Policies'!$F$4*IF($C54="TRF",1,(1+Markups!$B$4/100)) -> 0 | AC54: =AC$2 -> 2 | AD54: =AC54*K54 -> 0 | AE54: =AD54*(1+'Pricing Policies'!$C$12/100)*'Pricing Policies'!$D$11 -> 0 | AF54: =AD54*(1+'Pricing Policies'!$C$12/100)*'Pricing Policies'!$E$11 -> 0 | AG54: =AD54*(1+'Pricing Policies'!$C$12/100)*'Pricing Policies'!$F$11 -> 0 | AH54: =AD54*(1+'Pricing Policies'!$C$13/100)*'Pricing Policies'!$D$11 -> 0 | AI54: =AD54*(1+'Pricing Policies'!$C$13/100)*'Pricing Policies'!$E$11 -> 0 | AJ54: =AD54*(1+'Pricing Policies'!$C$13/100)*'Pricing Policies'!$F$11 -> 0 | AK54: =AD54*(1+'Pricing Policies'!$C$14/100)*'Pricing Policies'!$D$11 -> 0 | AL54: =AD54*(1+'Pricing Policies'!$C$14/100)*'Pricing Policies'!$E$11 -> 0 | AM54: =AD54*(1+'Pricing Policies'!$C$14/100)*'Pricing Policies'!$F$11 -> 0 | AN54: =(T$2*T54+U$2*U54+V$2*V54+W$2*W54+X$2*X54+Y$2*Y54+Z$2*Z54+AA$2*AA54+AB$2*AB54) -> 0 | AO54: =(AE$2*AE54+AF$2*AF54+AG$2*AG54+AH$2*AH54+AI$2*AI54+AJ$2*AJ54+AK$2*AK54+AL$2*AL54+AM$2*AM54) -> 0 | AQ54: =AN54+AO54 -> 0 | AR54: =AR$2 -> 0.1 | AS54: =AQ54*AR54 -> 0 | AT54: =AT$2 -> 0.05 | AU54: =(AQ54+AS54)*AT54 -> 0 | AW54: =AQ54+AS54+AU54 -> 0 | AX54: =AW54-AU54-AS54-AD54 -> 0 | AY54: =AX54*AY$2 -> 0 | AZ54: =AY54/D54 -> #DIV/0!

Sheet Settings
A1: Aliquota IVA % | C1: Card fees | E1: Extra Fees
A2: 0.1 | C2: 0 | E2: 0
A3: 0.22 | C3: 0.01 | E3: 0.05
C4: 0.02 | E4: 0.1
C5: 0.03 | E5: 0.15
C6: 0.04 | E6: 0.2
C7: 0.05 | E7: 0.25
C8: 0.06 | E8: 0.3
C9: 0.07 | E9: 0.35
C10: 0.08 | E10: 0.4
E11: 0.45
E12: 0.5

Sheet Vehicle Depreciation
A1: YEAR | B1: % YEAR DEPRECIATION | C1: RESIDUAL VALUE | D1: € DEPRECIATION | E1: USAGE | F1: EXPRECTED LIFESPAN | G1: RESIDUAL BEFORE SELLING | I1: DEPRECIATION PER KM BEFORE SELLING
A2: 0 | B2: 0.22 | C2: ='Vehicle Assumptions'!B3/(1+'Vehicle Depreciation'!B2) -> 55327.869 | D2: ='Vehicle Assumptions'!B3-'Vehicle Depreciation'!C2 -> 12172.131
A3: 1 | B3: 0.2 | C3: =C2*(1-B3) -> 44262.295 | D3: =C3-C4 -> 8852.459 | E3: ='Vehicle Assumptions'!B$8 -> 80000 | F3: =IF(E3<='Vehicle Assumptions'!B$5,1,0) -> 1 | G3: =C3*F3 -> 44262.295 | H3: =(D2+D3)/'Vehicle Assumptions'!B$8 -> 0.26280738 | I3: =F3*H3 -> 0.26280738
A4: 2 | B4: 0.2 | C4: =C3*(1-B4) -> 35409.836 | D4: =C4-C5 -> 7081.9672 | E4: =E3+'Vehicle Assumptions'!B$8 -> 160000 | F4: =IF(E4<='Vehicle Assumptions'!B$5,1,0) -> 1 | G4: =C4*F4 -> 35409.836 | H4: =(D4)/'Vehicle Assumptions'!B$8 -> 0.08852459 | I4: =F4*H4 -> 0.08852459
A5: 3 | B5: 0.2 | C5: =C4*(1-B5) -> 28327.869 | D5: =C5-C6 -> 5665.5738 | E5: =E4+'Vehicle Assumptions'!B$8 -> 240000 | F5: =IF(E5<='Vehicle Assumptions'!B$5,1,0) -> 1 | G5: =C5*F5 -> 28327.869 | H5: =(D5)/'Vehicle Assumptions'!B$8 -> 0.070819672 | I5: =F5*H5 -> 0.070819672
A6: 4 | B6: 0.2 | C6: =C5*(1-B6) -> 22662.295 | D6: =C6-C7 -> 4532.459 | E6: =E5+'Vehicle Assumptions'!B$8 -> 320000 | F6: =IF(E6<='Vehicle Assumptions'!B$5,1,0) -> 0 | G6: =C6*F6 -> 0 | H6: =(D6)/'Vehicle Assumptions'!B$8 -> 0.056655738 | I6: =F6*H6 -> 0
A7: 5 | B7: 0.2 | C7: =C6*(1-B7) -> 18129.836 | D7: =C7-C8 -> 3625.9672 | E7: =E6+'Vehicle Assumptions'!B$8 -> 400000 | F7: =IF(E7<='Vehicle Assumptions'!B$5,1,0) -> 0 | G7: =C7*F7 -> 0 | H7: =(D7)/'Vehicle Assumptions'!B$8 -> 0.04532459 | I7: =F7*H7 -> 0
A8: 6 | B8: 0.2 | C8: =C7*(1-B8) -> 14503.869 | D8: =C8-C9 -> 2900.7738 | E8: =E7+'Vehicle Assumptions'!B$8 -> 480000 | F8: =IF(E8<='Vehicle Assumptions'!B$5,1,0) -> 0 | G8: =C8*F8 -> 0 | H8: =(D8)/'Vehicle Assumptions'!B$8 -> 0.036259672 | I8: =F8*H8 -> 0
A9: 7 | B9: 0.2 | C9: =C8*(1-B9) -> 11603.095 | D9: =C9-C10 -> 2320.619 | E9: =E8+'Vehicle Assumptions'!B$8 -> 560000 | F9: =IF(E9<='Vehicle Assumptions'!B$5,1,0) -> 0 | G9: =C9*F9 -> 0 | H9: =(D9)/'Vehicle Assumptions'!B$8 -> 0.029007738 | I9: =F9*H9 -> 0
A10: 8 | B10: 0.2 | C10: =C9*(1-B10) -> 9282.4761 | D10: =C10-C11 -> 1856.4952 | E10: =E9+'Vehicle Assumptions'!B$8 -> 640000 | F10: =IF(E10<='Vehicle Assumptions'!B$5,1,0) -> 0 | G10: =C10*F10 -> 0 | H10: =(D10)/'Vehicle Assumptions'!B$8 -> 0.02320619 | I10: =F10*H10 -> 0
A11: 9 | B11: 0.2 | C11: =C10*(1-B11) -> 7425.9809 | D11: =C11-C12 -> 1485.1962 | E11: =E10+'Vehicle Assumptions'!B$8 -> 720000 | F11: =IF(E11<='Vehicle Assumptions'!B$5,1,0) -> 0 | G11: =C11*F11 -> 0 | H11: =(D11)/'Vehicle Assumptions'!B$8 -> 0.018564952 | I11: =F11*H11 -> 0
A12: 10 | B12: 0.2 | C12: =C11*(1-B12) -> 5940.7847 | D12: =C12-C13 -> 5940.7847 | E12: =E11+'Vehicle Assumptions'!B$8 -> 800000 | F12: =IF(E12<='Vehicle Assumptions'!B$5,1,0) -> 0 | G12: =C12*F12 -> 0 | H12: =(D12)/'Vehicle Assumptions'!B$8 -> 0.074259809 | I12: =F12*H12 -> 0
